Workbook

Sheet description
A1: Name | B1: Desc
A2: {=TRANSPOSE(tmdb_5000_movies!A1:Y1)} -> budget | B2: Biaya pembuatan
A3: genres | B3: Genre film (data mentah)
A4: genre_1 | B4: Genre film 1
A5: genre_2 | B5: Genre film 2
A6: genre_3 | B6: Genre film 3
A7: genre_4 | B7: Genre film 4
A8: homepage | B8: link halaman film
A9: id | B9: id film
A10: Title
A11: keywords | B11: keyword untuk film tersebut
A12: original_language | B12: bahasa yang digunakan
A13: overview | B13: gambaran singkat soal film tersebut
A14: popularity | B14: seberapa populer film ini
A15: production_companies | B15: perusahaan pembuat film ini
A16: Companies
A17: production_countries | B17: lokasi pembuatan film ini
A18: release_date | B18: tanggal rilis
A19: Year
A20: revenue | B20: estimasi yang didapatkan
A21: runtime | B21: durasi film (dalam menit)
A22: spoken_languages | B22: bahasa yang digunakan (serapan)
A23: status | B23: status film
A24: tagline | B24: tagline dari film tersebut
A25: vote_average | B25: rata-rata nilai vote
A26: vote_count | B26: jumlah yang vote
A27: profit

Sheet tes_dashboard

Sheet pivot
A1: genre_1 | B1: (All) | G1: genre_1 | H1: (All) | L1: Companies | M1: Universal Pictures
P2: popularity
A3: Companies | B3: Total Profit | C3: Total Budget | G3: Companies | H3: Total Popularity | L3: Row Labels | M3: Total Profit | N3: Total Popularity | R3: Berdasarkan total profit, paramount pictures menduduki posisi pertama yang diikuti oleh universal pictures dengan selisih pendapatan profit sebesar $ 452.121.987 namun
A4: Paramount Pictures | B4: 25082067469 | C4: 11989862948 | G4: Universal Pictures | H4: 7104638114 | L4: Minions | M4: 1082730962 | N4: 0.48517361 | P4: =GETPIVOTDATA("popularity",$G$3,"Companies","Universal Pictures")-GETPIVOTDATA("popularity",$G$3,"Companies","Paramount Pictures") -> 13176408 | R4: universal pictures menggunakan budget yang lebih sedikit dibandingkan paramount pictures yaitu selisih $ 1.866.434.296. Dari sini universal pictures mendapatkan
A5: Universal Pictures | B5: 24629945482 | C5: 10123428652 | G5: Paramount Pictures | H5: 7091461706 | L5: Despicable Me 2 | M5: 894761885 | N5: 0.075851113 | R5: keuntungan sebesar 24% dibandingkan dengan paramount pictures meskipun berada diurutan kedua berdasarkan profit yang diperoleh
A6: Walt Disney Pictures | B6: 19204470467 | C6: 9201780000 | G6: Columbia Pictures | H6: 5414298750 | L6: Lucy | M6: 86546825 | N6: 0.063857435
A7: Columbia Pictures | B7: 17670376626 | C7: 10192774736 | G7: Twentieth Century Fox Film Corporation | H7: 4780385911 | L7: Despicable Me | M7: 474513985 | N7: 0.063090691 | V7: =GETPIVOTDATA("Total Profit",$A$3,"Companies","Paramount Pictures")-GETPIVOTDATA("Total Profit",$A$3,"Companies","Universal Pictures") -> 452121987
A8: Twentieth Century Fox Film Corporation | B8: 16242464696 | C8: 6876440000 | G8: Walt Disney Pictures | H8: 4167392867 | L8: Bruce Almighty | M8: 404572835 | N8: 0.060778096 | R8: Berdasarkan analisis sebelumnya saya melanjutkan untuk mencari tahu apakah terdapat hubungan dengan popularitas yang diperoleh suatu company. Berdasarkan gambar diatas | V8: 452121987
A9: New Line Cinema | B9: 8552172273 | C9: 4641485000 | G9: New Line Cinema | H9: 3226314325 | L9: Schindler's List | M9: 299365567 | N9: 0.057888139 | R9: dapat dilihat bahwa universal pictures memiliki popularity 13.176.408 lebih banyak dari paramount pictures, hal ini berarti total popularitas yang diperoleh film suatu company tidak
A10: Village Roadshow Pictures | B10: 6951254238 | C10: 4867800003 | G10: Village Roadshow Pictures | H10: 2257235739 | L10: Furious 7 | M10: 1316249360 | N10: 0.056698378 | R10: bergantung dengan total profit yang diperoleh | V10: =GETPIVOTDATA("Total Budget",$A$3,"Companies","Paramount Pictures")-GETPIVOTDATA("Total Budget",$A$3,"Companies","Universal Pictures") -> 1866434296
A11: DreamWorks SKG | B11: 6298102144 | C11: 3081500000 | G11: Summit Entertainment | H11: 1610148976 | L11: The Bourne Identity | M11: 154034224 | N11: 0.047918188
A12: Lucasfilm | B12: 5810309700 | C12: 796427000 | G12: Miramax Films | H12: 1513740164 | L12: The Purge: Anarchy | M12: 99782847 | N12: 0.045978241 | R12: Popularitas film tertinggi yang diproduksi oleh universal pictures adala "Minions" meskipun profit yang diperolah lebih besar "Furious 7". Film "Minions" menyumbang | T12: =GETPIVOTDATA("Total Popularity",$L$3)/GETPIVOTDATA("popularity",$G$3,"Companies","Universal Pictures") -> 1.4075312e-10
A13: Marvel Studios | B13: 5551826201 | C13: 1750000000 | G13: DreamWorks SKG | H13: 1427649268 | L13: Snow White and the Huntsman | M13: 226600000 | N13: 0.042766104 | R13: sebesar 12,32% dari seluruh total popularitas yang diperoleh universal pictures. Sedangkan untuk urutan top 10, "Minions" memberikan kontribusi sebesar 48,52%, hal ini menunjukkan | V13: =V7/V10 -> 0.24223836
A14: Grand Total | B14: 135992989296 | C14: 63521498339 | G14: Grand Total | H14: 38593265820 | L14: Grand Total | M14: 5039158490 | N14: 1 | R14: bahwa "Minions" memberikan kontribusi yang sangat besar terhadap popularitas yang diperoleh universal pictures
A16: Companies | B16: Paramount Pictures
D17: Companies | E17: Paramount Pictures
A18: Row Labels | B18: Sum of Profit
A19: Action | B19: 5358895700 | D19: Sum of Profit | E19: Column Labels
A20: Drama | B20: 4706520363 | D20: Row Labels | E20: Action | F20: Grand Total
A21: Science Fiction | B21: 4102301748 | D21: Transformers: Dark of the Moon | E21: 928746996 | F21: 928746996
A22: Adventure | B22: 3584612644 | D22: Mission: Impossible - Ghost Protocol | E22: 549713380 | F22: 549713380
A23: Comedy | B23: 3164373506 | D23: Mission: Impossible - Rogue Nation | E23: 532330139 | F23: 532330139
A24: Fantasy | B24: 948469419 | D24: Top Gun | E24: 341830601 | F24: 341830601
A25: Crime | B25: 850466534 | D25: World War Z | E25: 331865000 | F25: 331865000
A26: Horror | B26: 843244359 | D26: Beverly Hills Cop | E26: 301360478 | F26: 301360478
A27: Thriller | B27: 690221099 | D27: Beverly Hills Cop II | E27: 279965036 | F27: 279965036
A28: Animation | B28: 480259427 | D28: Star Trek Into Darkness | E28: 277365246 | F28: 277365246
A29: Romance | B29: 162428050 | D29: The Hunt for Red October | E29: 169200000 | F29: 169200000
A30: Music | B30: 128113269 | D30: The Last Airbender | E30: 168502923 | F30: 168502923
A31: Documentary | B31: 80009268 | D31: Face/Off | E31: 165676146 | F31: 165676146
A32: War | B32: 30770585 | D32: Star Trek Beyond | E32: 158471816 | F32: 158471816
... A37: Grand Total | B37: 25082067469 | D37: Beverly Hills Cop III | E37: 69208989 | F37: 69208989
D38: Deep Impact | E38: 65464664 | F38: 65464664
D39: Jackass Number Two | E39: 61778712 | F39: 61778712
D40: Lara Croft Tomb Raider: The Cradle of Life | E40: 61505388 | F40: 61505388
D41: Shaft | E41: 61196498 | F41: 61196498
D42: Watchmen | E42: 55258983 | F42: 55258983
D43: The Golden Child | E43: 54817939 | F43: 54817939
D44: Without a Paddle | E44: 50631118 | F44: 50631118
D45: Changing Lanes | E45: 49935764 | F45: 49935764
D46: Crossroads | E46: 49141030 | F46: 49141030
D47: Four Brothers | E47: 47374674 | F47: 47374674
D48: Paycheck | E48: 36269812 | F48: 36269812
D49: Shooter | E49: 34696996 | F49: 34696996
... D70: Grand Total | E70: 5358895700 | F70: 5358895700

Sheet tmdb_5000_movies
A1: budget | B1: genres | C1: genre_1 | D1: genre_2 | E1: genre_3 | F1: genre_4 | G1: homepage | H1: id | I1: Title | J1: keywords | K1: original_language | L1: overview | M1: popularity | N1: production_companies | O1: Companies | P1: production_countries | Q1: release_date | R1: Year | S1: revenue | T1: runtime | U1: spoken_languages | V1: status | W1: tagline | X1: vote_average | Y1: vote_count | Z1: Profit
A2: 237000000 | B2: [{ 28, name: Action}, { 12, name: Adventure}, { 14, name: Fantasy}, { 878, name: Science Fiction}] | C2: Action | D2: Adventure | E2: Fantasy | F2: Science Fiction | G2: http://www.avatarmovie.com/ | H2: 19995 | I2: Avatar | J2: [{"id": 1463, "name": "culture clash"}, {"id": 2964, "name": "future"}, {"id": 3386, "name": "space war"}, {"id": 3388, "name": "space colony"}, {"id": 3679, "name": "society"}, {"id": 3801, "name": "space travel"}, {"id": 9685, "name": "futuristic"}, {"id": 9840, "name": "romance"}, {"id": 9882, "name": "space"}, {"id": 9951, "name": "alien"}, {"id": 10148, "name": "tribe"}, {"id": 10158, "name": "alien planet"}, {"id": 10987, "name": "cgi"}, {"id": 11399, "name": "marine"}, {"id": 13065, "name": "soldier"}, {"id": 14643, "name": "battle"}, {"id": 14720, "name": "love affair"}, {"id": 165431, "name": "anti war"}, {"id": 193554, "name": "power relations"}, {"id": 206690, "name": "mind and soul"}, {"id": 209714, "name": "3d"}] | K2: en | L2: In the 22nd century, a paraplegic Marine is dispatched to the moon Pandora on a unique mission, but becomes torn between following orders and protecting an alien civilization. | M2: 150437577 | N2: [{"name": "Ingenious Film Partners", "id": 289}, {"name": "Twentieth Century Fox Film Corporation", "id": 306}, {"name": "Dune Entertainment", "id": 444}, {"name": "Lightstorm Entertainment", "id": 574}] | O2: Ingenious Film Partners | P2: [{"iso_3166_1": "US", "name": "United States of America"}, {"iso_3166_1": "GB", "name": "United Kingdom"}] | Q2: 40157 | R2: 2009 | S2: 2787965087 | T2: 162 | U2: [{"iso_639_1": "en", "name": "English"}, {"iso_639_1": "es", "name": "Espa\u00f1ol"}] | V2: Released | W2: Enter the World of Pandora. | X2: 7.2 | Y2: 11800 | Z2: 2550965087
A3: 300000000 | B3: [{ 12, name: Adventure}, { 14, name: Fantasy}, { 28, name: Action}] | C3: Adventure | D3: Fantasy | E3: Action | F3: - | G3: http://disney.go.com/disneypictures/pirates/ | H3: 285 | I3: Pirates of the Caribbean: At World's End | J3: [{"id": 270, "name": "ocean"}, {"id": 726, "name": "drug abuse"}, {"id": 911, "name": "exotic island"}, {"id": 1319, "name": "east india trading company"}, {"id": 2038, "name": "love of one's life"}, {"id": 2052, "name": "traitor"}, {"id": 2580, "name": "shipwreck"}, {"id": 2660, "name": "strong woman"}, {"id": 3799, "name": "ship"}, {"id": 5740, "name": "alliance"}, {"id": 5941, "name": "calypso"}, {"id": 6155, "name": "afterlife"}, {"id": 6211, "name": "fighter"}, {"id": 12988, "name": "pirate"}, {"id": 157186, "name": "swashbuckler"}, {"id": 179430, "name": "aftercreditsstinger"}] | K3: en | L3: Captain Barbossa, long believed to be dead, has come back to life and is headed to the edge of the Earth with Will Turner and Elizabeth Swann. But nothing is quite as it seems. | M3: 139082615 | N3: [{"name": "Walt Disney Pictures", "id": 2}, {"name": "Jerry Bruckheimer Films", "id": 130}, {"name": "Second Mate Productions", "id": 19936}] | O3: Walt Disney Pictures | P3: [{"iso_3166_1": "US", "name": "United States of America"}] | Q3: 39221 | R3: 2007 | S3: 961000000 | T3: 169 | U3: [{"iso_639_1": "en", "name": "English"}] | V3: Released | W3: At the end of the world, the adventure begins. | X3: 6.9 | Y3: 4500 | Z3: 661000000
A4: 245000000 | B4: [{ 28, name: Action}, { 12, name: Adventure}, { 80, name: Crime}] | C4: Action | D4: Adventure | E4: Crime | F4: - | G4: http://www.sonypictures.com/movies/spectre/ | H4: 206647 | I4: Spectre | J4: [{"id": 470, "name": "spy"}, {"id": 818, "name": "based on novel"}, {"id": 4289, "name": "secret agent"}, {"id": 9663, "name": "sequel"}, {"id": 14555, "name": "mi6"}, {"id": 156095, "name": "british secret service"}, {"id": 158431, "name": "united kingdom"}] | K4: en | L4: A cryptic message from Bondâ€™s past sends him on a trail to uncover a sinister organization. While M battles political forces to keep the secret service alive, Bond peels back the layers of deceit to reveal the terrible truth behind SPECTRE. | M4: 107376788 | N4: [{"name": "Columbia Pictures", "id": 5}, {"name": "Danjaq", "id": 10761}, {"name": "B24", "id": 69434}] | O4: Columbia Pictures | P4: [{"iso_3166_1": "GB", "name": "United Kingdom"}, {"iso_3166_1": "US", "name": "United States of America"}] | Q4: 42303 | R4: 2015 | S4: 880674609 | T4: 148 | U4: [{"iso_639_1": "fr", "name": "Fran\u00e7ais"}, {"iso_639_1": "en", "name": "English"}, {"iso_639_1": "es", "name": "Espa\u00f1ol"}, {"iso_639_1": "it", "name": "Italiano"}, {"iso_639_1": "de", "name": "Deutsch"}] | V4: Released | W4: A Plan No One Escapes | X4: 6.3 | Y4: 4466 | Z4: 635674609
A5: 250000000 | B5: [{ 28, name: Action}, { 80, name: Crime}, { 18, name: Drama}, { 53, name: Thriller}] | C5: Action | D5: Crime | E5: Drama | F5: Thriller | G5: http://www.thedarkknightrises.com/ | H5: 49026 | I5: The Dark Knight Rises | J5: [{"id": 849, "name": "dc comics"}, {"id": 853, "name": "crime fighter"}, {"id": 949, "name": "terrorist"}, {"id": 1308, "name": "secret identity"}, {"id": 1437, "name": "burglar"}, {"id": 3051, "name": "hostage drama"}, {"id": 3562, "name": "time bomb"}, {"id": 6969, "name": "gotham city"}, {"id": 7002, "name": "vigilante"}, {"id": 9665, "name": "cover-up"}, {"id": 9715, "name": "superhero"}, {"id": 9990, "name": "villainess"}, {"id": 10044, "name": "tragic hero"}, {"id": 13015, "name": "terrorism"}, {"id": 14796, "name": "destruction"}, {"id": 18933, "name": "catwoman"}, {"id": 156082, "name": "cat burglar"}, {"id": 156395, "name": "imax"}, {"id": 173272, "name": "flood"}, {"id": 179093, "name": "criminal underworld"}, {"id": 230775, "name": "batman"}] | K5: en | L5: Following the death of District Attorney Harvey Dent, Batman assumes responsibility for Dent's crimes to protect the late attorney's reputation and is subsequently hunted by the Gotham City Police Department. Eight years later, Batman encounters the mysterious Selina Kyle and the villainous Bane, a new terrorist leader who overwhelms Gotham's finest. The Dark Knight resurfaces to protect a city that has branded him an enemy. | M5: 11231295 | N5: [{"name": "Legendary Pictures", "id": 923}, {"name": "Warner Bros.", "id": 6194}, {"name": "DC Entertainment", "id": 9993}, {"name": "Syncopy", "id": 9996}] | O5: Legendary Pictures | P5: [{"iso_3166_1": "US", "name": "United States of America"}] | Q5: 41106 | R5: 2012 | S5: 1084939099 | T5: 165 | U5: [{"iso_639_1": "en", "name": "English"}] | V5: Released | W5: The Legend Ends | X5: 7.6 | Y5: 9106 | Z5: 834939099
A6: 260000000 | B6: [{ 28, name: Action}, { 12, name: Adventure}, { 878, name: Science Fiction}] | C6: Action | D6: Adventure | E6: Science Fiction | F6: - | G6: http://movies.disney.com/john-carter | H6: 49529 | I6: John Carter | J6: [{"id": 818, "name": "based on novel"}, {"id": 839, "name": "mars"}, {"id": 1456, "name": "medallion"}, {"id": 3801, "name": "space travel"}, {"id": 7376, "name": "princess"}, {"id": 9951, "name": "alien"}, {"id": 10028, "name": "steampunk"}, {"id": 10539, "name": "martian"}, {"id": 10685, "name": "escape"}, {"id": 161511, "name": "edgar rice burroughs"}, {"id": 163252, "name": "alien race"}, {"id": 179102, "name": "superhuman strength"}, {"id": 190320, "name": "mars civilization"}, {"id": 195446, "name": "sword and planet"}, {"id": 207928, "name": "19th century"}, {"id": 209714, "name": "3d"}] | K6: en | L6: John Carter is a war-weary, former military captain who's inexplicably transported to the mysterious and exotic planet of Barsoom (Mars) and reluctantly becomes embroiled in an epic conflict. It's a world on the brink of collapse, and Carter rediscovers his humanity when he realizes the survival of Barsoom and its people rests in his hands. | M6: 43926995 | N6: [{"name": "Walt Disney Pictures", "id": 2}] | O6: Walt Disney Pictures | P6: [{"iso_3166_1": "US", "name": "United States of America"}] | Q6: 40975 | R6: 2012 | S6: 284139100 | T6: 132 | U6: [{"iso_639_1": "en", "name": "English"}] | V6: Released | W6: Lost in our world, found in another. | X6: 6.1 | Y6: 2124 | Z6: 24139100
A7: 258000000 | B7: [{ 14, name: Fantasy}, { 28, name: Action}, { 12, name: Adventure}] | C7: Fantasy | D7: Action | E7: Adventure | F7: - | G7: http://www.sonypictures.com/movies/spider-man3/ | H7: 559 | I7: Spider-Man 3 | J7: [{"id": 851, "name": "dual identity"}, {"id": 1453, "name": "amnesia"}, {"id": 1965, "name": "sandstorm"}, {"id": 2038, "name": "love of one's life"}, {"id": 3446, "name": "forgiveness"}, {"id": 3986, "name": "spider"}, {"id": 4391, "name": "wretch"}, {"id": 4959, "name": "death of a friend"}, {"id": 5776, "name": "egomania"}, {"id": 5789, "name": "sand"}, {"id": 5857, "name": "narcism"}, {"id": 6062, "name": "hostility"}, {"id": 8828, "name": "marvel comic"}, {"id": 9663, "name": "sequel"}, {"id": 9715, "name": "superhero"}, {"id": 9748, "name": "revenge"}] | K7: en | L7: The seemingly invincible Spider-Man goes up against an all-new crop of villain â€“ including the shape-shifting Sandman. While Spider-Manâ€™s superpowers are altered by an alien organism, his alter ego, Peter Parker, deals with nemesis Eddie Brock and also gets caught up in a love triangle. | M7: 115699814 | N7: [{"name": "Columbia Pictures", "id": 5}, {"name": "Laura Ziskin Productions", "id": 326}, {"name": "Marvel Enterprises", "id": 19551}] | O7: Columbia Pictures | P7: [{"iso_3166_1": "US", "name": "United States of America"}] | Q7: 39203 | R7: 2007 | S7: 890871626 | T7: 139 | U7: [{"iso_639_1": "en", "name": "English"}, {"iso_639_1": "fr", "name": "Fran\u00e7ais"}] | V7: Released | W7: The battle within. | X7: 5.9 | Y7: 3576 | Z7: 632871626
A8: 260000000 | B8: [{ 16, name: Animation}, { 10751, name: Family}] | C8: Animation | D8: Family | E8: - | F8: - | G8: http://disney.go.com/disneypictures/tangled/ | H8: 38757 | I8: Tangled | J8: [{"id": 1562, "name": "hostage"}, {"id": 2343, "name": "magic"}, {"id": 2673, "name": "horse"}, {"id": 3205, "name": "fairy tale"}, {"id": 4344, "name": "musical"}, {"id": 7376, "name": "princess"}, {"id": 10336, "name": "animation"}, {"id": 33787, "name": "tower"}, {"id": 155658, "name": "blonde woman"}, {"id": 162219, "name": "selfishness"}, {"id": 163545, "name": "healing power"}, {"id": 179411, "name": "based on fairy tale"}, {"id": 179431, "name": "duringcreditsstinger"}, {"id": 215258, "name": "healing gift"}, {"id": 234183, "name": "animal sidekick"}] | K8: en | L8: When the kingdom's most wanted-and most charming-bandit Flynn Rider hides out in a mysterious tower, he's taken hostage by Rapunzel, a beautiful and feisty tower-bound teen with 70 feet of magical, golden hair. Flynn's curious captor, who's looking for her ticket out of the tower where she's been locked away for years, strikes a deal with the handsome thief and the unlikely duo sets off on an action-packed escapade, complete with a super-cop horse, an over-protective chameleon and a gruff gang of pub thugs. | M8: 48681969 | N8: [{"name": "Walt Disney Pictures", "id": 2}, {"name": "Walt Disney Animation Studios", "id": 6125}] | O8: Walt Disney Pictures | P8: [{"iso_3166_1": "US", "name": "United States of America"}] | Q8: 40506 | R8: 2010 | S8: 591794936 | T8: 100 | U8: [{"iso_639_1": "en", "name": "English"}] | V8: Released | W8: They're taking adventure to new lengths. | X8: 7.4 | Y8: 3330 | Z8: 331794936
A9: 280000000 | B9: [{ 28, name: Action}, { 12, name: Adventure}, { 878, name: Science Fiction}] | C9: Action | D9: Adventure | E9: Science Fiction | F9: - | G9: http://marvel.com/movies/movie/193/avengers_age_of_ultron | H9: 99861 | I9: Avengers: Age of Ultron | J9: [{"id": 8828, "name": "marvel comic"}, {"id": 9663, "name": "sequel"}, {"id": 9715, "name": "superhero"}, {"id": 9717, "name": "based on comic book"}, {"id": 10629, "name": "vision"}, {"id": 155030, "name": "superhero team"}, {"id": 179431, "name": "duringcreditsstinger"}, {"id": 180547, "name": "marvel cinematic universe"}, {"id": 209714, "name": "3d"}] | K9: en | L9: When Tony Stark tries to jumpstart a dormant peacekeeping program, things go awry and Earthâ€™s Mightiest Heroes are put to the ultimate test as the fate of the planet hangs in the balance. As the villainous Ultron emerges, it is up to The Avengers to stop him from enacting his terrible plans, and soon uneasy alliances and unexpected action pave the way for an epic and unique global adventure. | M9: 134279229 | N9: [{"name": "Marvel Studios", "id": 420}, {"name": "Prime Focus", "id": 15357}, {"name": "Revolution Sun Studios", "id": 76043}] | O9: Marvel Studios | P9: [{"iso_3166_1": "US", "name": "United States of America"}] | Q9: 42116 | R9: 2015 | S9: 1405403694 | T9: 141 | U9: [{"iso_639_1": "en", "name": "English"}] | V9: Released | W9: A New Age Has Come. | X9: 7.3 | Y9: 6767 | Z9: 1125403694
A10: 250000000 | B10: [{ 12, name: Adventure}, { 14, name: Fantasy}, { 10751, name: Family}] | C10: Adventure | D10: Fantasy | E10: Family | F10: - | G10: http://harrypotter.warnerbros.com/harrypotterandthehalf-bloodprince/dvd/index.html | H10: 767 | I10: Harry Potter and the Half-Blood Prince | J10: [{"id": 616, "name": "witch"}, {"id": 2343, "name": "magic"}, {"id": 3872, "name": "broom"}, {"id": 3884, "name": "school of witchcraft"}, {"id": 6333, "name": "wizardry"}, {"id": 10164, "name": "apparition"}, {"id": 10791, "name": "teenage crush"}, {"id": 12564, "name": "werewolf"}] | K10: en | L10: As Harry begins his sixth year at Hogwarts, he discovers an old book marked as 'Property of the Half-Blood Prince', and begins to learn more about Lord Voldemort's dark past. | M10: 98885637 | N10: [{"name": "Warner Bros.", "id": 6194}, {"name": "Heyday Films", "id": 7364}] | O10: Warner Bros. | P10: [{"iso_3166_1": "GB", "name": "United Kingdom"}, {"iso_3166_1": "US", "name": "United States of America"}] | Q10: 40001 | R10: 2009 | S10: 933959197 | T10: 153 | U10: [{"iso_639_1": "en", "name": "English"}] | V10: Released | W10: Dark Secrets Revealed | X10: 7.4 | Y10: 5293 | Z10: 683959197
A11: 250000000 | B11: [{ 28, name: Action}, { 12, name: Adventure}, { 14, name: Fantasy}] | C11: Action | D11: Adventure | E11: Fantasy | F11: - | G11: http://www.batmanvsupermandawnofjustice.com/ | H11: 209112 | I11: Batman v Superman: Dawn of Justice | J11: [{"id": 849, "name": "dc comics"}, {"id": 7002, "name": "vigilante"}, {"id": 9715, "name": "superhero"}, {"id": 9717, "name": "based on comic book"}, {"id": 9748, "name": "revenge"}, {"id": 163455, "name": "super powers"}, {"id": 195242, "name": "clark kent"}, {"id": 195243, "name": "bruce wayne"}, {"id": 229266, "name": "dc extended universe"}] | K11: en | L11: Fearing the actions of a god-like Super Hero left unchecked, Gotham Cityâ€™s own formidable, forceful vigilante takes on Metropolisâ€™s most revered, modern-day savior, while the world wrestles with what sort of hero it really needs. And with Batman and Superman at war with one another, a new threat quickly arises, putting mankind in greater danger than itâ€™s ever known before. | M11: 155790452 | N11: [{"name": "DC Comics", "id": 429}, {"name": "Atlas Entertainment", "id": 507}, {"name": "Warner Bros.", "id": 6194}, {"name": "DC Entertainment", "id": 9993}, {"name": "Cruel & Unusual Films", "id": 9995}, {"name": "RatPac-Dune Entertainment", "id": 41624}] | O11: DC Comics | P11: [{"iso_3166_1": "US", "name": "United States of America"}] | Q11: 42452 | R11: 2016 | S11: 873260194 | T11: 151 | U11: [{"iso_639_1": "en", "name": "English"}] | V11: Released | W11: Justice or revenge | X11: 5.7 | Y11: 7004 | Z11: 623260194
A12: 270000000 | B12: [{ 12, name: Adventure}, { 14, name: Fantasy}, { 28, name: Action}, { 878, name: Science Fiction}] | C12: Adventure | D12: Fantasy | E12: Action | F12: Science Fiction | G12: http://www.superman.com | H12: 1452 | I12: Superman Returns | J12: [{"id": 83, "name": "saving the world"}, {"id": 849, "name": "dc comics"}, {"id": 8872, "name": "invulnerability"}, {"id": 9663, "name": "sequel"}, {"id": 9715, "name": "superhero"}, {"id": 9717, "name": "based on comic book"}, {"id": 163420, "name": "kryptonite"}, {"id": 163455, "name": "super powers"}, {"id": 179102, "name": "superhuman strength"}, {"id": 202526, "name": "lex luthor"}] | K12: en | L12: Superman returns to discover his 5-year absence has allowed Lex Luthor to walk free, and that those he was closest too felt abandoned and have moved on. Luthor plots his ultimate revenge that could see millions killed and change the face of the planet forever, as well as ridding himself of the Man of Steel. | M12: 57925623 | N12: [{"name": "DC Comics", "id": 429}, {"name": "Legendary Pictures", "id": 923}, {"name": "Warner Bros.", "id": 6194}, {"name": "Bad Hat Harry Productions", "id": 9168}] | O12: DC Comics | P12: [{"iso_3166_1": "US", "name": "United States of America"}] | Q12: 38896 | R12: 2006 | S12: 391081192 | T12: 154 | U12: [{"iso_639_1": "en", "name": "English"}, {"iso_639_1": "fr", "name": "Fran\u00e7ais"}, {"iso_639_1": "de", "name": "Deutsch"}] | V12: Released | X12: 5.4 | Y12: 1400 | Z12: 121081192
A13: 200000000 | B13: [{ 12, name: Adventure}, { 28, name: Action}, { 53, name: Thriller}, { 80, name: Crime}] | C13: Adventure | D13: Action | E13: Thriller | F13: Crime | G13: http://www.mgm.com/view/movie/234/Quantum-of-Solace/ | H13: 10764 | I13: Quantum of Solace | J13: [{"id": 627, "name": "killing"}, {"id": 1568, "name": "undercover"}, {"id": 4289, "name": "secret agent"}, {"id": 156095, "name": "british secret service"}] | K13: en | L13: Quantum of Solace continues the adventures of James Bond after Casino Royale. Betrayed by Vesper, the woman he loved, 007 fights the urge to make his latest mission personal. Pursuing his determination to uncover the truth, Bond and M interrogate Mr. White, who reveals that the organization that blackmailed Vesper is far more complex and dangerous than anyone had imagined. | M13: 107928811 | N13: [{"name": "Eon Productions", "id": 7576}] | O13: Eon Productions | P13: [{"iso_3166_1": "GB", "name": "United Kingdom"}, {"iso_3166_1": "US", "name": "United States of America"}] | Q13: 39751 | R13: 2008 | S13: 586090727 | T13: 106 | U13: [{"iso_639_1": "en", "name": "English"}, {"iso_639_1": "es", "name": "Espa\u00f1ol"}, {"iso_639_1": "it", "name": "Italiano"}, {"iso_639_1": "fr", "name": "Fran\u00e7ais"}, {"iso_639_1": "de", "name": "Deutsch"}] | V13: Released | W13: For love, for hate, for justice, for revenge. | X13: 6.1 | Y13: 2965 | Z13: 386090727
A14: 200000000 | B14: [{ 12, name: Adventure}, { 14, name: Fantasy}, { 28, name: Action}] | C14: Adventure | D14: Fantasy | E14: Action | F14: - | G14: http://disney.go.com/disneypictures/pirates/ | H14: 58 | I14: Pirates of the Caribbean: Dead Man's Chest | J14: [{"id": 616, "name": "witch"}, {"id": 663, "name": "fortune teller"}, {"id": 910, "name": "bondage"}, {"id": 911, "name": "exotic island"}, {"id": 1299, "name": "monster"}, {"id": 1316, "name": "captain"}, {"id": 1317, "name": "card game"}, {"id": 1319, "name": "east india trading company"}, {"id": 1461, "name": "compass"}, {"id": 3799, "name": "ship"}, {"id": 5600, "name": "daughter"}, {"id": 12988, "name": "pirate"}, {"id": 157186, "name": "swashbuckler"}, {"id": 179430, "name": "aftercreditsstinger"}] | K14: en | L14: Captain Jack Sparrow works his way out of a blood debt with the ghostly Davey Jones, he also attempts to avoid eternal damnation. | M14: 145847379 | N14: [{"name": "Walt Disney Pictures", "id": 2}, {"name": "Jerry Bruckheimer Films", "id": 130}, {"name": "Second Mate Productions", "id": 19936}] | O14: Walt Disney Pictures | P14: [{"iso_3166_1": "JM", "name": "Jamaica"}, {"iso_3166_1": "US", "name": "United States of America"}, {"iso_3166_1": "BS", "name": "Bahamas"}, {"iso_3166_1": "DM", "name": "Dominica"}] | Q14: 38888 | R14: 2006 | S14: 1065659812 | T14: 151 | U14: [{"iso_639_1": "en", "name": "English"}, {"iso_639_1": "tr", "name": "T\u00fcrk\u00e7e"}, {"iso_639_1": "el", "name": "\u03b5\u03bb\u03bb\u03b7\u03bd\u03b9\u03ba\u03ac"}, {"iso_639_1": "zh", "name": "\u666e\u901a\u8bdd"}] | V14: Released | W14: Jack is back! | X14: 7.0 | Y14: 5246 | Z14: 865659812
A15: 255000000 | B15: [{ 28, name: Action}, { 12, name: Adventure}, { 37, name: Western}] | C15: Action | D15: Adventure | E15: Western | F15: - | G15: http://disney.go.com/the-lone-ranger/ | H15: 57201 | I15: The Lone Ranger | J15: [{"id": 1556, "name": "texas"}, {"id": 2673, "name": "horse"}, {"id": 5385, "name": "survivor"}, {"id": 5901, "name": "texas ranger"}, {"id": 9104, "name": "partner"}, {"id": 9503, "name": "outlaw"}, {"id": 10685, "name": "escape"}, {"id": 10909, "name": "lawyer"}, {"id": 13008, "name": "train"}, {"id": 178867, "name": "lone ranger"}, {"id": 179419, "name": "comanche"}, {"id": 222787, "name": "the lone ranger"}, {"id": 228232, "name": "tonto"}] | K15: en | L15: The Texas Rangers chase down a gang of outlaws led by Butch Cavendish, but the gang ambushes the Rangers, seemingly killing them all. One survivor is found, however, by an American Indian named Tonto, who nurses him back to health. The Ranger, donning a mask and riding a white stallion named Silver, teams up with Tonto to bring the unscrupulous gang and others of that ilk to justice. | M15: 49046956 | N15: [{"name": "Walt Disney Pictures", "id": 2}, {"name": "Jerry Bruckheimer Films", "id": 130}, {"name": "Infinitum Nihil", "id": 2691}, {"name": "Silver Bullet Productions (II)", "id": 37380}, {"name": "Blind Wink Productions", "id": 37381}, {"name": "Classic Media", "id": 37382}] | O15: Walt Disney Pictures | P15: [{"iso_3166_1": "US", "name": "United States of America"}] | Q15: 41458 | R15: 2013 | S15: 89289910 | T15: 149 | U15: [{"iso_639_1": "en", "name": "English"}] | V15: Released | W15: Never Take Off the Mask | X15: 5.9 | Y15: 2311 | Z15: -165710090
A16: 225000000 | B16: [{ 28, name: Action}, { 12, name: Adventure}, { 14, name: Fantasy}, { 878, name: Science Fiction}] | C16: Action | D16: Adventure | E16: Fantasy | F16: Science Fiction | G16: http://www.manofsteel.com/ | H16: 49521 | I16: Man of Steel | J16: [{"id": 83, "name": "saving the world"}, {"id": 849, "name": "dc comics"}, {"id": 9715, "name": "superhero"}, {"id": 9717, "name": "based on comic book"}, {"id": 10761, "name": "superhuman"}, {"id": 14909, "name": "alien invasion"}, {"id": 161184, "name": "reboot"}, {"id": 163455, "name": "super powers"}, {"id": 229266, "name": "dc extended universe"}] | K16: en | L16: A young boy learns that he has extraordinary powers and is not of this earth. As a young man, he journeys to discover where he came from and what he was sent here to do. But the hero in him must emerge if he is to save the world from annihilation and become the symbol of hope for all mankind. | M16: 99398009 | N16: [{"name": "Legendary Pictures", "id": 923}, {"name": "Warner Bros.", "id": 6194}, {"name": "DC Entertainment", "id": 9993}, {"name": "Syncopy", "id": 9996}, {"name": "Cruel and Unusual Films", "id": 78685}] | O16: Legendary Pictures | P16: [{"iso_3166_1": "GB", "name": "United Kingdom"}, {"iso_3166_1": "US", "name": "United States of America"}] | Q16: 41437 | R16: 2013 | S16: 662845518 | T16: 143 | U16: [{"iso_639_1": "en", "name": "English"}] | V16: Released | W16: You will believe that a man can fly. | X16: 6.5 | Y16: 6359 | Z16: 437845518
A17: 225000000 | B17: [{ 12, name: Adventure}, { 10751, name: Family}, { 14, name: Fantasy}] | C17: Adventure | D17: Family | E17: Fantasy | F17: - | H17: 2454 | I17: The Chronicles of Narnia: Prince Caspian | J17: [{"id": 818, "name": "based on novel"}, {"id": 855, "name": "fictional place"}, {"id": 1155, "name": "brother sister relationship"}, {"id": 2043, "name": "lion"}, {"id": 3714, "name": "human being"}, {"id": 4391, "name": "wretch"}, {"id": 4820, "name": "leap in time"}, {"id": 5144, "name": "matter of life and death"}, {"id": 6150, "name": "faith"}, {"id": 6464, "name": "uncle"}, {"id": 166930, "name": "narnia"}, {"id": 170362, "name": "fantasy world"}] | K17: en | L17: One year after their incredible adventures in the Lion, the Witch and the Wardrobe, Peter, Edmund, Lucy and Susan Pevensie return to Narnia to aid a young prince whose life has been threatened by the evil King Miraz. Now, with the help of a colorful cast of new characters, including Trufflehunter the badger and Nikabrik the dwarf, the Pevensie clan embarks on an incredible quest to ensure that Narnia is returned to its rightful heir. | M17: 53978602 | N17: [{"name": "Walt Disney", "id": 5888}, {"name": "Walden Media", "id": 10221}, {"name": "Stillking Films", "id": 11345}, {"name": "Ozumi Films", "id": 11440}, {"name": "Propeler", "id": 11441}, {"name": "Silverbell Films", "id": 11442}, {"name": "Revolution Sun Studios", "id": 76043}] | O17: Walt Disney | P17: [{"iso_3166_1": "CZ", "name": "Czech Republic"}, {"iso_3166_1": "PL", "name": "Poland"}, {"iso_3166_1": "SI", "name": "Slovenia"}, {"iso_3166_1": "US", "name": "United States of America"}] | Q17: 39583 | R17: 2008 | S17: 419651413 | T17: 150 | U17: [{"iso_639_1": "en", "name": "English"}] | V17: Released | W17: Hope has a new face. | X17: 6.3 | Y17: 1630 | Z17: 194651413
A18: 220000000 | B18: [{ 878, name: Science Fiction}, { 28, name: Action}, { 12, name: Adventure}] | C18: Science Fiction | D18: Action | E18: Adventure | F18: - | G18: http://marvel.com/avengers_movie/ | H18: 24428 | I18: The Avengers | J18: [{"id": 242, "name": "new york"}, {"id": 5539, "name": "shield"}, {"id": 8828, "name": "marvel comic"}, {"id": 9715, "name": "superhero"}, {"id": 9717, "name": "based on comic book"}, {"id": 14909, "name": "alien invasion"}, {"id": 155030, "name": "superhero team"}, {"id": 179430, "name": "aftercreditsstinger"}, {"id": 179431, "name": "duringcreditsstinger"}, {"id": 180547, "name": "marvel cinematic universe"}] | K18: en | L18: When an unexpected enemy emerges and threatens global safety and security, Nick Fury, director of the international peacekeeping agency known as S.H.I.E.L.D., finds himself in need of a team to pull the world back from the brink of disaster. Spanning the globe, a daring recruitment effort begins! | M18: 144448633 | N18: [{"name": "Paramount Pictures", "id": 4}, {"name": "Marvel Studios", "id": 420}] | O18: Paramount Pictures | P18: [{"iso_3166_1": "US", "name": "United States of America"}] | Q18: 41024 | R18: 2012 | S18: 1519557910 | T18: 143 | U18: [{"iso_639_1": "en", "name": "English"}] | V18: Released | W18: Some assembly required. | X18: 7.4 | Y18: 11776 | Z18: 1299557910
A19: 380000000 | B19: [{ 12, name: Adventure}, { 28, name: Action}, { 14, name: Fantasy}] | C19: Adventure | D19: Action | E19: Fantasy | F19: - | G19: http://disney.go.com/pirates/index-on-stranger-tides.html#/video/ | H19: 1865 | I19: Pirates of the Caribbean: On Stranger Tides | J19: [{"id": 658, "name": "sea"}, {"id": 1316, "name": "captain"}, {"id": 1860, "name": "mutiny"}, {"id": 1938, "name": "sword"}, {"id": 2569, "name": "prime minister"}, {"id": 3180, "name": "sailing"}, {"id": 3625, "name": "silver"}, {"id": 3799, "name": "ship"}, {"id": 4235, "name": "duke"}, {"id": 5938, "name": "mermaid"}, {"id": 12988, "name": "pirate"}, {"id": 13065, "name": "soldier"}, {"id": 14643, "name": "battle"}, {"id": 157186, "name": "swashbuckler"}, {"id": 179430, "name": "aftercreditsstinger"}, {"id": 209714, "name": "3d"}] | K19: en | L19: Captain Jack Sparrow crosses paths with a woman from his past, and he's not sure if it's love -- or if she's a ruthless con artist who's using him to find the fabled Fountain of Youth. When she forces him aboard the Queen Anne's Revenge, the ship of the formidable pirate Blackbeard, Jack finds himself on an unexpected adventure in which he doesn't know who to fear more: Blackbeard or the woman from his past. | M19: 135413856 | N19: [{"name": "Walt Disney Pictures", "id": 2}, {"name": "Jerry Bruckheimer Films", "id": 130}, {"name": "Moving Picture Company (MPC)", "id": 20478}] | O19: Walt Disney Pictures | P19: [{"iso_3166_1": "US", "name": "United States of America"}] | Q19: 40677 | R19: 2011 | S19: 1045713802 | T19: 136 | U19: [{"iso_639_1": "en", "name": "English"}, {"iso_639_1": "es", "name": "Espa\u00f1ol"}] | V19: Released | W19: Live Forever Or Die Trying. | X19: 6.4 | Y19: 4948 | Z19: 665713802
A20: 225000000 | B20: [{ 28, name: Action}, { 35, name: Comedy}, { 878, name: Science Fiction}] | C20: Action | D20: Comedy | E20: Science Fiction | F20: - | G20: http://www.sonypictures.com/movies/meninblack3/ | H20: 41154 | I20: Men in Black 3 | J20: [{"id": 4379, "name": "time travel"}, {"id": 5455, "name": "time machine"}, {"id": 9951, "name": "alien"}, {"id": 174915, "name": "fictional government agency"}, {"id": 185668, "name": "seeing the future"}, {"id": 208756, "name": "changing history"}] | K20: en | L20: Agents J (Will Smith) and K (Tommy Lee Jones) are back...in time. J has seen some inexplicable things in his 15 years with the Men in Black, but nothing, not even aliens, perplexes him as much as his wry, reticent partner. But when K's life and the fate of the planet are put at stake, Agent J will have to travel back in time to put things right. J discovers that there are secrets to the universe that K never told him - secrets that will reveal themselves as he teams up with the young Agent K (Josh Brolin) to save his partner, the agency, and the future of humankind. | M20: 52035179 | N20: [{"name": "Amblin Entertainment", "id": 56}, {"name": "Media Magik Entertainment", "id": 5627}, {"name": "Imagenation Abu Dhabi FZ", "id": 6736}, {"name": "Hemisphere Media Capital", "id": 9169}, {"name": "Parkes/MacDonald Productions", "id": 11084}] | O20: Amblin Entertainment | P20: [{"iso_3166_1": "US", "name": "United States of America"}] | Q20: 41052 | R20: 2012 | S20: 624026776 | T20: 106 | U20: [{"iso_639_1": "en", "name": "English"}] | V20: Released | W20: They are back... in time. | X20: 6.2 | Y20: 4160 | Z20: 399026776
A21: 250000000 | B21: [{ 28, name: Action}, { 12, name: Adventure}, { 14, name: Fantasy}] | C21: Action | D21: Adventure | E21: Fantasy | F21: - | G21: http://www.thehobbit.com/ | H21: 122917 | I21: The Hobbit: The Battle of the Five Armies | J21: [{"id": 417, "name": "corruption"}, {"id": 603, "name": "elves"}, {"id": 604, "name": "dwarves"}, {"id": 606, "name": "orcs"}, {"id": 609, "name": "middle-earth (tolkien)"}, {"id": 611, "name": "hobbit"}, {"id": 12554, "name": "dragon"}, {"id": 14643, "name": "battle"}, {"id": 167982, "name": "unlikely friendship"}, {"id": 188270, "name": "epic battle"}, {"id": 234213, "name": "sword and sorcery"}] | K21: en | L21: Immediately after the events of The Desolation of Smaug, Bilbo and the dwarves try to defend Erebor's mountain of treasure from others who claim it: the men of the ruined Laketown and the elves of Mirkwood. Meanwhile an army of Orcs led by Azog the Defiler is marching on Erebor, fueled by the rise of the dark lord Sauron. Dwarves, elves and men must unite, and the hope for Middle-Earth falls into Bilbo's hands. | M21: 120965743 | N21: [{"name": "WingNut Films", "id": 11}, {"name": "New Line Cinema", "id": 12}, {"name": "Warner Bros. Pictures", "id": 174}, {"name": "3Foot7", "id": 7413}, {"name": "Metro-Goldwyn-Mayer (MGM)", "id": 8411}] | O21: WingNut Films | P21: [{"iso_3166_1": "NZ", "name": "New Zealand"}, {"iso_3166_1": "US", "name": "United States of America"}] | Q21: 41983 | R21: 2014 | S21: 956019788 | T21: 144 | U21: [{"iso_639_1": "en", "name": "English"}] | V21: Released | W21: Witness the defining chapter of the Middle-Earth saga | X21: 7.1 | Y21: 4760 | Z21: 706019788
A22: 215000000 | B22: [{ 28, name: Action}, { 12, name: Adventure}, { 14, name: Fantasy}] | C22: Action | D22: Adventure | E22: Fantasy | F22: - | G22: http://www.theamazingspiderman.com | H22: 1930 | I22: The Amazing Spider-Man | J22: [{"id": 1872, "name": "loss of father"}, {"id": 7002, "name": "vigilante"}, {"id": 8803, "name": "serum"}, {"id": 8828, "name": "marvel comic"}, {"id": 156855, "name": "scientific experiment"}, {"id": 158124, "name": "spider bite"}, {"id": 158456, "name": "masked vigilante"}, {"id": 161184, "name": "reboot"}, {"id": 163455, "name": "super powers"}, {"id": 163561, "name": "genetic engineering"}, {"id": 171556, "name": "social outcast"}, {"id": 179431, "name": "duringcreditsstinger"}] | K22: en | L22: Peter Parker is an outcast high schooler abandoned by his parents as a boy, leaving him to be raised by his Uncle Ben and Aunt May. Like most teenagers, Peter is trying to figure out who he is and how he got to be the person he is today. As Peter discovers a mysterious briefcase that belonged to his father, he begins a quest to understand his parents' disappearance â€“ leading him directly to Oscorp and the lab of Dr. Curt Connors, his father's former partner. As Spider-Man is set on a collision course with Connors' alter ego, The Lizard, Peter will make life-altering choices to use his powers and shape his destiny to become a hero. | M22: 89866276 | N22: [{"name": "Columbia Pictures", "id": 5}, {"name": "Laura Ziskin Productions", "id": 326}, {"name": "Marvel Entertainment", "id": 7505}] | O22: Columbia Pictures | P22: [{"iso_3166_1": "US", "name": "United States of America"}] | Q22: 41087 | R22: 2012 | S22: 752215857 | T22: 136 | U22: [{"iso_639_1": "en", "name": "English"}] | V22: Released | W22: The untold story begins. | X22: 6.5 | Y22: 6586 | Z22: 537215857
A23: 250000000 | B23: [{ 12, name: Adventure}, { 14, name: Fantasy}] | C23: Adventure | D23: Fantasy | E23: - | F23: - | G23: http://www.thehobbit.com/ | H23: 57158 | I23: The Hobbit: The Desolation of Smaug | J23: [{"id": 603, "name": "elves"}, {"id": 604, "name": "dwarves"}, {"id": 606, "name": "orcs"}, {"id": 611, "name": "hobbit"}, {"id": 12554, "name": "dragon"}, {"id": 177912, "name": "wizard"}, {"id": 234213, "name": "sword and sorcery"}] | K23: en | L23: The Dwarves, Bilbo and Gandalf have successfully escaped the Misty Mountains, and Bilbo has gained the One Ring. They all continue their journey to get their gold back from the Dragon, Smaug. | M23: 94370564 | N23: [{"name": "WingNut Films", "id": 11}, {"name": "New Line Cinema", "id": 12}, {"name": "Warner Bros. Pictures", "id": 174}, {"name": "Metro-Goldwyn-Mayer (MGM)", "id": 8411}] | O23: WingNut Films | P23: [{"iso_3166_1": "NZ", "name": "New Zealand"}, {"iso_3166_1": "US", "name": "United States of America"}] | Q23: 41619 | R23: 2013 | S23: 958400000 | T23: 161 | U23: [{"iso_639_1": "en", "name": "English"}] | V23: Released | W23: Beyond darkness... beyond desolation... lies the greatest danger of all. | X23: 7.6 | Y23: 4524 | Z23: 708400000
A24: 180000000 | B24: [{ 12, name: Adventure}, { 14, name: Fantasy}] | C24: Adventure | D24: Fantasy | E24: - | F24: - | G24: http://www.goldencompassmovie.com/index_german.html | H24: 2268 | I24: The Golden Compass | J24: [{"id": 392, "name": "england"}, {"id": 1461, "name": "compass"}, {"id": 1706, "name": "experiment"}, {"id": 2596, "name": "lordship"}, {"id": 6464, "name": "uncle"}, {"id": 6678, "name": "polar bear"}, {"id": 13014, "name": "orphan"}, {"id": 18165, "name": "animal"}, {"id": 223438, "name": "based on young adult novel"}] | K24: en | L24: After overhearing a shocking secret, precocious orphan Lyra Belacqua trades her carefree existence roaming the halls of Jordan College for an otherworldly adventure in the far North, unaware that it's part of her destiny. | M24: 42990906 | N24: [{"name": "New Line Cinema", "id": 12}, {"name": "Ingenious Film Partners", "id": 289}, {"name": "Depth of Field", "id": 1473}, {"name": "Scholastic Productions", "id": 1938}] | O24: New Line Cinema | P24: [{"iso_3166_1": "GB", "name": "United Kingdom"}, {"iso_3166_1": "US", "name": "United States of America"}] | Q24: 39420 | R24: 2007 | S24: 372234864 | T24: 113 | U24: [{"iso_639_1": "is", "name": "\u00cdslenska"}, {"iso_639_1": "en", "name": "English"}, {"iso_639_1": "ru", "name": "P\u0443\u0441\u0441\u043a\u0438\u0439"}, {"iso_639_1": "fr", "name": "Fran\u00e7ais"}] | V24: Released | W24: There are worlds beyond our own - the compass will show the way. | X24: 5.8 | Y24: 1303 | Z24: 192234864
A25: 207000000 | B25: [{ 12, name: Adventure}, { 18, name: Drama}, { 28, name: Action}] | C25: Adventure | D25: Drama | E25: Action | F25: - | H25: 254 | I25: King Kong | J25: [{"id": 774, "name": "film business"}, {"id": 776, "name": "screenplay"}, {"id": 837, "name": "show business"}, {"id": 886, "name": "film making"}, {"id": 887, "name": "film producer"}, {"id": 911, "name": "exotic island"}, {"id": 1299, "name": "monster"}, {"id": 1551, "name": "indigenous"}, {"id": 3799, "name": "ship"}, {"id": 12616, "name": "dinosaur"}] | K25: en | L25: In 1933 New York, an overly ambitious movie producer coerces his cast and hired ship crew to travel to mysterious Skull Island, where they encounter Kong, a giant ape who is immediately smitten with the leading lady. | M25: 6122601 | N25: [{"name": "WingNut Films", "id": 11}, {"name": "Universal Pictures", "id": 33}, {"name": "Big Primate Pictures", "id": 68}, {"name": "MFPV Film", "id": 69}] | O25: WingNut Films | P25: [{"iso_3166_1": "NZ", "name": "New Zealand"}, {"iso_3166_1": "US", "name": "United States of America"}, {"iso_3166_1": "DE", "name": "Germany"}] | Q25: 38700 | R25: 2005 | S25: 550000000 | T25: 187 | U25: [{"iso_639_1": "en", "name": "English"}] | V25: Released | W25: The eighth wonder of the world. | X25: 6.6 | Y25: 2337 | Z25: 343000000
A26: 200000000 | B26: [{ 18, name: Drama}, { 10749, name: Romance}, { 53, name: Thriller}] | C26: Drama | D26: Romance | E26: Thriller | F26: - | G26: http://www.titanicmovie.com | H26: 597 | I26: Titanic | J26: [{"id": 2580, "name": "shipwreck"}, {"id": 2984, "name": "iceberg"}, {"id": 3799, "name": "ship"}, {"id": 4210, "name": "panic"}, {"id": 4388, "name": "titanic"}, {"id": 4953, "name": "ocean liner"}, {"id": 6917, "name": "epic"}, {"id": 7579, "name": "rich woman - poor man"}, {"id": 9673, "name": "love"}, {"id": 10617, "name": "disaster"}, {"id": 10703, "name": "tragic love"}, {"id": 14514, "name": "class differences"}, {"id": 156395, "name": "imax"}, {"id": 165086, "name": "star crossed lovers"}, {"id": 182615, "name": "steerage"}, {"id": 182621, "name": "salvage"}, {"id": 182625, "name": "rich snob"}, {"id": 209714, "name": "3d"}, {"id": 210184, "name": "1910s"}] | K26: en | L26: 84 years later, a 101-year-old woman named Rose DeWitt Bukater tells the story to her granddaughter Lizzy Calvert, Brock Lovett, Lewis Bodine, Bobby Buell and Anatoly Mikailavich on the Keldysh about her life set in April 10th 1912, on a ship called Titanic when young Rose boards the departing ship with the upper-class passengers and her mother, Ruth DeWitt Bukater, and her fiancÃ©, Caledon Hockley. Meanwhile, a drifter and artist named Jack Dawson and his best friend Fabrizio De Rossi win third-class tickets to the ship in a game. And she explains the whole story from departure until the death of Titanic on its first and last voyage April 15th, 1912 at 2:20 in the morning. | M26: 100025899 | N26: [{"name": "Paramount Pictures", "id": 4}, {"name": "Twentieth Century Fox Film Corporation", "id": 306}, {"name": "Lightstorm Entertainment", "id": 574}] | O26: Paramount Pictures | P26: [{"iso_3166_1": "US", "name": "United States of America"}] | Q26: 35752 | R26: 1997 | S26: 1845034188 | T26: 194 | U26: [{"iso_639_1": "en", "name": "English"}, {"iso_639_1": "fr", "name": "Fran\u00e7ais"}, {"iso_639_1": "de", "name": "Deutsch"}, {"iso_639_1": "sv", "name": "svenska"}, {"iso_639_1": "it", "name": "Italiano"}, {"iso_639_1": "ru", "name": "P\u0443\u0441\u0441\u043a\u0438\u0439"}] | V26: Released | W26: Nothing on Earth could come between them. | X26: 7.5 | Y26: 7562 | Z26: 1645034188
A27: 250000000 | B27: [{ 12, name: Adventure}, { 28, name: Action}, { 878, name: Science Fiction}] | C27: Adventure | D27: Action | E27: Science Fiction | F27: - | G27: http://marvel.com/captainamericapremiere | H27: 271110 | I27: Captain America: Civil War | J27: [{"id": 393, "name": "civil war"}, {"id": 6091, "name": "war"}, {"id": 8828, "name": "marvel comic"}, {"id": 9663, "name": "sequel"}, {"id": 9715, "name": "superhero"}, {"id": 9717, "name": "based on comic book"}, {"id": 156395, "name": "imax"}, {"id": 179430, "name": "aftercreditsstinger"}, {"id": 179431, "name": "duringcreditsstinger"}, {"id": 180547, "name": "marvel cinematic universe"}, {"id": 209714, "name": "3d"}] | K27: en | L27: Following the events of Age of Ultron, the collective governments of the world pass an act designed to regulate all superhuman activity. This polarizes opinion amongst the Avengers, causing two factions to side with Iron Man or Captain America, which causes an epic battle between former allies. | M27: 198372395 | N27: [{"name": "Studio Babelsberg", "id": 264}, {"name": "Marvel Studios", "id": 420}, {"name": "Walt Disney Studios Motion Pictures", "id": 3036}, {"name": "Vita-Ray Dutch Productions (III)", "id": 84424}, {"name": "Deluxe Digital Studios", "id": 84425}] | O27: Studio Babelsberg | P27: [{"iso_3166_1": "US", "name": "United States of America"}] | Q27: 42487 | R27: 2016 | S27: 1153304495 | T27: 147 | U27: [{"iso_639_1": "ro", "name": "Rom\u00e2n\u0103"}, {"iso_639_1": "en", "name": "English"}, {"iso_639_1": "de", "name": "Deutsch"}, {"iso_639_1": "ru", "name": "P\u0443\u0441\u0441\u043a\u0438\u0439"}] | V27: Released | W27: Divided We Fall | X27: 7.1 | Y27: 7241 | Z27: 903304495
A28: 74000000 | B28: [{ 10751, name: Family}, { 16, name: Animation}, { 12, name: Adventure}, { 35, name: Comedy}] | C28: Family | D28: Animation | E28: Adventure | F28: Comedy | G28: http://www.minionsmovie.com/ | H28: 211672 | I28: Minions | J28: [{"id": 3487, "name": "assistant"}, {"id": 179430, "name": "aftercreditsstinger"}, {"id": 179431, "name": "duringcreditsstinger"}, {"id": 189481, "name": "evil mastermind"}, {"id": 190999, "name": "minions"}, {"id": 209714, "name": "3d"}] | K28: en | L28: Minions Stuart, Kevin and Bob are recruited by Scarlet Overkill, a super-villain who, alongside her inventor husband Herb, hatches a plot to take over the world. | M28: 875581305 | N28: [{"name": "Universal Pictures", "id": 33}, {"name": "Illumination Entertainment", "id": 6704}] | O28: Universal Pictures | P28: [{"iso_3166_1": "US", "name": "United States of America"}] | Q28: 42172 | R28: 2015 | S28: 1156730962 | T28: 91 | U28: [{"iso_639_1": "en", "name": "English"}] | V28: Released | W28: Before Gru, they had a history of bad bosses | X28: 6.4 | Y28: 4571 | Z28: 1082730962
A29: 150000000 | B29: [{ 28, name: Action}, { 12, name: Adventure}, { 878, name: Science Fiction}, { 53, name: Thriller}] | C29: Action | D29: Adventure | E29: Science Fiction | F29: Thriller | G29: http://www.jurassicworld.com/ | H29: 135397 | I29: Jurassic World | J29: [{"id": 1299, "name": "monster"}, {"id": 1718, "name": "dna"}, {"id": 1720, "name": "tyrannosaurus rex"}, {"id": 1766, "name": "velociraptor"}, {"id": 2041, "name": "island"}, {"id": 9663, "name": "sequel"}, {"id": 9937, "name": "suspense"}, {"id": 10617, "name": "disaster"}, {"id": 10685, "name": "escape"}, {"id": 12616, "name": "dinosaur"}, {"id": 155582, "name": "amusement park"}, {"id": 158130, "name": "animal attack"}, {"id": 158340, "name": "theme park"}, {"id": 178010, "name": "jurassic park"}, {"id": 209714, "name": "3d"}, {"id": 223059, "name": "animal horror"}] | K29: en | L29: Twenty-two years after the events of Jurassic Park, Isla Nublar now features a fully functioning dinosaur theme park, Jurassic World, as originally envisioned by John Hammond. | M29: 418708552 | N29: [{"name": "Universal Studios", "id": 13}, {"name": "Amblin Entertainment", "id": 56}, {"name": "Legendary Pictures", "id": 923}, {"name": "Fuji Television Network", "id": 3341}, {"name": "Dentsu", "id": 6452}] | O29: Universal Studios | P29: [{"iso_3166_1": "US", "name": "United States of America"}] | Q29: 42164 | R29: 2015 | S29: 1513528810 | T29: 124 | U29: [{"iso_639_1": "en", "name": "English"}] | V29: Released | W29: The park is open. | X29: 6.5 | Y29: 8662 | Z29: 1363528810
A30: 200000000 | B30: [{ 28, name: Action}, { 12, name: Adventure}, { 53, name: Thriller}] | C30: Action | D30: Adventure | E30: Thriller | F30: - | G30: http://www.skyfall-movie.com | H30: 37724 | I30: Skyfall | J30: [{"id": 470, "name": "spy"}, {"id": 4289, "name": "secret agent"}, {"id": 9740, "name": "sociopath"}, {"id": 15127, "name": "killer"}, {"id": 15478, "name": "art gallery"}, {"id": 156095, "name": "british secret service"}, {"id": 156345, "name": "istanbul turkey"}, {"id": 156395, "name": "imax"}, {"id": 159932, "name": "uzi"}, {"id": 163841, "name": "booby trap"}, {"id": 185071, "name": "impersonating a police officer"}, {"id": 185077, "name": "macao"}] | K30: en | L30: When Bond's latest assignment goes gravely wrong and agents around the world are exposed, MI6 is attacked forcing M to relocate the agency. These events cause her authority and position to be challenged by Gareth Mallory, the new Chairman of the Intelligence and Security Committee. With MI6 now compromised from both inside and out, M is left with one ally she can trust: Bond. 007 takes to the shadows - aided only by field agent, Eve - following a trail to the mysterious Silva, whose lethal and hidden motives have yet to reveal themselves. | M30: 93004993 | N30: [{"name": "Columbia Pictures", "id": 5}] | O30: Columbia Pictures | P30: [{"iso_3166_1": "GB", "name": "United Kingdom"}, {"iso_3166_1": "US", "name": "United States of America"}] | Q30: 41207 | R30: 2012 | S30: 1108561013 | T30: 143 | U30: [{"iso_639_1": "en", "name": "English"}] | V30: Released | W30: Think on your sins. | X30: 6.9 | Y30: 7604 | Z30: 908561013
A31: 200000000 | B31: [{ 28, name: Action}, { 12, name: Adventure}, { 14, name: Fantasy}] | C31: Action | D31: Adventure | E31: Fantasy | F31: - | G31: http://www.sonypictures.com/movies/spider-man2/ | H31: 558 | I31: Spider-Man 2 | J31: [{"id": 851, "name": "dual identity"}, {"id": 2038, "name": "love of one's life"}, {"id": 5983, "name": "pizza boy"}, {"id": 8828, "name": "marvel comic"}, {"id": 9663, "name": "sequel"}, {"id": 9715, "name": "superhero"}, {"id": 13005, "name": "doctor"}, {"id": 14760, "name": "scientist"}, {"id": 14991, "name": "tentacle"}, {"id": 34079, "name": "death"}, {"id": 163074, "name": "super villain"}] | K31: en | L31: Peter Parker is going through a major identity crisis. Burned out from being Spider-Man, he decides to shelve his superhero alter ego, which leaves the city suffering in the wake of carnage left by the evil Doc Ock. In the meantime, Parker still can't act on his feelings for Mary Jane Watson, a girl he's loved since childhood. | M31: 35149586 | N31: [{"name": "Columbia Pictures", "id": 5}, {"name": "Laura Ziskin Productions", "id": 326}, {"name": "Marvel Enterprises", "id": 19551}] | O31: Columbia Pictures | P31: [{"iso_3166_1": "US", "name": "United States of America"}] | Q31: 38163 | R31: 2004 | S31: 783766341 | T31: 127 | U31: [{"iso_639_1": "en", "name": "English"}, {"iso_639_1": "ru", "name": "P\u0443\u0441\u0441\u043a\u0438\u0439"}, {"iso_639_1": "zh", "name": "\u666e\u901a\u8bdd"}] | V31: Released | W31: There's a hero in all of us. | X31: 6.7 | Y31: 4321 | Z31: 583766341
A32: 200000000 | B32: [{ 28, name: Action}, { 12, name: Adventure}, { 878, name: Science Fiction}] | C32: Action | D32: Adventure | E32: Science Fiction | F32: - | G32: http://marvel.com/ironman3 | H32: 68721 | I32: Iron Man 3 | J32: [{"id": 949, "name": "terrorist"}, {"id": 5597, "name": "war on terror"}, {"id": 6335, "name": "tennessee"}, {"id": 8613, "name": "malibu"}, {"id": 8828, "name": "marvel comic"}, {"id": 9715, "name": "superhero"}, {"id": 9717, "name": "based on comic book"}, {"id": 12555, "name": "tony stark"}, {"id": 173776, "name": "iron man"}, {"id": 179430, "name": "aftercreditsstinger"}, {"id": 180547, "name": "marvel cinematic universe"}, {"id": 188721, "name": "mandarin"}, {"id": 209714, "name": "3d"}, {"id": 209748, "name": "war machine"}, {"id": 209822, "name": "iron patriot"}, {"id": 209823, "name": "extremis"}] | K32: en | L32: When Tony Stark's world is torn apart by a formidable terrorist called the Mandarin, he starts an odyssey of rebuilding and retribution. | M32: 7768208 | N32: [{"name": "Marvel Studios", "id": 420}] | O32: Marvel Studios | P32: [{"iso_3166_1": "CN", "name": "China"}, {"iso_3166_1": "US", "name": "United States of America"}] | Q32: 41382 | R32: 2013 | S32: 1215439994 | T32: 130 | U32: [{"iso_639_1": "en", "name": "English"}] | V32: Released | W32: Unleash the power behind the armor. | X32: 6.8 | Y32: 8806 | Z32: 1015439994
A33: 200000000 | B33: [{ 10751, name: Family}, { 14, name: Fantasy}, { 12, name: Adventure}] | C33: Family | D33: Fantasy | E33: Adventure | F33: - | G33: http://disney.go.com/wonderland/ | H33: 12155 | I33: Alice in Wonderland | J33: [{"id": 818, "name": "based on novel"}, {"id": 855, "name": "fictional place"}, {"id": 2011, "name": "queen"}, {"id": 2486, "name": "fantasy"}, {"id": 12552, "name": "alice in wonderland"}, {"id": 170362, "name": "fantasy world"}, {"id": 209714, "name": "3d"}] | K33: en | L33: Alice, an unpretentious and individual 19-year-old, is betrothed to a dunce of an English nobleman. At her engagement party, she escapes the crowd to consider whether to go through with the marriage and falls down a hole in the garden after spotting an unusual rabbit. Arriving in a strange and surreal place called 'Underland,' she finds herself in a world that resembles the nightmares she had as a child, filled with talking animals, villainous queens and knights, and frumious bandersnatches. Alice realizes that she is there for a reason â€“ to conquer the horrific Jabberwocky and restore the rightful queen to her throne. | M33: 78530105 | N33: [{"name": "Walt Disney Pictures", "id": 2}, {"name": "Team Todd", "id": 598}, {"name": "Tim Burton Productions", "id": 8601}, {"name": "Roth Films", "id": 16314}, {"name": "Zanuck Company, The", "id": 20004}] | O33: Walt Disney Pictures | P33: [{"iso_3166_1": "US", "name": "United States of America"}] | Q33: 40240 | R33: 2010 | S33: 1025491110 | T33: 108 | U33: [{"iso_639_1": "en", "name": "English"}] | V33: Released | W33: You're invited to a very important date. | X33: 6.4 | Y33: 4645 | Z33: 825491110
A34: 210000000 | B34: [{ 12, name: Adventure}, { 28, name: Action}, { 878, name: Science Fiction}, { 53, name: Thriller}] | C34: Adventure | D34: Action | E34: Science Fiction | F34: Thriller | H34: 36668 | I34: X-Men: The Last Stand | J34: [{"id": 1852, "name": "mutant"}, {"id": 8828, "name": "marvel comic"}, {"id": 9717, "name": "based on comic book"}, {"id": 10761, "name": "superhuman"}, {"id": 161271, "name": "beast"}, {"id": 161893, "name": "cyclops"}, {"id": 179430, "name": "aftercreditsstinger"}] | K34: en | L34: When a cure is found to treat mutations, lines are drawn amongst the X-Men and The Brotherhood, a band of powerful mutants organized under Xavier's former ally, Magneto. | M34: 3857526 | N34: [{"name": "Ingenious Film Partners", "id": 289}, {"name": "Twentieth Century Fox Film Corporation", "id": 306}, {"name": "Donners' Company", "id": 431}, {"name": "Dune Entertainment", "id": 444}, {"name": "Major Studio Partners", "id": 445}, {"name": "Bad Hat Harry Productions", "id": 9168}, {"name": "thinkfilm", "id": 12247}, {"name": "Marvel Enterprises", "id": 19551}, {"name": "X3 Canada Productions", "id": 79028}, {"name": "X3US Productions", "id": 79029}, {"name": "XM3 Service", "id": 79030}] | O34: Ingenious Film Partners | P34: [{"iso_3166_1": "CA", "name": "Canada"}, {"iso_3166_1": "GB", "name": "United Kingdom"}, {"iso_3166_1": "US", "name": "United States of America"}] | Q34: 38861 | R34: 2006 | S34: 459359555 | T34: 104 | U34: [{"iso_639_1": "en", "name": "English"}] | V34: Released | W34: Take a Stand | X34: 6.3 | Y34: 3525 | Z34: 249359555
A35: 200000000 | B35: [{ 16, name: Animation}, { 10751, name: Family}] | C35: Animation | D35: Family | E35: - | F35: - | H35: 62211 | I35: Monsters University | J35: [{"id": 1299, "name": "monster"}, {"id": 5984, "name": "dormitory"}, {"id": 6186, "name": "games"}, {"id": 10336, "name": "animation"}, {"id": 12392, "name": "best friend"}, {"id": 13160, "name": "university"}, {"id": 163303, "name": "scary"}, {"id": 179430, "name": "aftercreditsstinger"}] | K35: en | L35: A look at the relationship between Mike and Sulley during their days at Monsters University â€” when they weren't necessarily the best of friends. | M35: 89186492 | N35: [{"name": "Walt Disney Pictures", "id": 2}, {"name": "Pixar Animation Studios", "id": 3}] | O35: Walt Disney Pictures | P35: [{"iso_3166_1": "US", "name": "United States of America"}] | Q35: 41445 | R35: 2013 | S35: 743559607 | T35: 104 | U35: [{"iso_639_1": "en", "name": "English"}] | V35: Released | W35: School never looked this scary. | X35: 7.0 | Y35: 3528 | Z35: 543559607
A36: 150000000 | B36: [{ 878, name: Science Fiction}, { 28, name: Action}, { 12, name: Adventure}] | C36: Science Fiction | D36: Action | E36: Adventure | F36: - | G36: http://www.transformersmovie.com/ | H36: 8373 | I36: Transformers: Revenge of the Fallen | J36: [{"id": 1160, "name": "egypt"}, {"id": 1670, "name": "sun"}, {"id": 4630, "name": "chaos"}, {"id": 8264, "name": "symbol"}, {"id": 9854, "name": "artifact"}, {"id": 10607, "name": "transformers"}, {"id": 11117, "name": "tank"}, {"id": 14544, "name": "robot"}, {"id": 156395, "name": "imax"}, {"id": 179431, "name": "duringcreditsstinger"}] | K36: en | L36: Sam Witwicky leaves the Autobots behind for a normal life. But when his mind is filled with cryptic symbols, the Decepticons target him and he is dragged back into the Transformers' war. | M36: 21939663 | N36: [{"name": "Paramount Pictures", "id": 4}, {"name": "DreamWorks SKG", "id": 27}, {"name": "Amblin Entertainment", "id": 56}, {"name": "Di Bonaventura Pictures", "id": 435}, {"name": "Platinum Dunes", "id": 2481}, {"name": "Hasbro Studios", "id": 22826}, {"name": "Revolution Sun Studios", "id": 76043}] | O36: Paramount Pictures | P36: [{"iso_3166_1": "US", "name": "United States of America"}] | Q36: 39983 | R36: 2009 | S36: 836297228 | T36: 150 | U36: [{"iso_639_1": "en", "name": "English"}, {"iso_639_1": "es", "name": "Espa\u00f1ol"}] | V36: Released | W36: Revenge is coming. | X36: 6.0 | Y36: 3138 | Z36: 686297228
A37: 210000000 | B37: [{ 878, name: Science Fiction}, { 28, name: Action}, { 12, name: Adventure}] | C37: Science Fiction | D37: Action | E37: Adventure | F37: - | G37: http://www.transformersmovie.com | H37: 91314 | I37: Transformers: Age of Extinction | J37: [{"id": 9663, "name": "sequel"}, {"id": 9951, "name": "alien"}, {"id": 10607, "name": "transformers"}, {"id": 10891, "name": "giant robot"}, {"id": 14544, "name": "robot"}, {"id": 156395, "name": "imax"}, {"id": 166594, "name": "transforming robot"}] | K37: en | L37: As humanity picks up the pieces, following the conclusion of "Transformers: Dark of the Moon," Autobots and Decepticons have all but vanished from the face of the planet. However, a group of powerful, ingenious businessman and scientists attempt to learn from past Transformer incursions and push the boundaries of technology beyond what they can control - all while an ancient, powerful Transformer menace sets Earth in his cross-hairs. | M37: 116840296 | N37: [{"name": "Paramount Pictures", "id": 4}, {"name": "Amblin Entertainment", "id": 56}, {"name": "Di Bonaventura Pictures", "id": 435}, {"name": "Platinum Dunes", "id": 2481}, {"name": "China Movie Channel", "id": 11413}, {"name": "Hasbro Studios", "id": 22826}, {"name": "Ian Bryce Productions", "id": 38833}, {"name": "Revolution Sun Studios", "id": 76043}] | O37: Paramount Pictures | P37: [{"iso_3166_1": "US", "name": "United States of America"}] | Q37: 41815 | R37: 2014 | S37: 1091405097 | T37: 165 | U37: [{"iso_639_1": "en", "name": "English"}] | V37: Released | W37: This is not war. It's extinction. | X37: 5.8 | Y37: 3095 | Z37: 881405097
A38: 200000000 | B38: [{ 14, name: Fantasy}, { 12, name: Adventure}, { 10751, name: Family}] | C38: Fantasy | D38: Adventure | E38: Family | F38: - | G38: http://www.ozthegreatandpowerfulmovie.com | H38: 68728 | I38: Oz: The Great and Powerful | J38: [{"id": 291, "name": "circus"}, {"id": 616, "name": "witch"}, {"id": 2343, "name": "magic"}, {"id": 3929, "name": "hope"}, {"id": 4662, "name": "illusion"}, {"id": 44451, "name": "lost"}, {"id": 172365, "name": "magic trick"}, {"id": 177912, "name": "wizard"}, {"id": 209714, "name": "3d"}] | K38: en | L38: Oscar Diggs, a small-time circus illusionist and con-artist, is whisked from Kansas to the Land of Oz where the inhabitants assume he's the great wizard of prophecy, there to save Oz from the clutches of evil. | M38: 46985445 | N38: [{"name": "Walt Disney Pictures", "id": 2}, {"name": "Roth Films", "id": 16314}] | O38: Walt Disney Pictures | P38: [{"iso_3166_1": "US", "name": "United States of America"}] | Q38: 41340 | R38: 2013 | S38: 491868548 | T38: 130 | U38: [{"iso_639_1": "en", "name": "English"}] | V38: Released | W38: In Oz, nothing is what it seems | X38: 5.7 | Y38: 3530 | Z38: 291868548
A39: 200000000 | B39: [{ 28, name: Action}, { 12, name: Adventure}, { 14, name: Fantasy}] | C39: Action | D39: Adventure | E39: Fantasy | F39: - | G39: http://www.theamazingspiderman.com | H39: 102382 | I39: The Amazing Spider-Man 2 | J39: [{"id": 1523, "name": "obsession"}, {"id": 8828, "name": "marvel comic"}, {"id": 9663, "name": "sequel"}, {"id": 9717, "name": "based on comic book"}, {"id": 13040, "name": "electrocution"}, {"id": 33977, "name": "medical experiment"}, {"id": 41594, "name": "electricity"}, {"id": 163455, "name": "super powers"}] | K39: en | L39: For Peter Parker, life is busy. Between taking out the bad guys as Spider-Man and spending time with the person he loves, Gwen Stacy, high school graduation cannot come quickly enough. Peter has not forgotten about the promise he made to Gwenâ€™s father to protect her by staying away, but that is a promise he cannot keep. Things will change for Peter when a new villain, Electro, emerges, an old friend, Harry Osborn, returns, and Peter uncovers new clues about his past. | M39: 89270217 | N39: [{"name": "Columbia Pictures", "id": 5}, {"name": "Marvel Enterprises", "id": 19551}, {"name": "Avi Arad Productions", "id": 31828}, {"name": "Matt Tolmach Productions", "id": 53462}] | O39: Columbia Pictures | P39: [{"iso_3166_1": "US", "name": "United States of America"}] | Q39: 41745 | R39: 2014 | S39: 705717432 | T39: 142 | U39: [{"iso_639_1": "en", "name": "English"}] | V39: Released | W39: No more secrets. | X39: 6.5 | Y39: 4179 | Z39: 505717432
A40: 170000000 | B40: [{ 12, name: Adventure}, { 28, name: Action}, { 878, name: Science Fiction}] | C40: Adventure | D40: Action | E40: Science Fiction | F40: - | G40: http://disney.go.com/tron/ | H40: 20526 | I40: TRON: Legacy | J40: [{"id": 310, "name": "artificial intelligence"}, {"id": 1308, "name": "secret identity"}, {"id": 4286, "name": "computer program"}, {"id": 4565, "name": "dystopia"}, {"id": 6104, "name": "computer"}, {"id": 9758, "name": "deception"}, {"id": 12965, "name": "duel"}, {"id": 14735, "name": "motorcycle"}, {"id": 185351, "name": "neon light"}, {"id": 236778, "name": "autocracy"}] | K40: en | L40: Sam Flynn, the tech-savvy and daring son of Kevin Flynn, investigates his father's disappearance and is pulled into The Grid. With the help of a mysterious program named Quorra, Sam quests to stop evil dictator Clu from crossing into the real world. | M40: 7379505 | N40: [{"name": "Walt Disney Pictures", "id": 2}, {"name": "LivePlanet", "id": 7161}, {"name": "Prana Studios", "id": 18713}, {"name": "Sean Bailey Productions", "id": 23791}, {"name": "Revolution Sun Studios", "id": 76043}, {"name": "Kontsept Film Company", "id": 76067}] | O40: Walt Disney Pictures | P40: [{"iso_3166_1": "US", "name": "United States of America"}] | Q40: 40522 | R40: 2010 | S40: 400062763 | T40: 125 | U40: [{"iso_639_1": "en", "name": "English"}] | V40: Released | W40: The Game Has Changed. | X40: 6.3 | Y40: 2841 | Z40: 230062763
A41: 200000000 | B41: [{ 16, name: Animation}, { 10751, name: Family}, { 12, name: Adventure}, { 35, name: Comedy}] | C41: Animation | D41: Family | E41: Adventure | F41: Comedy | G41: http://www.disney.go.com/cars/ | H41: 49013 | I41: Cars 2 | J41: [{"id": 830, "name": "car race"}, {"id": 9663, "name": "sequel"}, {"id": 10267, "name": "comedy"}, {"id": 11500, "name": "anthropomorphism"}, {"id": 12392, "name": "best friend"}, {"id": 179431, "name": "duringcreditsstinger"}] | K41: en | L41: Star race car Lightning McQueen and his pal Mater head overseas to compete in the World Grand Prix race. But the road to the championship becomes rocky as Mater gets caught up in an intriguing adventure of his own: international espionage. | M41: 4998659 | N41: [{"name": "Walt Disney Pictures", "id": 2}, {"name": "Pixar Animation Studios", "id": 3}] | O41: Walt Disney Pictures | P41: [{"iso_3166_1": "US", "name": "United States of America"}] | Q41: 40705 | R41: 2011 | S41: 559852396 | T41: 106 | U41: [{"iso_639_1": "en", "name": "English"}, {"iso_639_1": "ja", "name": "\u65e5\u672c\u8a9e"}, {"iso_639_1": "it", "name": "Italiano"}, {"iso_639_1": "fr", "name": "Fran\u00e7ais"}] | V41: Released | W41: Ka-ciao! | X41: 5.8 | Y41: 2033 | Z41: 359852396
A42: 200000000 | B42: [{ 12, name: Adventure}, { 28, name: Action}, { 53, name: Thriller}, { 878, name: Science Fiction}] | C42: Adventure | D42: Action | E42: Thriller | F42: Science Fiction | G42: http://greenlanternmovie.warnerbros.com/ | H42: 44912 | I42: Green Lantern | J42: [{"id": 849, "name": "dc comics"}, {"id": 4375, "name": "transformation"}, {"id": 9715, "name": "superhero"}, {"id": 9951, "name": "alien"}, {"id": 15250, "name": "alien infection"}, {"id": 15252, "name": "magical object"}, {"id": 15254, "name": "protector"}, {"id": 163455, "name": "super powers"}, {"id": 202540, "name": "origin"}, {"id": 209714, "name": "3d"}] | K42: en | L42: For centuries, a small but powerful force of warriors called the Green Lantern Corps has sworn to keep intergalactic order. Each Green Lantern wears a ring that grants him superpowers. But when a new enemy called Parallax threatens to destroy the balance of power in the Universe, their fate and the fate of Earth lie in the hands of the first human ever recruited. | M42: 51872839 | N42: [{"name": "De Line Pictures", "id": 2609}, {"name": "Warner Bros.", "id": 6194}, {"name": "DC Entertainment", "id": 9993}] | O42: De Line Pictures | P42: [{"iso_3166_1": "US", "name": "United States of America"}] | Q42: 40710 | R42: 2011 | S42: 219851172 | T42: 114 | U42: [{"iso_639_1": "en", "name": "English"}] | V42: Released | W42: In our darkest hour, there will be light. | X42: 5.1 | Y42: 2487 | Z42: 19851172
A43: 200000000 | B43: [{ 16, name: Animation}, { 10751, name: Family}, { 35, name: Comedy}] | C43: Animation | D43: Family | E43: Comedy | F43: - | G43: http://disney.go.com/toystory/ | H43: 10193 | I43: Toy Story 3 | J43: [{"id": 1562, "name": "hostage"}, {"id": 3616, "name": "college"}, {"id": 4290, "name": "toy"}, {"id": 5462, "name": "barbie"}, {"id": 10336, "name": "animation"}, {"id": 10685, "name": "escape"}, {"id": 33794, "name": "day care"}, {"id": 158162, "name": "teddy bear"}, {"id": 179431, "name": "duringcreditsstinger"}, {"id": 187065, "name": "toy comes to life"}, {"id": 209386, "name": "personification"}, {"id": 209387, "name": "inanimate objects coming to life"}, {"id": 224516, "name": "toy story"}] | K43: en | L43: Woody, Buzz, and the rest of Andy's toys haven't been played with in years. With Andy about to go to college, the gang find themselves accidentally left at a nefarious day care center. The toys must band together to escape and return home to Andy. | M43: 59995418 | N43: [{"name": "Walt Disney Pictures", "id": 2}, {"name": "Pixar Animation Studios", "id": 3}] | O43: Walt Disney Pictures | P43: [{"iso_3166_1": "US", "name": "United States of America"}] | Q43: 40345 | R43: 2010 | S43: 1066969703 | T43: 103 | U43: [{"iso_639_1": "en", "name": "English"}, {"iso_639_1": "es", "name": "Espa\u00f1ol"}] | V43: Released | W43: No toy gets left behind. | X43: 7.6 | Y43: 4597 | Z43: 866969703
A44: 200000000 | B44: [{ 28, name: Action}, { 878, name: Science Fiction}, { 53, name: Thriller}] | C44: Action | D44: Science Fiction | E44: Thriller | F44: - | G44: https://www.warnerbros.com/terminator-salvation | H44: 534 | I44: Terminator Salvation | J44: [{"id": 83, "name": "saving the world"}, {"id": 310, "name": "artificial intelligence"}, {"id": 530, "name": "prophecy"}, {"id": 582, "name": "san francisco"}, {"id": 679, "name": "cyborg"}, {"id": 1373, "name": "killer robot"}, {"id": 1420, "name": "gas station"}, {"id": 4458, "name": "post-apocalyptic"}, {"id": 4565, "name": "dystopia"}, {"id": 6092, "name": "army"}, {"id": 6112, "name": "firearm"}, {"id": 11159, "name": "wartime"}, {"id": 12670, "name": "los angeles"}] | K44: en | L44: All grown up in post-apocalyptic 2018, John Connor must lead the resistance of humans against the increasingly dominating militaristic robots. But when Marcus Wright appears, his existence confuses the mission as Connor tries to determine whether Wright has come from the future or the past -- and whether he's friend or foe. | M44: 71862892 | N44: [{"name": "Columbia Pictures", "id": 5}, {"name": "The Halcyon Company", "id": 4021}, {"name": "Wonderland Sound and Vision", "id": 4022}, {"name": "Warner Bros.", "id": 6194}] | O44: Columbia Pictures | P44: [{"iso_3166_1": "DE", "name": "Germany"}, {"iso_3166_1": "IT", "name": "Italy"}, {"iso_3166_1": "GB", "name": "United Kingdom"}, {"iso_3166_1": "US", "name": "United States of America"}] | Q44: 39953 | R44: 2009 | S44: 371353001 | T44: 115 | U44: [{"iso_639_1": "en", "name": "English"}, {"iso_639_1": "it", "name": "Italiano"}] | V44: Released | W44: The End Begins. | X44: 5.9 | Y44: 2463 | Z44: 171353001
A45: 76000000 | B45: [{ 16, name: Animation}, { 35, name: Comedy}, { 10751, name: Family}] | C45: Animation | D45: Comedy | E45: Family | F45: - | G45: http://www.despicableme.com/ | H45: 93456 | I45: Despicable Me 2 | J45: [{"id": 4289, "name": "secret agent"}, {"id": 7397, "name": "bakery"}, {"id": 13072, "name": "falling in love"}, {"id": 15300, "name": "father daughter relationship"}, {"id": 179431, "name": "duringcreditsstinger"}, {"id": 184783, "name": "first date"}, {"id": 190999, "name": "minions"}, {"id": 209714, "name": "3d"}] | K45: en | L45: Gru is recruited by the Anti-Villain League to help deal with a powerful new super criminal. | M45: 136886704 | N45: [{"name": "Universal Pictures", "id": 33}, {"name": "Illumination Entertainment", "id": 6704}] | O45: Universal Pictures | P45: [{"iso_3166_1": "US", "name": "United States of America"}] | Q45: 41450 | R45: 2013 | S45: 970761885 | T45: 98 | U45: [{"iso_639_1": "en", "name": "English"}] | V45: Released | W45: Back 2 Work | X45: 7.0 | Y45: 4637 | Z45: 894761885
A46: 200000000 | B46: [{ 28, name: Action}, { 18, name: Drama}, { 27, name: Horror}, { 878, name: Science Fiction}, { 53, name: Thriller}] | C46: Action | D46: Drama | E46: Horror | F46: Science Fiction | G46: http://www.worldwarzmovie.com | H46: 72190 | I46: World War Z | J46: [{"id": 4565, "name": "dystopia"}, {"id": 12332, "name": "apocalypse"}, {"id": 12377, "name": "zombie"}, {"id": 160381, "name": "nuclear weapons"}, {"id": 180635, "name": "multiple perspectives"}, {"id": 186565, "name": "zombie apocalypse"}] | K46: en | L46: Life for former United Nations investigator Gerry Lane and his family seems content. Suddenly, the world is plagued by a mysterious infection turning whole human populations into rampaging mindless zombies. After barely escaping the chaos, Lane is persuaded to go on a mission to investigate this disease. What follows is a perilous trek around the world where Lane must brave horrific dangers and long odds to find answers before human civilization falls. | M46: 81834855 | N46: [{"name": "Paramount Pictures", "id": 4}, {"name": "GK Films", "id": 3281}, {"name": "Skydance Productions", "id": 6277}, {"name": "Hemisphere Media Capital", "id": 9169}, {"name": "Apparatus Productions", "id": 11956}, {"name": "Latina Pictures", "id": 19108}, {"name": "2DUX\u00b2", "id": 23644}] | O46: Paramount Pictures | P46: [{"iso_3166_1": "US", "name": "United States of America"}, {"iso_3166_1": "MT", "name": "Malta"}] | Q46: 41445 | R46: 2013 | S46: 531865000 | T46: 116 | U46: [{"iso_639_1": "en", "name": "English"}] | V46: Released | W46: Remember Philly! | X46: 6.7 | Y46: 5560 | Z46: 331865000
A47: 250000000 | B47: [{ 28, name: Action}, { 12, name: Adventure}, { 14, name: Fantasy}, { 878, name: Science Fiction}] | C47: Action | D47: Adventure | E47: Fantasy | F47: Science Fiction | G47: http://www.x-menmovies.com/ | H47: 127585 | I47: X-Men: Days of Future Past | J47: [{"id": 1228, "name": "1970s"}, {"id": 1852, "name": "mutant"}, {"id": 4379, "name": "time travel"}, {"id": 8828, "name": "marvel comic"}, {"id": 9717, "name": "based on comic book"}, {"id": 10761, "name": "superhuman"}, {"id": 14527, "name": "storm"}, {"id": 161271, "name": "beast"}, {"id": 179430, "name": "aftercreditsstinger"}, {"id": 206736, "name": "changing the past or future"}] | K47: en | L47: The ultimate X-Men ensemble fights a war for the survival of the species across two time periods as they join forces with their younger selves in an epic battle that must change the past â€“ to save our future. | M47: 118078691 | N47: [{"name": "Twentieth Century Fox Film Corporation", "id": 306}, {"name": "Donners' Company", "id": 431}, {"name": "Marvel Entertainment", "id": 7505}, {"name": "Bad Hat Harry Productions", "id": 9168}, {"name": "TSG Entertainment", "id": 22213}, {"name": "Down Productions", "id": 37336}, {"name": "Revolution Sun Studios", "id": 76043}] | O47: Twentieth Century Fox Film Corporation | P47: [{"iso_3166_1": "GB", "name": "United Kingdom"}, {"iso_3166_1": "US", "name": "United States of America"}] | Q47: 41774 | R47: 2014 | S47: 747862775 | T47: 131 | U47: [{"iso_639_1": "en", "name": "English"}] | V47: Released | W47: To save the future, they must alter the past | X47: 7.5 | Y47: 6032 | Z47: 497862775
A48: 190000000 | B48: [{ 28, name: Action}, { 12, name: Adventure}, { 878, name: Science Fiction}] | C48: Action | D48: Adventure | E48: Science Fiction | F48: - | H48: 54138 | I48: Star Trek Into Darkness | J48: [{"id": 1612, "name": "spacecraft"}, {"id": 6054, "name": "friendship"}, {"id": 9663, "name": "sequel"}, {"id": 9685, "name": "futuristic"}, {"id": 9882, "name": "space"}, {"id": 9951, "name": "alien"}, {"id": 156395, "name": "imax"}, {"id": 161176, "name": "space opera"}, {"id": 179569, "name": "terrorist bombing"}, {"id": 209714, "name": "3d"}] | K48: en | L48: When the crew of the Enterprise is called back home, they find an unstoppable force of terror from within their own organization has detonated the fleet and everything it stands for, leaving our world in a state of crisis. With a personal score to settle, Captain Kirk leads a manhunt to a war-zone world to capture a one man weapon of mass destruction. As our heroes are propelled into an epic chess game of life and death, love will be challenged, friendships will be torn apart, and sacrifices must be made for the only family Kirk has left: his crew. | M48: 78291018 | N48: [{"name": "Paramount Pictures", "id": 4}, {"name": "Skydance Productions", "id": 6277}, {"name": "Bad Robot", "id": 11461}, {"name": "Kurtzman/Orci", "id": 12536}] | O48: Paramount Pictures | P48: [{"iso_3166_1": "US", "name": "United States of America"}] | Q48: 41399 | R48: 2013 | S48: 467365246 | T48: 132 | U48: [{"iso_639_1": "en", "name": "English"}] | V48: Released | W48: Earth Will Fall | X48: 7.4 | Y48: 4418 | Z48: 277365246
A49: 195000000 | B49: [{ 28, name: Action}, { 10751, name: Family}, { 14, name: Fantasy}] | C49: Action | D49: Family | E49: Fantasy | F49: - | G49: http://jackthegiantkiller.warnerbros.com | H49: 81005 | I49: Jack the Giant Slayer | J49: [{"id": 179411, "name": "based on fairy tale"}, {"id": 189099, "name": "giant"}] | K49: en | L49: The story of an ancient war that is reignited when a young farmhand unwittingly opens a gateway between our world and a fearsome race of giants. Unleashed on the Earth for the first time in centuries, the giants strive to reclaim the land they once lost, forcing the young man, Jack into the battle of his life to stop them. Fighting for a kingdom, its people, and the love of a brave princess, he comes face to face with the unstoppable warriors he thought only existed in legendâ€“and gets the chance to become a legend himself. | M49: 43349855 | N49: [{"name": "New Line Cinema", "id": 12}, {"name": "Original Film", "id": 333}, {"name": "Legendary Pictures", "id": 923}, {"name": "Warner Bros.", "id": 6194}, {"name": "Big Kid Pictures", "id": 8406}, {"name": "Bad Hat Harry Productions", "id": 9168}] | O49: New Line Cinema | P49: [{"iso_3166_1": "US", "name": "United States of America"}] | Q49: 41332 | R49: 2013 | S49: 197687603 | T49: 114 | U49: [{"iso_639_1": "en", "name": "English"}] | V49: Released | W49: Prepare for a giant adventure | X49: 5.5 | Y49: 2598 | Z49: 2687603
A50: 105000000 | B50: [{ 18, name: Drama}, { 10749, name: Romance}] | C50: Drama | D50: Romance | E50: - | F50: - | H50: 64682 | I50: The Great Gatsby | J50: [{"id": 818, "name": "based on novel"}, {"id": 1326, "name": "infidelity"}, {"id": 1523, "name": "obsession"}, {"id": 3929, "name": "hope"}, {"id": 209714, "name": "3d"}] | K50: en | L50: An adaptation of F. Scott Fitzgerald's Long Island-set novel, where Midwesterner Nick Carraway is lured into the lavish world of his neighbor, Jay Gatsby. Soon enough, however, Carraway will see through the cracks of Gatsby's nouveau riche existence, where obsession, madness, and tragedy await. | M50: 61196071 | N50: [{"name": "Village Roadshow Pictures", "id": 79}, {"name": "Bazmark Films", "id": 240}, {"name": "Warner Bros.", "id": 6194}, {"name": "A&E Television Networks", "id": 11858}, {"name": "Red Wagon Entertainment", "id": 14440}, {"name": "Spectrum Films", "id": 14604}] | O50: Village Roadshow Pictures | P50: [{"iso_3166_1": "US", "name": "United States of America"}, {"iso_3166_1": "AU", "name": "Australia"}] | Q50: 41404 | R50: 2013 | S50: 351040419 | T50: 143 | U50: [{"iso_639_1": "en", "name": "English"}] | V50: Released | W50: Reserving judgments is a matter of infinite hope... I come to the admission that it has a limit. | X50: 7.3 | Y50: 3769 | Z50: 246040419
A51: 150000000 | B51: [{ 12, name: Adventure}, { 14, name: Fantasy}, { 28, name: Action}, { 10749, name: Romance}] | C51: Adventure | D51: Fantasy | E51: Action | F51: Romance | G51: http://disney.go.com/disneypictures/princeofpersia | H51: 9543 | I51: Prince of Persia: The Sands of Time | J51: [{"id": 1241, "name": "persia"}, {"id": 1965, "name": "sandstorm"}, {"id": 12653, "name": "brother against brother"}, {"id": 12654, "name": "armageddon"}, {"id": 12655, "name": "regent"}, {"id": 41645, "name": "based on video game"}] | K51: en | L51: A rogue prince reluctantly joins forces with a mysterious princess and together, they race against dark forces to safeguard an ancient dagger capable of releasing the Sands of Time â€“ gift from the gods that can reverse time and allow its possessor to rule the world. | M51: 62169881 | N51: [{"name": "Walt Disney Pictures", "id": 2}, {"name": "Jerry Bruckheimer Films", "id": 130}] | O51: Walt Disney Pictures | P51: [{"iso_3166_1": "US", "name": "United States of America"}] | Q51: 40317 | R51: 2010 | S51: 335154643 | T51: 116 | U51: [{"iso_639_1": "en", "name": "English"}] | V51: Released | W51: Defy the Future | X51: 6.2 | Y51: 2317 | Z51: 185154643
A52: 180000000 | B52: [{ 28, name: Action}, { 878, name: Science Fiction}, { 12, name: Adventure}] | C52: Action | D52: Science Fiction | E52: Adventure | F52: - | G52: http://www.pacificrimmovie.com/ | H52: 68726 | I52: Pacific Rim | J52: [{"id": 4565, "name": "dystopia"}, {"id": 10891, "name": "giant robot"}, {"id": 11100, "name": "giant monster"}, {"id": 12332, "name": "apocalypse"}, {"id": 156395, "name": "imax"}, {"id": 179431, "name": "duringcreditsstinger"}, {"id": 209714, "name": "3d"}] | K52: en | L52: When legions of monstrous creatures, known as Kaiju, started rising from the sea, a war began that would take millions of lives and consume humanity's resources for years on end. To combat the giant Kaiju, a special type of weapon was devised: massive robots, called Jaegers, which are controlled simultaneously by two pilots whose minds are locked in a neural bridge. But even the Jaegers are proving nearly defenseless in the face of the relentless Kaiju. On the verge of defeat, the forces defending mankind have no choice but to turn to two unlikely heroesâ€”a washed-up former pilot (Charlie Hunnam) and an untested trainee (Rinko Kikuchi)â€”who are teamed to drive a legendary but seemingly obsolete Jaeger from the past. Together, they stand as mankind's last hope against the mounting apocalypse. | M52: 56523205 | N52: [{"name": "Legendary Pictures", "id": 923}, {"name": "Warner Bros.", "id": 6194}, {"name": "Disney Double Dare You (DDY)", "id": 19750}, {"name": "Indochina Productions", "id": 19751}] | O52: Legendary Pictures | P52: [{"iso_3166_1": "US", "name": "United States of America"}, {"iso_3166_1": "CA", "name": "Canada"}] | Q52: 41466 | R52: 2013 | S52: 407602906 | T52: 131 | U52: [{"iso_639_1": "en", "name": "English"}] | V52: Released | W52: To Fight Monsters, We Created Monsters | X52: 6.7 | Y52: 4794 | Z52: 227602906
A53: 195000000 | B53: [{ 28, name: Action}, { 878, name: Science Fiction}, { 12, name: Adventure}] | C53: Action | D53: Science Fiction | E53: Adventure | F53: - | G53: http://www.transformersmovie.com/ | H53: 38356 | I53: Transformers: Dark of the Moon | J53: [{"id": 305, "name": "moon"}, {"id": 1612, "name": "spacecraft"}, {"id": 2052, "name": "traitor"}, {"id": 3088, "name": "bodyguard"}, {"id": 10158, "name": "alien planet"}, {"id": 10244, "name": "based on cartoon"}, {"id": 10607, "name": "transformers"}, {"id": 10891, "name": "giant robot"}, {"id": 15246, "name": "sabotage"}, {"id": 15247, "name": "word domination"}, {"id": 15248, "name": "commando"}, {"id": 179431, "name": "duringcreditsstinger"}] | K53: en | L53: Sam Witwicky takes his first tenuous steps into adulthood while remaining a reluctant human ally of Autobot-leader Optimus Prime. The film centers around the space race between the USSR and the USA, suggesting there was a hidden Transformers role in it all that remains one of the planet's most dangerous secrets. | M53: 28529607 | N53: [{"name": "Paramount Pictures", "id": 4}, {"name": "Di Bonaventura Pictures", "id": 435}, {"name": "Indochina Productions", "id": 19751}, {"name": "Hasbro Studios", "id": 22826}] | O53: Paramount Pictures | P53: [{"iso_3166_1": "US", "name": "United States of America"}] | Q53: 40722 | R53: 2011 | S53: 1123746996 | T53: 154 | U53: [{"iso_639_1": "en", "name": "English"}] | V53: Released | W53: The invasion we always feared. An enemy we never expected. | X53: 6.1 | Y53: 3299 | Z53: 928746996
A54: 185000000 | B54: [{ 12, name: Adventure}, { 28, name: Action}] | C54: Adventure | D54: Action | E54: - | F54: - | G54: http://www.indianajones.com/site/index.html | H54: 217 | I54: Indiana Jones and the Kingdom of the Crystal Skull | J54: [{"id": 83, "name": "saving the world"}, {"id": 483, "name": "riddle"}, {"id": 1294, "name": "whip"}, {"id": 1454, "name": "treasure"}, {"id": 1547, "name": "mexico city"}, {"id": 2650, "name": "leather jacket"}, {"id": 4276, "name": "machinegun"}, {"id": 4939, "name": "alien phenomenons"}, {"id": 5566, "name": "maya civilization"}, {"id": 5967, "name": "peru"}, {"id": 6956, "name": "treasure hunt"}, {"id": 9830, "name": "nuclear explosion"}, {"id": 18524, "name": "refrigerator"}, {"id": 41586, "name": "archaeologist"}, {"id": 176731, "name": "indiana jones"}, {"id": 184134, "name": "archeology\u00a0"}] | K54: en | L54: Set during the Cold War, the Soviets â€“ led by sword-wielding Irina Spalko â€“ are in search of a crystal skull which has supernatural powers related to a mystical Lost City of Gold. After being captured and then escaping from them, Indy is coerced to head to Peru at the behest of a young man whose friend â€“ and Indy's colleague â€“ Professor Oxley has been captured for his knowledge of the skull's whereabouts. | M54: 75674458 | N54: [{"name": "Lucasfilm", "id": 1}, {"name": "Paramount Pictures", "id": 4}] | O54: Lucasfilm | P54: [{"iso_3166_1": "US", "name": "United States of America"}] | Q54: 39589 | R54: 2008 | S54: 786636033 | T54: 122 | U54: [{"iso_639_1": "en", "name": "English"}, {"iso_639_1": "de", "name": "Deutsch"}, {"iso_639_1": "ru", "name": "P\u0443\u0441\u0441\u043a\u0438\u0439"}] | V54: Released | W54: The adventure continues . . . | X54: 5.7 | Y54: 2495 | Z54: 601636033
A55: 175000000 | B55: [{ 12, name: Adventure}, { 16, name: Animation}, { 10751, name: Family}] | C55: Adventure | D55: Animation | E55: Family | F55: - | G55: http://movies.disney.com/the-good-dinosaur | H55: 105864 | I55: The Good Dinosaur | J55: [{"id": 1720, "name": "tyrannosaurus rex"}, {"id": 9713, "name": "friends"}, {"id": 12026, "name": "alternate history"}, {"id": 12616, "name": "dinosaur"}, {"id": 13073, "name": "fear"}, {"id": 14527, "name": "storm"}, {"id": 18330, "name": "nature"}, {"id": 187864, "name": "human"}, {"id": 189092, "name": "journey"}] | K55: en | L55: An epic journey into the world of dinosaurs where an Apatosaurus named Arlo makes an unlikely human friend. | M55: 51692953 | N55: [{"name": "Walt Disney Pictures", "id": 2}, {"name": "Pixar Animation Studios", "id": 3}] | O55: Walt Disney Pictures | P55: [{"iso_3166_1": "US", "name": "United States of America"}] | Q55: 42322 | R55: 2015 | S55: 331926147 | T55: 93 | U55: [{"iso_639_1": "en", "name": "English"}] | V55: Released | W55: Little Arms With Big Attitude | X55: 6.6 | Y55: 1736 | Z55: 156926147
A56: 185000000 | B56: [{ 16, name: Animation}, { 12, name: Adventure}, { 35, name: Comedy}, { 10751, name: Family}, { 28, name: Action}, { 14, name: Fantasy}] | C56: Animation | D56: Adventure | E56: Comedy | F56: Family | G56: http://disney.go.com/brave/#/home | H56: 62177 | I56: Brave | J56: [{"id": 388, "name": "scotland"}, {"id": 526, "name": "rebel"}, {"id": 3930, "name": "bravery"}, {"id": 4152, "name": "kingdom"}, {"id": 4393, "name": "archer"}, {"id": 4896, "name": "wish"}, {"id": 10468, "name": "bear"}, {"id": 14753, "name": "scot"}, {"id": 15161, "name": "rebellious daughter"}, {"id": 41538, "name": "turns into animal"}, {"id": 53995, "name": "archery"}, {"id": 162715, "name": "ruins"}, {"id": 179430, "name": "aftercreditsstinger"}, {"id": 181181, "name": "peace offering"}, {"id": 187056, "name": "woman director"}, {"id": 189098, "name": "courage"}, {"id": 209714, "name": "3d"}] | K56: en | L56: Brave is set in the mystical Scottish Highlands, where MÃ©rida is the princess of a kingdom ruled by King Fergus and Queen Elinor. An unruly daughter and an accomplished archer, MÃ©rida one day defies a sacred custom of the land and inadvertently brings turmoil to the kingdom. In an attempt to set things right, MÃ©rida seeks out an eccentric old Wise Woman and is granted an ill-fated wish. Also figuring into MÃ©ridaâ€™s quest â€” and serving as comic relief â€” are the kingdomâ€™s three lords: the enormous Lord MacGuffin, the surly Lord Macintosh, and the disagreeable Lord Dingwall. | M56: 125114374 | N56: [{"name": "Walt Disney Pictures", "id": 2}, {"name": "Pixar Animation Studios", "id": 3}] | O56: Walt Disney Pictures | P56: [{"iso_3166_1": "US", "name": "United States of America"}] | Q56: 41081 | R56: 2012 | S56: 538983207 | T56: 93 | U56: [{"iso_639_1": "en", "name": "English"}] | V56: Released | W56: Change your fate. | X56: 6.7 | Y56: 4641 | Z56: 353983207
A57: 185000000 | B57: [{ 28, name: Action}, { 12, name: Adventure}, { 878, name: Science Fiction}] | C57: Action | D57: Adventure | E57: Science Fiction | F57: - | G57: http://www.startrekmovie.com/ | H57: 188927 | I57: Star Trek Beyond | J57: [{"id": 9663, "name": "sequel"}, {"id": 9743, "name": "stranded"}, {"id": 158449, "name": "hatred"}, {"id": 161176, "name": "space opera"}] | K57: en | L57: The USS Enterprise crew explores the furthest reaches of uncharted space, where they encounter a mysterious new enemy who puts them and everything the Federation stands for to the test. | M57: 65352913 | N57: [{"name": "Paramount Pictures", "id": 4}, {"name": "Bad Robot", "id": 11461}, {"name": "Perfect Storm Entertainment", "id": 34530}, {"name": "Alibaba Pictures Group", "id": 69484}, {"name": "Skydance Media", "id": 82819}, {"name": "Sneaky Shark", "id": 83644}, {"name": "Huahua Media", "id": 83645}] | O57: Paramount Pictures | P57: [{"iso_3166_1": "US", "name": "United States of America"}] | Q57: 42558 | R57: 2016 | S57: 343471816 | T57: 122 | U57: [{"iso_639_1": "en", "name": "English"}] | V57: Released | X57: 6.6 | Y57: 2568 | Z57: 158471816
A58: 180000000 | B58: [{ 16, name: Animation}, { 10751, name: Family}] | C58: Animation | D58: Family | E58: - | F58: - | G58: http://disney.go.com/disneypictures/wall-e/ | H58: 10681 | I58: WALLÂ·E | J58: [{"id": 9799, "name": "romantic comedy"}] | K58: en | L58: WALLÂ·E is the last robot left on an Earth that has been overrun with garbage and all humans have fled to outer space. For 700 years he has continued to try and clean up the mess, but has developed some rather interesting human-like qualities. When a ship arrives with a sleek new type of robot, WALLÂ·E thinks he's finally found a friend and stows away on the ship when it leaves. | M58: 66390712 | N58: [{"name": "Walt Disney Pictures", "id": 2}, {"name": "Pixar Animation Studios", "id": 3}, {"name": "FortyFour Studios", "id": 93408}] | O58: Walt Disney Pictures | P58: [{"iso_3166_1": "US", "name": "United States of America"}] | Q58: 39621 | R58: 2008 | S58: 521311860 | T58: 98 | U58: [{"iso_639_1": "en", "name": "English"}] | V58: Released | W58: An adventure beyond the ordinar-E. | X58: 7.8 | Y58: 6296 | Z58: 341311860
A59: 140000000 | B59: [{ 28, name: Action}, { 35, name: Comedy}, { 80, name: Crime}, { 53, name: Thriller}] | C59: Action | D59: Comedy | E59: Crime | F59: Thriller | H59: 5174 | I59: Rush Hour 3 | J59: [{"id": 1704, "name": "ambassador"}] | K59: en | L59: After an attempted assassination on Ambassador Han, Inspector Lee and Detective Carter are back in action as they head to Paris to protect a French woman with knowledge of the Triads' secret leaders. Lee also holds secret meetings with a United Nations authority, but his personal struggles with a Chinese criminal mastermind named Kenji, which reveals that it's Lee's long-lost...brother. | M59: 2257178 | N59: [{"name": "New Line Cinema", "id": 12}] | O59: New Line Cinema | P59: [{"iso_3166_1": "US", "name": "United States of America"}] | Q59: 39302 | R59: 2007 | S59: 258022233 | T59: 91 | U59: [{"iso_639_1": "la", "name": "Latin"}, {"iso_639_1": "en", "name": "English"}, {"iso_639_1": "fr", "name": "Fran\u00e7ais"}, {"iso_639_1": "ja", "name": "\u65e5\u672c\u8a9e"}, {"iso_639_1": "zh", "name": "\u666e\u901a\u8bdd"}] | V59: Released | W59: The Rush Is On! | X59: 6.1 | Y59: 783 | Z59: 118022233
A60: 200000000 | B60: [{ 28, name: Action}, { 12, name: Adventure}, { 878, name: Science Fiction}] | C60: Action | D60: Adventure | E60: Science Fiction | F60: - | G60: http://www.sonypictures.com/movies/2012 | H60: 14161 | I60: 2012 | J60: [{"id": 2163, "name": "civilization"}, {"id": 5096, "name": "natural disaster"}, {"id": 10150, "name": "end of the world"}, {"id": 10617, "name": "disaster"}, {"id": 12332, "name": "apocalypse"}, {"id": 14796, "name": "destruction"}, {"id": 163398, "name": "volcanic eruption"}, {"id": 208090, "name": "mayan"}, {"id": 230910, "name": "ark"}, {"id": 232318, "name": "solar"}, {"id": 232339, "name": "destruction of mankind"}] | K60: en | L60: Dr. Adrian Helmsley, part of a worldwide geophysical team investigating the effect on the earth of radiation from unprecedented solar storms, learns that the earth's core is heating up. He warns U.S. President Thomas Wilson that the crust of the earth is becoming unstable and that without proper preparations for saving a fraction of the world's population, the entire race is doomed. Meanwhile, writer Jackson Curtis stumbles on the same information. While the world's leaders race to build "arks" to escape the impending cataclysm, Curtis struggles to find a way to save his family. Meanwhile, volcanic eruptions and earthquakes of unprecedented strength wreak havoc around the world. | M60: 45274225 | N60: [{"name": "Columbia Pictures", "id": 5}, {"name": "Centropolis Entertainment", "id": 347}, {"name": "The Mark Gordon Company", "id": 1557}, {"name": "Farewell Productions", "id": 10905}] | O60: Columbia Pictures | P60: [{"iso_3166_1": "CA", "name": "Canada"}, {"iso_3166_1": "US", "name": "United States of America"}] | Q60: 40096 | R60: 2009 | S60: 769653595 | T60: 158 | U60: [{"iso_639_1": "en", "name": "English"}, {"iso_639_1": "fr", "name": "Fran\u00e7ais"}, {"iso_639_1": "hi", "name": "\u0939\u093f\u0928\u094d\u0926\u0940"}, {"iso_639_1": "it", "name": "Italiano"}, {"iso_639_1": "la", "name": "Latin"}, {"iso_639_1": "zh", "name": "\u666e\u901a\u8bdd"}, {"iso_639_1": "pt", "name": "Portugu\u00eas"}, {"iso_639_1": "ru", "name": "P\u0443\u0441\u0441\u043a\u0438\u0439"}, {"iso_639_1": "bo", "name": ""}] | V60: Released | W60: We Were Warned. | X60: 5.6 | Y60: 4903 | Z60: 569653595
A61: 200000000 | B61: [{ 16, name: Animation}, { 18, name: Drama}] | C61: Animation | D61: Drama | E61: - | F61: - | G61: http://disney.go.com/disneypictures/achristmascarol/?cmp=dcom_VAN_WDSHE_ACC_van_dcomcc__Extl | H61: 17979 | I61: A Christmas Carol | J61: [{"id": 65, "name": "holiday"}, {"id": 818, "name": "based on novel"}, {"id": 8250, "name": "victorian england"}, {"id": 10594, "name": "money"}, {"id": 33965, "name": "christmas eve"}, {"id": 33966, "name": "scrooge"}, {"id": 161174, "name": "christmas carol"}, {"id": 162846, "name": "ghost"}, {"id": 170457, "name": "lesson"}, {"id": 180975, "name": "charles dickens"}, {"id": 207317, "name": "christmas"}] | K61: en | L61: Miser Ebenezer Scrooge is awakened on Christmas Eve by spirits who reveal to him his own miserable existence, what opportunities he wasted in his youth, his current cruelties, and the dire fate that awaits him if he does not change his ways. Scrooge is faced with his own story of growing bitterness and meanness, and must decide what his own future will hold: death or redemption. | M61: 39744242 | N61: [{"name": "Walt Disney", "id": 5888}, {"name": "ImageMovers", "id": 11395}] | O61: Walt Disney | P61: [{"iso_3166_1": "US", "name": "United States of America"}] | Q61: 40121 | R61: 2009 | S61: 325233863 | T61: 96 | U61: [{"iso_639_1": "en", "name": "English"}] | V61: Released | W61: Season's Greedings | X61: 6.6 | Y61: 1095 | Z61: 125233863
A62: 176000003 | B62: [{ 878, name: Science Fiction}, { 14, name: Fantasy}, { 28, name: Action}, { 12, name: Adventure}] | C62: Science Fiction | D62: Fantasy | E62: Action | F62: Adventure | G62: http://www.jupiterascending.com | H62: 76757 | I62: Jupiter Ascending | J62: [{"id": 306, "name": "jupiter"}, {"id": 9882, "name": "space"}, {"id": 187056, "name": "woman director"}, {"id": 209714, "name": "3d"}, {"id": 212760, "name": "interspecies romance"}] | K62: en | L62: In a universe where human genetic material is the most precious commodity, an impoverished young Earth woman becomes the key to strategic maneuvers and internal strife within a powerful dynastyâ€¦ | M62: 8536908 | N62: [{"name": "Village Roadshow Pictures", "id": 79}, {"name": "Dune Entertainment", "id": 444}, {"name": "Anarchos Productions", "id": 450}, {"name": "Warner Bros.", "id": 6194}] | O62: Village Roadshow Pictures | P62: [{"iso_3166_1": "US", "name": "United States of America"}] | Q62: 42039 | R62: 2015 | S62: 183987723 | T62: 124 | U62: [{"iso_639_1": "en", "name": "English"}] | V62: Released | W62: Expand your universe. | X62: 5.2 | Y62: 2768 | Z62: 7987720
A63: 180000000 | B63: [{ 28, name: Action}, { 12, name: Adventure}] | C63: Action | D63: Adventure | E63: - | F63: - | G63: http://legendoftarzan.com | H63: 258489 | I63: The Legend of Tarzan | J63: [{"id": 409, "name": "africa"}, {"id": 5650, "name": "feral child"}, {"id": 7347, "name": "tarzan"}, {"id": 10787, "name": "jungle"}, {"id": 158130, "name": "animal attack"}] | K63: en | L63: Tarzan, having acclimated to life in London, is called back to his former home in the jungle to investigate the activities at a mining encampment. | M63: 42741719 | N63: [{"name": "Village Roadshow Pictures", "id": 79}, {"name": "Dark Horse Entertainment", "id": 552}, {"name": "Jerry Weintraub Productions", "id": 2596}, {"name": "RatPac-Dune Entertainment", "id": 41624}, {"name": "Beagle Pug Films", "id": 46339}, {"name": "Riche Productions", "id": 86565}, {"name": "Village Roadshow Films North America", "id": 86566}] | O63: Village Roadshow Pictures | P63: [{"iso_3166_1": "CA", "name": "Canada"}, {"iso_3166_1": "GB", "name": "United Kingdom"}, {"iso_3166_1": "US", "name": "United States of America"}] | Q63: 42550 | R63: 2016 | S63: 356743061 | T63: 109 | U63: [{"iso_639_1": "en", "name": "English"}] | V63: Released | W63: Human. Nature. | X63: 5.5 | Y63: 2430 | Z63: 176743061
A64: 180000000 | B64: [{ 12, name: Adventure}, { 10751, name: Family}, { 14, name: Fantasy}] | C64: Adventure | D64: Family | E64: Fantasy | F64: - | H64: 411 | I64: The Chronicles of Narnia: The Lion, the Witch and the Wardrobe | J64: [{"id": 83, "name": "saving the world"}, {"id": 616, "name": "witch"}, {"id": 818, "name": "based on novel"}, {"id": 1155, "name": "brother sister relationship"}, {"id": 1430, "name": "self sacrifice"}, {"id": 1442, "name": "winter"}, {"id": 1990, "name": "cupboard"}, {"id": 2042, "name": "beaver"}, {"id": 2043, "name": "lion"}, {"id": 6187, "name": "fairy-tale figure"}, {"id": 14643, "name": "battle"}, {"id": 166930, "name": "narnia"}, {"id": 170362, "name": "fantasy world"}, {"id": 179431, "name": "duringcreditsstinger"}] | K64: en | L64: Siblings Lucy, Edmund, Susan and Peter step through a magical wardrobe and find the land of Narnia. There, the they discover a charming, once peaceful kingdom that has been plunged into eternal winter by the evil White Witch, Jadis. Aided by the wise and magnificent lion, Aslan, the children lead Narnia into a spectacular, climactic battle to be free of the Witch's glacial powers forever. | M64: 67391328 | N64: [{"name": "Walt Disney", "id": 5888}, {"name": "Walden Media", "id": 10221}] | O64: Walt Disney | P64: [{"iso_3166_1": "GB", "name": "United Kingdom"}, {"iso_3166_1": "US", "name": "United States of America"}] | Q64: 38693 | R64: 2005 | S64: 748806957 | T64: 143 | U64: [{"iso_639_1": "en", "name": "English"}, {"iso_639_1": "de", "name": "Deutsch"}] | V64: Released | W64: Evil Has Reigned For 100 Years... | X64: 6.7 | Y64: 2629 | Z64: 568806957
A65: 178000000 | B65: [{ 878, name: Science Fiction}] | C65: Science Fiction | D65: - | E65: - | F65: - | G65: http://www.foxmovies.com/movies/x-men-apocalypse | H65: 246655 | I65: X-Men: Apocalypse | J65: [{"id": 1852, "name": "mutant"}, {"id": 4769, "name": "supernatural powers"}, {"id": 8828, "name": "marvel comic"}, {"id": 9715, "name": "superhero"}, {"id": 9717, "name": "based on comic book"}, {"id": 10761, "name": "superhuman"}, {"id": 12332, "name": "apocalypse"}, {"id": 155030, "name": "superhero team"}, {"id": 176217, "name": "world domination"}, {"id": 179430, "name": "aftercreditsstinger"}, {"id": 208289, "name": "1980s"}] | K65: en | L65: After the re-emergence of the world's first mutant, world-destroyer Apocalypse, the X-Men must unite to defeat his extinction level plan. | M65: 139272042 | N65: [{"name": "Twentieth Century Fox Film Corporation", "id": 306}, {"name": "Donners' Company", "id": 431}, {"name": "Marvel Entertainment", "id": 7505}, {"name": "Bad Hat Harry Productions", "id": 9168}, {"name": "TSG Entertainment", "id": 22213}, {"name": "Kinberg Genre", "id": 78091}] | O65: Twentieth Century Fox Film Corporation | P65: [{"iso_3166_1": "US", "name": "United States of America"}] | Q65: 42508 | R65: 2016 | S65: 543934787 | T65: 144 | U65: [{"iso_639_1": "en", "name": "English"}] | V65: Released | W65: Only the strong will survive | X65: 6.4 | Y65: 4721 | Z65: 365934787
A66: 185000000 | B66: [{ 18, name: Drama}, { 28, name: Action}, { 80, name: Crime}, { 53, name: Thriller}] | C66: Drama | D66: Action | E66: Crime | F66: Thriller | G66: http://thedarkknight.warnerbros.com/dvdsite/ | H66: 155 | I66: The Dark Knight | J66: [{"id": 849, "name": "dc comics"}, {"id": 853, "name": "crime fighter"}, {"id": 1308, "name": "secret identity"}, {"id": 3151, "name": "scarecrow"}, {"id": 4426, "name": "sadism"}, {"id": 4630, "name": "chaos"}, {"id": 6969, "name": "gotham city"}, {"id": 7002, "name": "vigilante"}, {"id": 9537, "name": "joker"}, {"id": 9715, "name": "superhero"}, {"id": 9717, "name": "based on comic book"}, {"id": 10044, "name": "tragic hero"}, {"id": 10291, "name": "organized crime"}, {"id": 18023, "name": "criminal mastermind"}, {"id": 33518, "name": "district attorney"}, {"id": 156395, "name": "imax"}, {"id": 163074, "name": "super villain"}, {"id": 163455, "name": "super powers"}, {"id": 230775, "name": "batman"}] | K66: en | L66: Batman raises the stakes in his war on crime. With the help of Lt. Jim Gordon and District Attorney Harvey Dent, Batman sets out to dismantle the remaining criminal organizations that plague the streets. The partnership proves to be effective, but they soon find themselves prey to a reign of chaos unleashed by a rising criminal mastermind known to the terrified citizens of Gotham as the Joker. | M66: 187322927 | N66: [{"name": "DC Comics", "id": 429}, {"name": "Legendary Pictures", "id": 923}, {"name": "Warner Bros.", "id": 6194}, {"name": "DC Entertainment", "id": 9993}, {"name": "Syncopy", "id": 9996}] | O66: DC Comics | P66: [{"iso_3166_1": "GB", "name": "United Kingdom"}, {"iso_3166_1": "US", "name": "United States of America"}] | Q66: 39645 | R66: 2008 | S66: 1004558444 | T66: 152 | U66: [{"iso_639_1": "en", "name": "English"}, {"iso_639_1": "zh", "name": "\u666e\u901a\u8bdd"}] | V66: Released | W66: Why So Serious? | X66: 8.2 | Y66: 12002 | Z66: 819558444
A67: 175000000 | B67: [{ 16, name: Animation}, { 35, name: Comedy}, { 10751, name: Family}, { 12, name: Adventure}] | C67: Animation | D67: Comedy | E67: Family | F67: Adventure | G67: http://disney.go.com/disneypictures/up/ | H67: 14160 | I67: Up | J67: [{"id": 965, "name": "age difference"}, {"id": 1291, "name": "central and south america"}, {"id": 9903, "name": "balloon"}, {"id": 10336, "name": "animation"}, {"id": 175715, "name": "floating in the air"}, {"id": 179431, "name": "duringcreditsstinger"}, {"id": 221536, "name": "exploring"}] | K67: en | L67: Carl Fredricksen spent his entire life dreaming of exploring the globe and experiencing life to its fullest. But at age 78, life seems to have passed him by, until a twist of fate (and a persistent 8-year old Wilderness Explorer named Russell) gives him a new lease on life. | M67: 92201962 | N67: [{"name": "Pixar Animation Studios", "id": 3}] | O67: Pixar Animation Studios | P67: [{"iso_3166_1": "US", "name": "United States of America"}] | Q67: 39946 | R67: 2009 | S67: 735099082 | T67: 96 | U67: [{"iso_639_1": "en", "name": "English"}] | V67: Released | X67: 7.7 | Y67: 6870 | Z67: 560099082
A68: 175000000 | B68: [{ 16, name: Animation}, { 10751, name: Family}, { 12, name: Adventure}, { 878, name: Science Fiction}] | C68: Animation | D68: Family | E68: Adventure | F68: Science Fiction | G68: http://www.monstersvsaliens.com/ | H68: 15512 | I68: Monsters vs Aliens | J68: [{"id": 9951, "name": "alien"}, {"id": 10891, "name": "giant robot"}, {"id": 179431, "name": "duringcreditsstinger"}] | K68: en | L68: When Susan Murphy is unwittingly clobbered by a meteor full of outer space gunk on her wedding day, she mysteriously grows to 49-feet-11-inches. The military jumps into action and captures Susan, secreting her away to a covert government compound. She is renamed Ginormica and placed in confinement with a ragtag group of Monsters... | M68: 36167578 | N68: [{"name": "DreamWorks Animation", "id": 521}] | O68: DreamWorks Animation | P68: [{"iso_3166_1": "US", "name": "United States of America"}] | Q68: 39891 | R68: 2009 | S68: 381509870 | T68: 94 | U68: [{"iso_639_1": "en", "name": "English"}] | V68: Released | W68: When aliens attack, monsters fight back. | X68: 6.0 | Y68: 1423 | Z68: 206509870
A69: 140000000 | B69: [{ 28, name: Action}, { 878, name: Science Fiction}, { 12, name: Adventure}] | C69: Action | D69: Science Fiction | E69: Adventure | F69: - | G69: http://www.ironmanmovie.com/ | H69: 1726 | I69: Iron Man | J69: [{"id": 539, "name": "middle east"}, {"id": 6163, "name": "arms dealer"}, {"id": 8613, "name": "malibu"}, {"id": 8828, "name": "marvel comic"}, {"id": 9715, "name": "superhero"}, {"id": 9717, "name": "based on comic book"}, {"id": 12555, "name": "tony stark"}, {"id": 173776, "name": "iron man"}, {"id": 179430, "name": "aftercreditsstinger"}, {"id": 180547, "name": "marvel cinematic universe"}, {"id": 208630, "name": "counter terrorism"}, {"id": 209756, "name": "agent coulson"}] | K69: en | L69: After being held captive in an Afghan cave, billionaire engineer Tony Stark creates a unique weaponized suit of armor to fight evil. | M69: 120725053 | N69: [{"name": "Marvel Studios", "id": 420}] | O69: Marvel Studios | P69: [{"iso_3166_1": "US", "name": "United States of America"}] | Q69: 39568 | R69: 2008 | S69: 585174222 | T69: 126 | U69: [{"iso_639_1": "en", "name": "English"}, {"iso_639_1": "fa", "name": "\u0641\u0627\u0631\u0633\u06cc"}, {"iso_639_1": "ur", "name": "\u0627\u0631\u062f\u0648"}, {"iso_639_1": "ar", "name": "\u0627\u0644\u0639\u0631\u0628\u064a\u0629"}] | V69: Released | W69: Heroes aren't born. They're built. | X69: 7.4 | Y69: 8776 | Z69: 445174222
A70: 170000000 | B70: [{ 12, name: Adventure}, { 18, name: Drama}, { 10751, name: Family}] | C70: Adventure | D70: Drama | E70: Family | F70: - | G70: http://www.hugomovie.com/ | H70: 44826 | I70: Hugo | J70: [{"id": 295, "name": "library"}, {"id": 1507, "name": "clock"}, {"id": 2793, "name": "film director"}, {"id": 2849, "name": "key"}, {"id": 4290, "name": "toy"}, {"id": 5202, "name": "boy"}, {"id": 9673, "name": "love"}, {"id": 13014, "name": "orphan"}, {"id": 14544, "name": "robot"}, {"id": 14545, "name": "automaton"}, {"id": 18028, "name": "hiding"}, {"id": 33490, "name": "filmmaking"}, {"id": 41372, "name": "leg brace"}, {"id": 156149, "name": "doberman"}, {"id": 209714, "name": "3d"}] | K70: en | L70: Hugo is an orphan boy living in the walls of a train station in 1930s Paris. He learned to fix clocks and other gadgets from his father and uncle which he puts to use keeping the train station clocks running. The only thing that he has left that connects him to his dead father is an automaton (mechanical man) that doesn't work without a special key which Hugo needs to find to unlock the secret he believes it contains. On his adventures, he meets with a shopkeeper, George Melies, who works in the train station and his adventure-seeking god-daughter. Hugo finds that they have a surprising connection to his father and the automaton, and he discovers it unlocks some memories the old man has buried inside regarding his past. | M70: 32319043 | N70: [{"name": "Paramount Pictures", "id": 4}, {"name": "Infinitum Nihil", "id": 2691}, {"name": "GK Films", "id": 3281}] | O70: Paramount Pictures | P70: [{"iso_3166_1": "FR", "name": "France"}, {"iso_3166_1": "US", "name": "United States of America"}, {"iso_3166_1": "GB", "name": "United Kingdom"}] | Q70: 40869 | R70: 2011 | S70: 185770160 | T70: 126 | U70: [{"iso_639_1": "en", "name": "English"}] | V70: Released | W70: One of the most legendary directors of our time takes you on an extraordinary adventure. | X70: 7.0 | Y70: 2141 | Z70: 15770160
A71: 170000000 | B71: [{ 28, name: Action}, { 12, name: Adventure}, { 35, name: Comedy}, { 878, name: Science Fiction}, { 37, name: Western}] | C71: Action | D71: Adventure | E71: Comedy | F71: Science Fiction | H71: 8487 | I71: Wild Wild West | J71: [{"id": 10028, "name": "steampunk"}, {"id": 10988, "name": "based on tv series"}, {"id": 163671, "name": "steam locomotive"}, {"id": 171636, "name": "drag"}] | K71: en | L71: Legless Southern inventor Dr. Arliss Loveless plans to rekindle the Civil War by assassinating President U.S. Grant. Only two men can stop him: gunfighter James West and master-of-disguise and inventor Artemus Gordon. The two must team up to thwart Loveless' plans. | M71: 40748915 | N71: [{"name": "Todman, Simon, LeMasters Productions", "id": 2507}, {"name": "Warner Bros.", "id": 6194}, {"name": "Peters Entertainment", "id": 16774}, {"name": "Sonnenfeld Josephson Worldwide Entertainment", "id": 57088}] | O71: Todma | P71: [{"iso_3166_1": "US", "name": "United States of America"}] | Q71: 36340 | R71: 1999 | S71: 222104681 | T71: 106 | U71: [{"iso_639_1": "en", "name": "English"}] | V71: Released | W71: It's a whole new west. | X71: 5.1 | Y71: 1020 | Z71: 52104681
A72: 40000000 | B72: [{ 28, name: Action}, { 878, name: Science Fiction}] | C72: Action | D72: Science Fiction | E72: - | F72: - | G72: http://lucymovie.com/ | H72: 240832 | I72: Lucy | J72: [{"id": 310, "name": "artificial intelligence"}, {"id": 1475, "name": "telepathy"}, {"id": 2051, "name": "intelligence"}, {"id": 2235, "name": "drug mule"}, {"id": 5086, "name": "telekinesis"}, {"id": 9685, "name": "futuristic"}, {"id": 14964, "name": "drug"}, {"id": 33637, "name": "superpower"}, {"id": 34009, "name": "tough girl"}, {"id": 156395, "name": "imax"}, {"id": 157959, "name": "surgery"}, {"id": 234944, "name": "brain capacity"}, {"id": 234945, "name": "synthetic drug"}, {"id": 234946, "name": "human brain"}] | K72: en | L72: A woman, accidentally caught in a dark deal, turns the tables on her captors and transforms into a merciless warrior evolved beyond human logic. | M72: 115241998 | N72: [{"name": "Universal Pictures", "id": 33}, {"name": "TF1 Films Production", "id": 3823}, {"name": "Canal+", "id": 5358}, {"name": "EuropaCorp", "id": 6896}, {"name": "Cin\u00e9+", "id": 23616}] | O72: Universal Pictures | P72: [{"iso_3166_1": "FR", "name": "France"}, {"iso_3166_1": "US", "name": "United States of America"}] | Q72: 41834 | R72: 2014 | S72: 126546825 | T72: 89 | U72: [{"iso_639_1": "zh", "name": "\u666e\u901a\u8bdd"}, {"iso_639_1": "en", "name": "English"}, {"iso_639_1": "fr", "name": "Fran\u00e7ais"}, {"iso_639_1": "es", "name": "Espa\u00f1ol"}, {"iso_639_1": "ko", "name": "\ud55c\uad6d\uc5b4/\uc870\uc120\ub9d0"}] | V72: Released | W72: The average person uses 10% of their brain capacity. Imagine what she could do with 100%. | X72: 6.3 | Y72: 5878 | Z72: 86546825
A73: 175000000 | B73: [{ 28, name: Action}, { 12, name: Adventure}, { 80, name: Crime}, { 14, name: Fantasy}, { 878, name: Science Fiction}] | C73: Action | D73: Adventure | E73: Crime | F73: Fantasy | G73: http://www.suicidesquad.com/ | H73: 297761 | I73: Suicide Squad | J73: [{"id": 849, "name": "dc comics"}, {"id": 1296, "name": "shared universe"}, {"id": 2095, "name": "anti hero"}, {"id": 3269, "name": "secret mission"}, {"id": 3289, "name": "villain"}, {"id": 9715, "name": "superhero"}, {"id": 194404, "name": "supervillain"}, {"id": 229266, "name": "dc extended universe"}] | K73: en | L73: From DC Comics comes the Suicide Squad, an antihero team of incarcerated supervillains who act as deniable assets for the United States government, undertaking high-risk black ops missions in exchange for commuted prison sentences. | M73: 9023792 | N73: [{"name": "DC Comics", "id": 429}, {"name": "Dune Entertainment", "id": 444}, {"name": "Atlas Entertainment", "id": 507}, {"name": "Warner Bros.", "id": 6194}, {"name": "DC Entertainment", "id": 9993}] | O73: DC Comics | P73: [{"iso_3166_1": "US", "name": "United States of America"}] | Q73: 42584 | R73: 2016 | S73: 745000000 | T73: 123 | U73: [{"iso_639_1": "en", "name": "English"}] | V73: Released | W73: Worst Heroes Ever | X73: 5.9 | Y73: 7458 | Z73: 570000000
A74: 175000000 | B74: [{ 14, name: Fantasy}, { 35, name: Comedy}, { 10751, name: Family}] | C74: Fantasy | D74: Comedy | E74: Family | F74: - | G74: http://www.evanalmighty.com/ | H74: 2698 | I74: Evan Almighty | J74: [{"id": 494, "name": "father son relationship"}, {"id": 1850, "name": "daily life"}, {"id": 2587, "name": "married couple"}, {"id": 3848, "name": "support"}, {"id": 5905, "name": "father"}, {"id": 6038, "name": "marriage"}, {"id": 6150, "name": "faith"}, {"id": 6603, "name": "baustelle"}, {"id": 10084, "name": "rescue"}, {"id": 18165, "name": "animal"}, {"id": 18330, "name": "nature"}, {"id": 179431, "name": "duringcreditsstinger"}, {"id": 210450, "name": "noah's ark"}] | K74: en | L74: God contacts Congressman Evan Baxter and tells him to build an ark in preparation for a great flood. | M74: 27082182 | N74: [{"name": "Columbia Pictures", "id": 5}, {"name": "Universal Pictures", "id": 33}, {"name": "Spyglass Entertainment", "id": 158}, {"name": "Shady Acres Entertainment", "id": 159}, {"name": "Original Film", "id": 333}, {"name": "Playtone", "id": 4171}, {"name": "Relativity Media", "id": 7295}] | O74: Columbia Pictures | P74: [{"iso_3166_1": "US", "name": "United States of America"}] | Q74: 39242 | R74: 2007 | S74: 173000000 | T74: 96 | U74: [{"iso_639_1": "en", "name": "English"}] | V74: Released | W74: A comedy of biblical proportions | X74: 5.3 | Y74: 1151 | Z74: -2000000
A75: 178000000 | B75: [{ 28, name: Action}, { 878, name: Science Fiction}] | C75: Action | D75: Science Fiction | E75: - | F75: - | G75: http://www.edgeoftomorrowmovie.com/ | H75: 137113 | I75: Edge of Tomorrow | J75: [{"id": 563, "name": "deja vu"}, {"id": 1521, "name": "time warp"}, {"id": 2062, "name": "restart"}, {"id": 4565, "name": "dystopia"}, {"id": 6091, "name": "war"}, {"id": 9951, "name": "alien"}, {"id": 11109, "name": "military officer"}, {"id": 13065, "name": "soldier"}, {"id": 14909, "name": "alien invasion"}, {"id": 204318, "name": "exoskeleton"}] | K75: en | L75: Major Bill Cage is an officer who has never seen a day of combat when he is unceremoniously demoted and dropped into combat. Cage is killed within minutes, managing to take an alpha alien down with him. He awakens back at the beginning of the same day and is forced to fight and die again... and again - as physical contact with the alien has thrown him into a time loop. | M75: 79456485 | N75: [{"name": "Village Roadshow Pictures", "id": 79}, {"name": "Warner Bros.", "id": 6194}, {"name": "Viz Media", "id": 6687}, {"name": "Province of British Columbia Production Services Tax Credit", "id": 12200}, {"name": "3 Arts Entertainment", "id": 36390}, {"name": "RatPac-Dune Entertainment", "id": 41624}] | O75: Village Roadshow Pictures | P75: [{"iso_3166_1": "AU", "name": "Australia"}, {"iso_3166_1": "US", "name": "United States of America"}] | Q75: 41786 | R75: 2014 | S75: 370541256 | T75: 113 | U75: [{"iso_639_1": "en", "name": "English"}] | V75: Released | W75: Live, Die, Repeat | X75: 7.6 | Y75: 4858 | Z75: 192541256
A76: 69000000 | B76: [{ 16, name: Animation}, { 10751, name: Family}] | C76: Animation | D76: Family | E76: - | F76: - | G76: http://www.despicable.me/ | H76: 20352 | I76: Despicable Me | J76: [{"id": 4130, "name": "adoptive father"}, {"id": 6783, "name": "orphanage"}, {"id": 7393, "name": "life's dream"}, {"id": 9823, "name": "rivalry"}, {"id": 10261, "name": "stealing"}, {"id": 10551, "name": "ballet"}, {"id": 12663, "name": "little girl"}, {"id": 13014, "name": "orphan"}, {"id": 15300, "name": "father daughter relationship"}, {"id": 156928, "name": "tomboy"}, {"id": 157499, "name": "mother son relationship"}, {"id": 160097, "name": "intelligent"}, {"id": 161155, "name": "kids"}, {"id": 179095, "name": "evil doctor"}, {"id": 179431, "name": "duringcreditsstinger"}, {"id": 190999, "name": "minions"}, {"id": 194404, "name": "supervillain"}, {"id": 209714, "name": "3d"}, {"id": 219832, "name": "despicable"}, {"id": 235459, "name": "cattivissimo"}] | K76: en | L76: Villainous Gru lives up to his reputation as a despicable, deplorable and downright unlikable guy when he hatches a plan to steal the moon from the sky. But he has a tough time staying on task after three orphans land in his care. | M76: 113858273 | N76: [{"name": "Universal Pictures", "id": 33}, {"name": "Illumination Entertainment", "id": 6704}] | O76: Universal Pictures | P76: [{"iso_3166_1": "US", "name": "United States of America"}] | Q76: 40367 | R76: 2010 | S76: 543513985 | T76: 95 | U76: [{"iso_639_1": "en", "name": "English"}] | V76: Released | W76: Superbad. Superdad. | X76: 7.1 | Y76: 6478 | Z76: 474513985
A77: 175000000 | B77: [{ 12, name: Adventure}, { 28, name: Action}, { 53, name: Thriller}, { 878, name: Science Fiction}] | C77: Adventure | D77: Action | E77: Thriller | F77: Science Fiction | G77: http://www.gijoemovie.com/ | H77: 14869 | I77: G.I. Joe: The Rise of Cobra | J77: [{"id": 949, "name": "terrorist"}, {"id": 1328, "name": "secret"}, {"id": 1562, "name": "hostage"}, {"id": 1576, "name": "technology"}, {"id": 3467, "name": "warhead"}, {"id": 6086, "name": "government"}, {"id": 8570, "name": "president"}, {"id": 9748, "name": "revenge"}, {"id": 9826, "name": "murder"}, {"id": 10563, "name": "attack"}, {"id": 14601, "name": "explosion"}, {"id": 14760, "name": "scientist"}, {"id": 155551, "name": "lasers"}, {"id": 156075, "name": "evil"}, {"id": 191574, "name": "cobra"}] | K77: en | L77: From the Egyptian desert to deep below the polar ice caps, the elite G.I. JOE team uses the latest in next-generation spy and military equipment to fight the corrupt arms dealer Destro and the growing threat of the mysterious Cobra organization to prevent them from plunging the world into chaos. | M77: 32852443 | N77: [{"name": "Paramount Pictures", "id": 4}, {"name": "Spyglass Entertainment", "id": 158}, {"name": "Di Bonaventura Pictures", "id": 435}, {"name": "Hasbro", "id": 2598}, {"name": "Kontsept Film Company", "id": 76067}] | O77: Paramount Pictures | P77: [{"iso_3166_1": "CZ", "name": "Czech Republic"}, {"iso_3166_1": "US", "name": "United States of America"}] | Q77: 40029 | R77: 2009 | S77: 302469017 | T77: 118 | U77: [{"iso_639_1": "en", "name": "English"}, {"iso_639_1": "fr", "name": "Fran\u00e7ais"}, {"iso_639_1": "gd", "name": ""}] | V77: Released | W77: When all else fails, they don't. | X77: 5.6 | Y77: 1962 | Z77: 127469017
A78: 175000000 | B78: [{ 18, name: Drama}, { 35, name: Comedy}, { 16, name: Animation}, { 10751, name: Family}] | C78: Drama | D78: Comedy | E78: Animation | F78: Family | G78: http://movies.disney.com/inside-out | H78: 150540 | I78: Inside Out | J78: [{"id": 1566, "name": "dream"}, {"id": 6513, "name": "cartoon"}, {"id": 7942, "name": "imaginary friend"}, {"id": 10336, "name": "animation"}, {"id": 18035, "name": "family"}, {"id": 18253, "name": "moving"}, {"id": 161155, "name": "kids"}, {"id": 163227, "name": "unicorn"}, {"id": 179431, "name": "duringcreditsstinger"}, {"id": 209714, "name": "3d"}, {"id": 211269, "name": "emotions"}] | K78: en | L78: Growing up can be a bumpy road, and it's no exception for Riley, who is uprooted from her Midwest life when her father starts a new job in San Francisco. Like all of us, Riley is guided by her emotions - Joy, Fear, Anger, Disgust and Sadness. The emotions live in Headquarters, the control center inside Riley's mind, where they help advise her through everyday life. As Riley and her emotions struggle to adjust to a new life in San Francisco, turmoil ensues in Headquarters. Although Joy, Riley's main and most important emotion, tries to keep things positive, the emotions conflict on how best to navigate a new city, house and school. | M78: 128655964 | N78: [{"name": "Walt Disney Pictures", "id": 2}, {"name": "Pixar Animation Studios", "id": 3}] | O78: Walt Disney Pictures | P78: [{"iso_3166_1": "US", "name": "United States of America"}] | Q78: 42164 | R78: 2015 | S78: 857611174 | T78: 94 | U78: [{"iso_639_1": "en", "name": "English"}] | V78: Released | W78: Meet the little voices inside your head. | X78: 8.0 | Y78: 6560 | Z78: 682611174
A79: 175000000 | B79: [{ 10751, name: Family}, { 12, name: Adventure}, { 18, name: Drama}, { 14, name: Fantasy}] | C79: Family | D79: Adventure | E79: Drama | F79: Fantasy | G79: http://movies.disney.com/the-jungle-book-2016 | H79: 278927 | I79: The Jungle Book | J79: [{"id": 818, "name": "based on novel"}, {"id": 1585, "name": "snake"}, {"id": 1994, "name": "wolf"}, {"id": 2857, "name": "elephant"}, {"id": 4809, "name": "tiger"}, {"id": 5650, "name": "feral child"}, {"id": 8775, "name": "panther"}, {"id": 9714, "name": "remake"}, {"id": 10468, "name": "bear"}, {"id": 10787, "name": "jungle"}, {"id": 11477, "name": "talking animal"}, {"id": 13014, "name": "orphan"}, {"id": 18165, "name": "animal"}, {"id": 167625, "name": "talking to animals"}] | K79: en | L79: After a threat from the tiger Shere Khan forces him to flee the jungle, a man-cub named Mowgli embarks on a journey of self discovery with the help of panther, Bagheera, and free spirited bear, Baloo. | M79: 94199316 | N79: [{"name": "Walt Disney Pictures", "id": 2}, {"name": "Walt Disney Studios Motion Pictures", "id": 3036}, {"name": "Fairview Entertainment", "id": 7297}, {"name": "Moving Picture Company (MPC)", "id": 20478}] | O79: Walt Disney Pictures | P79: [{"iso_3166_1": "GB", "name": "United Kingdom"}, {"iso_3166_1": "US", "name": "United States of America"}] | Q79: 42467 | R79: 2016 | S79: 966550600 | T79: 106 | U79: [{"iso_639_1": "en", "name": "English"}] | V79: Released | X79: 6.7 | Y79: 2892 | Z79: 791550600
A80: 200000000 | B80: [{ 12, name: Adventure}, { 28, name: Action}, { 878, name: Science Fiction}] | C80: Adventure | D80: Action | E80: Science Fiction | F80: - | G80: http://www.ironmanmovie.com/ | H80: 10138 | I80: Iron Man 2 | J80: [{"id": 8613, "name": "malibu"}, {"id": 8828, "name": "marvel comic"}, {"id": 9715, "name": "superhero"}, {"id": 9717, "name": "based on comic book"}, {"id": 9748, "name": "revenge"}, {"id": 179430, "name": "aftercreditsstinger"}, {"id": 180547, "name": "marvel cinematic universe"}] | K80: en | L80: With the world now aware of his dual life as the armored superhero Iron Man, billionaire inventor Tony Stark faces pressure from the government, the press and the public to share his technology with the military. Unwilling to let go of his invention, Stark, with Pepper Potts and James 'Rhodey' Rhodes at his side, must forge new alliances â€“ and confront powerful enemies. | M80: 77300194 | N80: [{"name": "Marvel Studios", "id": 420}] | O80: Marvel Studios | P80: [{"iso_3166_1": "US", "name": "United States of America"}] | Q80: 40296 | R80: 2010 | S80: 623933331 | T80: 124 | U80: [{"iso_639_1": "en", "name": "English"}, {"iso_639_1": "ru", "name": "P\u0443\u0441\u0441\u043a\u0438\u0439"}, {"iso_639_1": "fr", "name": "Fran\u00e7ais"}] | V80: Released | W80: It's not the armor that makes the hero, but the man inside. | X80: 6.6 | Y80: 6849 | Z80: 423933331
A81: 80000000 | B81: [{ 14, name: Fantasy}, { 35, name: Comedy}] | C81: Fantasy | D81: Comedy | E81: - | F81: - | G81: http://www.brucealmighty.com/ | H81: 310 | I81: Bruce Almighty | J81: [{"id": 186, "name": "christianity"}, {"id": 305, "name": "moon"}, {"id": 457, "name": "responsability"}, {"id": 488, "name": "moses"}, {"id": 542, "name": "street gang"}, {"id": 725, "name": "lovesickness"}, {"id": 917, "name": "journalism"}, {"id": 1605, "name": "new love"}, {"id": 6150, "name": "faith"}, {"id": 6157, "name": "prayer"}, {"id": 9649, "name": "god"}, {"id": 9844, "name": "car crash"}] | K81: en | L81: Bruce Nolan toils as a "human interest" television reporter in Buffalo, N.Y. Despite his high ratings and the love of his beautiful girlfriend, Grace, Bruce remains unfulfilled. At the end of the worst day in his life, he angrily ridicules God -- and the Almighty responds, endowing Bruce with all of His divine powers. | M81: 109684788 | N81: [{"name": "Universal Pictures", "id": 33}, {"name": "Spyglass Entertainment", "id": 158}, {"name": "Shady Acres Entertainment", "id": 159}, {"name": "Pit Bull Productions", "id": 160}] | O81: Universal Pictures | P81: [{"iso_3166_1": "US", "name": "United States of America"}] | Q81: 37764 | R81: 2003 | S81: 484572835 | T81: 101 | U81: [{"iso_639_1": "en", "name": "English"}] | V81: Released | W81: In Bruce we trust | X81: 6.4 | Y81: 3012 | Z81: 404572835
A82: 180000000 | B82: [{ 14, name: Fantasy}, { 12, name: Adventure}, { 28, name: Action}, { 10751, name: Family}, { 10749, name: Romance}] | C82: Fantasy | D82: Adventure | E82: Action | F82: Family | G82: http://movies.disney.com/maleficent | H82: 102651 | I82: Maleficent | J82: [{"id": 3205, "name": "fairy tale"}, {"id": 3289, "name": "villain"}, {"id": 7430, "name": "sleeping beauty"}, {"id": 177895, "name": "dark fantasy"}, {"id": 179411, "name": "based on fairy tale"}, {"id": 186846, "name": "adaptation"}, {"id": 186847, "name": "retelling"}, {"id": 186849, "name": "literary adaptation"}, {"id": 209714, "name": "3d"}] | K82: en | L82: The untold story of Disney's most iconic villain from the 1959 classic 'Sleeping Beauty'. A beautiful, pure-hearted young woman, Maleficent has an idyllic life growing up in a peaceable forest kingdom, until one day when an invading army threatens the harmony of the land. Maleficent rises to be the land's fiercest protector, but she ultimately suffers a ruthless betrayal â€“ an act that begins to turn her heart into stone. Bent on revenge, Maleficent faces an epic battle with the invading King's successor and, as a result, places a curse upon his newborn infant Aurora. As the child grows, Maleficent realizes that Aurora holds the key to peace in the kingdom - and to Maleficent's true happiness as well. | M82: 110620647 | N82: [{"name": "Walt Disney Pictures", "id": 2}, {"name": "Walt Disney Studios Motion Pictures", "id": 3036}, {"name": "Roth Films", "id": 16314}] | O82: Walt Disney Pictures | P82: [{"iso_3166_1": "US", "name": "United States of America"}] | Q82: 41787 | R82: 2014 | S82: 758539785 | T82: 97 | U82: [{"iso_639_1": "en", "name": "English"}] | V82: Released | W82: Don't believe the fairy tale. | X82: 7.0 | Y82: 4496 | Z82: 578539785
A83: 170000000 | B83: [{ 878, name: Science Fiction}, { 28, name: Action}, { 18, name: Drama}, { 53, name: Thriller}] | C83: Science Fiction | D83: Action | E83: Drama | F83: Thriller | G83: http://www.dawnofapes.com/ | H83: 119450 | I83: Dawn of the Planet of the Apes | J83: [{"id": 3077, "name": "leader"}, {"id": 4090, "name": "colony"}, {"id": 4458, "name": "post-apocalyptic"}, {"id": 4565, "name": "dystopia"}, {"id": 5774, "name": "forest"}, {"id": 9663, "name": "sequel"}, {"id": 9720, "name": "woods"}, {"id": 14759, "name": "ape"}, {"id": 14760, "name": "scientist"}, {"id": 15149, "name": "monkey"}, {"id": 158025, "name": "medical research"}, {"id": 158130, "name": "animal attack"}, {"id": 188959, "name": "plague"}, {"id": 209714, "name": "3d"}] | K83: en | L83: A group of scientists in San Francisco struggle to stay alive in the aftermath of a plague that is wiping out humanity, while Caesar tries to maintain dominance over his community of intelligent apes. | M83: 243791743 | N83: [{"name": "Ingenious Media", "id": 290}, {"name": "Chernin Entertainment", "id": 7076}, {"name": "TSG Entertainment", "id": 22213}] | O83: Ingenious Media | P83: [{"iso_3166_1": "US", "name": "United States of America"}] | Q83: 41816 | R83: 2014 | S83: 710644566 | T83: 130 | U83: [{"iso_639_1": "en", "name": "English"}] | V83: Released | W83: One last chance for peace. | X83: 7.3 | Y83: 4410 | Z83: 540644566
A84: 175000000 | B84: [{ 18, name: Drama}, { 28, name: Action}, { 12, name: Adventure}, { 14, name: Fantasy}] | C84: Drama | D84: Action | E84: Adventure | F84: Fantasy | H84: 64686 | I84: 47 Ronin | J84: [{"id": 233, "name": "japan"}, {"id": 236, "name": "suicide"}, {"id": 1462, "name": "samurai"}, {"id": 9672, "name": "based on true story"}, {"id": 18098, "name": "samurai sword"}, {"id": 155198, "name": "ronin"}, {"id": 155242, "name": "shogun"}, {"id": 183528, "name": "half breed"}, {"id": 209714, "name": "3d"}] | K84: en | L84: Based on the original 1941 movie from Japan, and from ancient Japanâ€™s most enduring tale, the epic 3D fantasy-adventure 47 Ronin is born. Keanu Reeves leads the cast as Kai, an outcast who joins Oishi (Hiroyuki Sanada), the leader of the 47 outcast samurai. Together they seek vengeance upon the treacherous overlord who killed their master and banished their kind. To restore honor to their homeland, the warriors embark upon a quest that challenges them with a series of trials that would destroy ordinary warriors. | M84: 41796339 | N84: [{"name": "Mid Atlantic Films", "id": 2735}, {"name": "Stuber Productions", "id": 4403}, {"name": "Universal", "id": 6292}, {"name": "Moving Picture Company (MPC)", "id": 20478}, {"name": "H2F Entertainment", "id": 20851}] | O84: Mid Atlantic Films | P84: [{"iso_3166_1": "US", "name": "United States of America"}] | Q84: 41614 | R84: 2013 | S84: 150962475 | T84: 119 | U84: [{"iso_639_1": "en", "name": "English"}, {"iso_639_1": "ja", "name": "\u65e5\u672c\u8a9e"}] | V84: Released | W84: For courage. For loyalty. For honor. | X84: 5.9 | Y84: 1326 | Z84: -24037525
A85: 170000000 | B85: [{ 28, name: Action}, { 12, name: Adventure}, { 878, name: Science Fiction}] | C85: Action | D85: Adventure | E85: Science Fiction | F85: - | G85: http://www.captainamericathewintersoldiermovie.com | H85: 100402 | I85: Captain America: The Winter Soldier | J85: [{"id": 521, "name": "washington d.c."}, {"id": 2964, "name": "future"}, {"id": 5539, "name": "shield"}, {"id": 8828, "name": "marvel comic"}, {"id": 9715, "name": "superhero"}, {"id": 9717, "name": "based on comic book"}, {"id": 173775, "name": "captain america"}, {"id": 179430, "name": "aftercreditsstinger"}, {"id": 179431, "name": "duringcreditsstinger"}, {"id": 180547, "name": "marvel cinematic universe"}, {"id": 209714, "name": "3d"}, {"id": 209817, "name": "political thriller"}] | K85: en | L85: After the cataclysmic events in New York with The Avengers, Steve Rogers, aka Captain America is living quietly in Washington, D.C. and trying to adjust to the modern world. But when a S.H.I.E.L.D. colleague comes under attack, Steve becomes embroiled in a web of intrigue that threatens to put the world at risk. Joining forces with the Black Widow, Captain America struggles to expose the ever-widening conspiracy while fighting off professional assassins sent to silence him at every turn. When the full scope of the villainous plot is revealed, Captain America and the Black Widow enlist the help of a new ally, the Falcon. However, they soon find themselves up against an unexpected and formidable enemyâ€”the Winter Soldier. | M85: 72225265 | N85: [{"name": "Marvel Studios", "id": 420}] | O85: Marvel Studios | P85: [{"iso_3166_1": "US", "name": "United States of America"}] | Q85: 41718 | R85: 2014 | S85: 714766572 | T85: 136 | U85: [{"iso_639_1": "en", "name": "English"}] | V85: Released | W85: In heroes we trust. | X85: 7.6 | Y85: 5764 | Z85: 544766572
A86: 165000000 | B86: [{ 35, name: Comedy}, { 12, name: Adventure}, { 14, name: Fantasy}, { 16, name: Animation}, { 10751, name: Family}] | C86: Comedy | D86: Adventure | E86: Fantasy | F86: Animation | G86: http://www.shrekforeverafter.com/ | H86: 10192 | I86: Shrek Forever After | J86: [{"id": 189111, "name": "ogre"}, {"id": 209714, "name": "3d"}] | K86: en | L86: A bored and domesticated Shrek pacts with deal-maker Rumpelstiltskin to get back to feeling like a real ogre again, but when he's duped and sent to a twisted version of Far Far Awayâ€”where Rumpelstiltskin is king, ogres are hunted, and he and Fiona have never metâ€”he sets out to restore his world and reclaim his true love. | M86: 44041186 | N86: [{"name": "DreamWorks Animation", "id": 521}] | O86: DreamWorks Animation | P86: [{"iso_3166_1": "US", "name": "United States of America"}] | Q86: 40314 | R86: 2010 | S86: 752600867 | T86: 93 | U86: [{"iso_639_1": "en", "name": "English"}] | V86: Released | W86: It ain't Ogre... Til it's Ogre | X86: 6.0 | Y86: 1959 | Z86: 587600867
A87: 190000000 | B87: [{ 12, name: Adventure}, { 10751, name: Family}, { 9648, name: Mystery}, { 878, name: Science Fiction}] | C87: Adventure | D87: Family | E87: Mystery | F87: Science Fiction | G87: http://movies.disney.com/tomorrowland | H87: 158852 | I87: Tomorrowland | J87: [{"id": 1436, "name": "inventor"}, {"id": 12332, "name": "apocalypse"}, {"id": 40850, "name": "destiny"}, {"id": 156395, "name": "imax"}, {"id": 173276, "name": "dreamer"}, {"id": 214714, "name": "futuristic car"}, {"id": 214715, "name": "futuristic city"}] | K87: en | L87: Bound by a shared destiny, a bright, optimistic teen bursting with scientific curiosity and a former boy-genius inventor jaded by disillusionment embark on a danger-filled mission to unearth the secrets of an enigmatic place somewhere in time and space that exists in their collective memory as "Tomorrowland." | M87: 130311355 | N87: [{"name": "Walt Disney Pictures", "id": 2}, {"name": "Babieka", "id": 20656}, {"name": "A113", "id": 59778}] | O87: Walt Disney Pictures | P87: [{"iso_3166_1": "US", "name": "United States of America"}] | Q87: 42143 | R87: 2015 | S87: 209154322 | T87: 130 | U87: [{"iso_639_1": "en", "name": "English"}] | V87: Released | W87: Imagine a world where nothing is impossible. | X87: 6.2 | Y87: 2846 | Z87: 19154322
A88: 165000000 | B88: [{ 12, name: Adventure}, { 10751, name: Family}, { 16, name: Animation}, { 28, name: Action}, { 35, name: Comedy}] | C88: Adventure | D88: Family | E88: Animation | F88: Action | G88: http://movies.disney.com/big-hero-6 | H88: 177572 | I88: Big Hero 6 | J88: [{"id": 380, "name": "brother brother relationship"}, {"id": 1701, "name": "hero"}, {"id": 2276, "name": "talent"}, {"id": 9748, "name": "revenge"}, {"id": 12392, "name": "best friend"}, {"id": 12446, "name": "another dimension"}, {"id": 14544, "name": "robot"}, {"id": 33353, "name": "boy genius"}, {"id": 41509, "name": "hate"}, {"id": 179430, "name": "aftercreditsstinger"}, {"id": 198423, "name": "moral dilemma"}, {"id": 209714, "name": "3d"}, {"id": 213104, "name": "teen superheroes"}, {"id": 215235, "name": "dead brother"}] | K88: en | L88: The special bond that develops between plus-sized inflatable robot Baymax, and prodigy Hiro Hamada, who team up with a group of friends to form a band of high-tech heroes. | M88: 20373459 | N88: [{"name": "Walt Disney Pictures", "id": 2}, {"name": "Walt Disney Animation Studios", "id": 6125}] | O88: Walt Disney Pictures | P88: [{"iso_3166_1": "US", "name": "United States of America"}] | Q88: 41936 | R88: 2014 | S88: 652105443 | T88: 102 | U88: [{"iso_639_1": "en", "name": "English"}] | V88: Released | W88: From the creators of Wreck-it Ralph and Frozen | X88: 7.8 | Y88: 6135 | Z88: 487105443
A89: 165000000 | B89: [{ 10751, name: Family}, { 16, name: Animation}, { 35, name: Comedy}, { 12, name: Adventure}] | C89: Family | D89: Animation | E89: Comedy | F89: Adventure | G89: http://disney.go.com/wreck-it-ralph | H89: 82690 | I89: Wreck-It Ralph | J89: [{"id": 825, "name": "support group"}, {"id": 3977, "name": "product placement"}, {"id": 6733, "name": "bullying"}, {"id": 10039, "name": "racing"}, {"id": 10547, "name": "arcade"}, {"id": 11124, "name": "medal"}, {"id": 155023, "name": "self esteem"}, {"id": 158023, "name": "curiosity"}, {"id": 162936, "name": "precocious child"}, {"id": 179430, "name": "aftercreditsstinger"}, {"id": 179431, "name": "duringcreditsstinger"}, {"id": 185859, "name": "first person shooter"}, {"id": 185861, "name": "glitch"}, {"id": 185863, "name": "carefree"}, {"id": 185867, "name": "video gamer"}, {"id": 185868, "name": "q*bert"}, {"id": 185876, "name": "interrupted wedding"}, {"id": 185880, "name": "social reject"}] | K89: en | L89: Wreck-It Ralph is the 9-foot-tall, 643-pound villain of an arcade video game named Fix-It Felix Jr., in which the game's titular hero fixes buildings that Ralph destroys. Wanting to prove he can be a good guy and not just a villain, Ralph escapes his game and lands in Hero's Duty, a first-person shooter where he helps the game's hero battle against alien invaders. He later enters Sugar Rush, a kart racing game set on tracks made of candies, cookies and other sweets. There, Ralph meets Vanellope von Schweetz who has learned that her game is faced with a dire threat that could affect the entire arcade, and one that Ralph may have inadvertently started. | M89: 62341073 | N89: [{"name": "Walt Disney Animation Studios", "id": 6125}] | O89: Walt Disney Animation Studios | P89: [{"iso_3166_1": "US", "name": "United States of America"}] | Q89: 41214 | R89: 2012 | S89: 471222889 | T89: 108 | U89: [{"iso_639_1": "en", "name": "English"}] | V89: Released | W89: The story of a regular guy just looking for a little wreck-ognition. | X89: 7.1 | Y89: 4570 | Z89: 306222889
A90: 165000000 | B90: [{ 12, name: Adventure}, { 16, name: Animation}, { 10751, name: Family}, { 14, name: Fantasy}] | C90: Adventure | D90: Animation | E90: Family | F90: Fantasy | H90: 5255 | I90: The Polar Express | J90: [{"id": 1991, "name": "santa claus"}, {"id": 5801, "name": "nerd"}, {"id": 6150, "name": "faith"}, {"id": 9989, "name": "gift"}, {"id": 9995, "name": "bell"}, {"id": 33678, "name": "beard"}, {"id": 34154, "name": "north pole"}, {"id": 41312, "name": "chute"}, {"id": 41314, "name": "trestle"}, {"id": 48711, "name": "ticket"}, {"id": 207317, "name": "christmas"}] | K90: en | L90: When a doubting young boy takes an extraordinary train ride to the North Pole, he embarks on a journey of self-discovery that shows him that the wonder of life never fades for those who believe. | M90: 47323228 | N90: [{"name": "Golden Mean", "id": 1867}, {"name": "Playtone", "id": 4171}, {"name": "ImageMovers", "id": 11395}] | O90: Golden Mean | P90: [{"iso_3166_1": "US", "name": "United States of America"}] | Q90: 38301 | R90: 2004 | S90: 305875730 | T90: 100 | U90: [{"iso_639_1": "en", "name": "English"}] | V90: Released | W90: This holiday season... believe. | X90: 6.4 | Y90: 1474 | Z90: 140875730
A91: 165000000 | B91: [{ 28, name: Action}, { 12, name: Adventure}, { 878, name: Science Fiction}] | C91: Action | D91: Adventure | E91: Science Fiction | F91: - | G91: http://www.warof1996.com | H91: 47933 | I91: Independence Day: Resurgence | J91: [{"id": 12026, "name": "alternate history"}, {"id": 14909, "name": "alien invasion"}] | K91: en | L91: We always knew they were coming back. Using recovered alien technology, the nations of Earth have collaborated on an immense defense program to protect the planet. But nothing can prepare us for the aliensâ€™ advanced and unprecedented force. Only the ingenuity of a few brave men and women can bring our world back from the brink of extinction. | M91: 48775723 | N91: [{"name": "Twentieth Century Fox Film Corporation", "id": 306}, {"name": "Centropolis Entertainment", "id": 347}, {"name": "TSG Entertainment", "id": 22213}, {"name": "Stereo D", "id": 86561}] | O91: Twentieth Century Fox Film Corporation | P91: [{"iso_3166_1": "US", "name": "United States of America"}] | Q91: 42543 | R91: 2016 | S91: 389681935 | T91: 120 | U91: [{"iso_639_1": "en", "name": "English"}] | V91: Released | W91: We had twenty years to prepare. So did they. | X91: 4.9 | Y91: 2491 | Z91: 224681935
A92: 165000000 | B92: [{ 14, name: Fantasy}, { 12, name: Adventure}, { 16, name: Animation}, { 10751, name: Family}] | C92: Fantasy | D92: Adventure | E92: Animation | F92: Family | G92: http://www.howtotrainyourdragon.com/ | H92: 10191 | I92: How to Train Your Dragon | J92: [{"id": 334, "name": "flying"}, {"id": 1318, "name": "blacksmith"}, {"id": 1395, "name": "arena"}, {"id": 2041, "name": "island"}, {"id": 3752, "name": "night"}, {"id": 3799, "name": "ship"}, {"id": 4613, "name": "training"}, {"id": 5331, "name": "village"}, {"id": 5774, "name": "forest"}, {"id": 5895, "name": "viking"}, {"id": 6054, "name": "friendship"}, {"id": 6253, "name": "ignorance"}, {"id": 8044, "name": "flight"}, {"id": 9109, "name": "nest"}, {"id": 12554, "name": "dragon"}, {"id": 14643, "name": "battle"}, {"id": 18543, "name": "combat"}, {"id": 172784, "name": "well"}, {"id": 192913, "name": "warrior"}] | K92: en | L92: As the son of a Viking leader on the cusp of manhood, shy Hiccup Horrendous Haddock III faces a rite of passage: he must kill a dragon to prove his warrior mettle. But after downing a feared dragon, he realizes that he no longer wants to destroy it, and instead befriends the beast â€“ which he names Toothless â€“ much to the chagrin of his warrior father | M92: 67263269 | N92: [{"name": "DreamWorks Animation", "id": 521}, {"name": "Vertigo Entertainment", "id": 829}, {"name": "Mad Hatter Entertainment", "id": 20154}] | O92: DreamWorks Animation | P92: [{"iso_3166_1": "US", "name": "United States of America"}] | Q92: 40242 | R92: 2010 | S92: 494878759 | T92: 98 | U92: [{"iso_639_1": "en", "name": "English"}] | V92: Released | W92: One adventure will change two worlds | X92: 7.5 | Y92: 4227 | Z92: 329878759
A93: 200000000 | B93: [{ 28, name: Action}, { 53, name: Thriller}, { 878, name: Science Fiction}] | C93: Action | D93: Thriller | E93: Science Fiction | F93: - | H93: 296 | I93: Terminator 3: Rise of the Machines | J93: [{"id": 83, "name": "saving the world"}, {"id": 310, "name": "artificial intelligence"}, {"id": 312, "name": "man vs machine"}, {"id": 679, "name": "cyborg"}, {"id": 1373, "name": "killer robot"}, {"id": 1381, "name": "sun glasses"}, {"id": 2650, "name": "leather jacket"}, {"id": 2651, "name": "nanotechnology"}, {"id": 2732, "name": "rocket launcher"}, {"id": 2733, "name": "firemen"}, {"id": 2735, "name": "veterinarian"}, {"id": 2736, "name": "fire engine"}, {"id": 4565, "name": "dystopia"}, {"id": 15106, "name": "psychiatrist"}] | K93: en | L93: It's been 10 years since John Connor saved Earth from Judgment Day, and he's now living under the radar, steering clear of using anything Skynet can trace. That is, until he encounters T-X, a robotic assassin ordered to finish what T-1000 started. Good thing Connor's former nemesis, the Terminator, is back to aid the now-adult Connor â€¦ just like he promised. | M93: 69405188 | N93: [{"name": "Columbia Pictures", "id": 5}, {"name": "Intermedia Films", "id": 763}, {"name": "Warner Bros.", "id": 6194}, {"name": "C-2 Pictures", "id": 7340}, {"name": "IMF Internationale Medien und Film GmbH & Co. 3. Produktions KG", "id": 19116}, {"name": "Mostow/Lieberman Productions", "id": 23636}] | O93: Columbia Pictures | P93: [{"iso_3166_1": "DE", "name": "Germany"}, {"iso_3166_1": "GB", "name": "United Kingdom"}, {"iso_3166_1": "US", "name": "United States of America"}] | Q93: 37804 | R93: 2003 | S93: 435000000 | T93: 109 | U93: [{"iso_639_1": "en", "name": "English"}] | V93: Released | W93: The Machines Will Rise. | X93: 5.9 | Y93: 2143 | Z93: 235000000
A94: 170000000 | B94: [{ 28, name: Action}, { 878, name: Science Fiction}, { 12, name: Adventure}] | C94: Action | D94: Science Fiction | E94: Adventure | F94: - | G94: http://marvel.com/guardians | H94: 118340 | I94: Guardians of the Galaxy | J94: [{"id": 8828, "name": "marvel comic"}, {"id": 9831, "name": "spaceship"}, {"id": 9882, "name": "space"}, {"id": 12405, "name": "outer space"}, {"id": 13014, "name": "orphan"}, {"id": 175428, "name": "adventurer"}, {"id": 179430, "name": "aftercreditsstinger"}, {"id": 179431, "name": "duringcreditsstinger"}, {"id": 180547, "name": "marvel cinematic universe"}] | K94: en | L94: Light years from Earth, 26 years after being abducted, Peter Quill finds himself the prime target of a manhunt after discovering an orb wanted by Ronan the Accuser. | M94: 481098624 | N94: [{"name": "Marvel Studios", "id": 420}, {"name": "Moving Picture Company (MPC)", "id": 20478}, {"name": "Bulletproof Cupid", "id": 54850}, {"name": "Revolution Sun Studios", "id": 76043}] | O94: Marvel Studios | P94: [{"iso_3166_1": "GB", "name": "United Kingdom"}, {"iso_3166_1": "US", "name": "United States of America"}] | Q94: 41850 | R94: 2014 | S94: 773328629 | T94: 121 | U94: [{"iso_639_1": "en", "name": "English"}] | V94: Released | W94: All heroes start somewhere. | X94: 7.9 | Y94: 9742 | Z94: 603328629
A95: 165000000 | B95: [{ 12, name: Adventure}, { 18, name: Drama}, { 878, name: Science Fiction}] | C95: Adventure | D95: Drama | E95: Science Fiction | F95: - | G95: http://www.interstellarmovie.net/ | H95: 157336 | I95: Interstellar | J95: [{"id": 83, "name": "saving the world"}, {"id": 310, "name": "artificial intelligence"}, {"id": 494, "name": "father son relationship"}, {"id": 641, "name": "single parent"}, {"id": 1432, "name": "nasa"}, {"id": 1963, "name": "expedition"}, {"id": 3417, "name": "wormhole"}, {"id": 3801, "name": "space travel"}, {"id": 4337, "name": "famine"}, {"id": 4380, "name": "black hole"}, {"id": 4565, "name": "dystopia"}, {"id": 4776, "name": "race against time"}, {"id": 8056, "name": "quantum mechanics"}, {"id": 9831, "name": "spaceship"}, {"id": 9882, "name": "space"}, {"id": 10084, "name": "rescue"}, {"id": 10235, "name": "family relationships"}, {"id": 13127, "name": "farmhouse"}, {"id": 14544, "name": "robot"}, {"id": 14626, "name": "astronaut"}, {"id": 14760, "name": "scientist"}, {"id": 15300, "name": "father daughter relationship"}, {"id": 33479, "name": "single father"}, {"id": 154846, "name": "farmer"}, {"id": 156039, "name": "space station"}, {"id": 156395, "name": "imax"}, {"id": 160331, "name": "astrophysics"}, {"id": 162630, "name": "zero gravity"}, {"id": 189098, "name": "courage"}, {"id": 208757, "name": "time paradox"}, {"id": 214349, "name": "relativity"}] | K95: en | L95: Interstellar chronicles the adventures of a group of explorers who make use of a newly discovered wormhole to surpass the limitations on human space travel and conquer the vast distances involved in an interstellar voyage. | M95: 724247784 | N95: [{"name": "Paramount Pictures", "id": 4}, {"name": "Legendary Pictures", "id": 923}, {"name": "Warner Bros.", "id": 6194}, {"name": "Syncopy", "id": 9996}, {"name": "Lynda Obst Productions", "id": 13769}] | O95: Paramount Pictures | P95: [{"iso_3166_1": "CA", "name": "Canada"}, {"iso_3166_1": "US", "name": "United States of America"}, {"iso_3166_1": "GB", "name": "United Kingdom"}] | Q95: 41948 | R95: 2014 | S95: 675120017 | T95: 169 | U95: [{"iso_639_1": "en", "name": "English"}] | V95: Released | W95: Mankind was born on Earth. It was never meant to die here. | X95: 8.1 | Y95: 10867 | Z95: 510120017
A96: 160000000 | B96: [{ 28, name: Action}, { 53, name: Thriller}, { 878, name: Science Fiction}, { 9648, name: Mystery}, { 12, name: Adventure}] | C96: Action | D96: Thriller | E96: Science Fiction | F96: Mystery | G96: http://inceptionmovie.warnerbros.com/ | H96: 27205 | I96: Inception | J96: [{"id": 1014, "name": "loss of lover"}, {"id": 1566, "name": "dream"}, {"id": 1930, "name": "kidnapping"}, {"id": 2116, "name": "sleep"}, {"id": 2117, "name": "subconsciousness"}, {"id": 10051, "name": "heist"}, {"id": 11436, "name": "redemption"}, {"id": 160137, "name": "female hero"}] | K96: en | L96: Cobb, a skilled thief who commits corporate espionage by infiltrating the subconscious of his targets is offered a chance to regain his old life as payment for a task considered to be impossible: "inception", the implantation of another person's idea into a target's subconscious. | M96: 16758371 | N96: [{"name": "Legendary Pictures", "id": 923}, {"name": "Warner Bros.", "id": 6194}, {"name": "Syncopy", "id": 9996}] | O96: Legendary Pictures | P96: [{"iso_3166_1": "GB", "name": "United Kingdom"}, {"iso_3166_1": "US", "name": "United States of America"}] | Q96: 40373 | R96: 2010 | S96: 825532764 | T96: 148 | U96: [{"iso_639_1": "en", "name": "English"}, {"iso_639_1": "ja", "name": "\u65e5\u672c\u8a9e"}, {"iso_639_1": "fr", "name": "Fran\u00e7ais"}] | V96: Released | W96: Your mind is the scene of the crime. | X96: 8.1 | Y96: 13752 | Z96: 665532764
A97: 15000000 | B97: [{ 28, name: Action}, { 12, name: Adventure}, { 18, name: Drama}, { 27, name: Horror}, { 878, name: Science Fiction}] | C97: Action | D97: Adventure | E97: Drama | F97: Horror | H97: 315011 | I97: Shin Godzilla | J97: [{"id": 1299, "name": "monster"}, {"id": 7671, "name": "godzilla"}, {"id": 11100, "name": "giant monster"}, {"id": 14796, "name": "destruction"}, {"id": 161791, "name": "kaiju"}, {"id": 235525, "name": "toyko"}] | K97: ja | L97: From the mind behind Evangelion comes a hit larger than life. When a massive, gilled monster emerges from the deep and tears through the city, the government scrambles to save its citizens. A rag-tag team of volunteers cuts through a web of red tape to uncover the monster's weakness and its mysterious ties to a foreign superpower. But time is not on their side - the greatest catastrophe to ever befall the world is about to evolve right before their very eyes. | M97: 9476999 | N97: [{"name": "Cine Bazar", "id": 5896}, {"name": "Toho Pictures", "id": 49301}] | O97: Cine Bazar | P97: [{"iso_3166_1": "JP", "name": "Japan"}] | Q97: 42580 | R97: 2016 | S97: 77000000 | T97: 120 | U97: [{"iso_639_1": "it", "name": "Italiano"}, {"iso_639_1": "de", "name": "Deutsch"}, {"iso_639_1": "en", "name": "English"}, {"iso_639_1": "ja", "name": "\u65e5\u672c\u8a9e"}] | V97: Released | W97: A god incarnate. A city doomed. | X97: 6.5 | Y97: 143 | Z97: 62000000
A98: 250000000 | B98: [{ 12, name: Adventure}, { 14, name: Fantasy}, { 28, name: Action}] | C98: Adventure | D98: Fantasy | E98: Action | F98: - | G98: http://www.thehobbit.com/ | H98: 49051 | I98: The Hobbit: An Unexpected Journey | J98: [{"id": 483, "name": "riddle"}, {"id": 603, "name": "elves"}, {"id": 604, "name": "dwarves"}, {"id": 606, "name": "orcs"}, {"id": 609, "name": "middle-earth (tolkien)"}, {"id": 611, "name": "hobbit"}, {"id": 1262, "name": "mountains"}, {"id": 177912, "name": "wizard"}, {"id": 189092, "name": "journey"}, {"id": 189093, "name": "ring"}, {"id": 189094, "name": "goblin"}, {"id": 189098, "name": "courage"}, {"id": 189099, "name": "giant"}, {"id": 189102, "name": "tunnel"}, {"id": 189103, "name": "underground lake"}, {"id": 189108, "name": "buried treasure"}, {"id": 189114, "name": "climbing a tree"}, {"id": 189115, "name": "invisibility"}, {"id": 189119, "name": "ancient"}, {"id": 191739, "name": "gnomes"}] | K98: en | L98: Bilbo Baggins, a hobbit enjoying his quiet life, is swept into an epic quest by Gandalf the Grey and thirteen dwarves who seek to reclaim their mountain home from Smaug, the dragon. | M98: 108849621 | N98: [{"name": "WingNut Films", "id": 11}, {"name": "New Line Cinema", "id": 12}, {"name": "Warner Bros. Pictures", "id": 174}, {"name": "Metro-Goldwyn-Mayer (MGM)", "id": 8411}] | O98: WingNut Films | P98: [{"iso_3166_1": "NZ", "name": "New Zealand"}, {"iso_3166_1": "US", "name": "United States of America"}] | Q98: 41239 | R98: 2012 | S98: 1021103568 | T98: 169 | U98: [{"iso_639_1": "en", "name": "English"}] | V98: Released | W98: From the smallest beginnings come the greatest legends. | X98: 7.0 | Y98: 8297 | Z98: 771103568
A99: 22000000 | B99: [{ 18, name: Drama}, { 36, name: History}, { 10752, name: War}] | C99: Drama | D99: History | E99: War | F99: - | G99: http://www.schindlerslist.com/ | H99: 424 | I99: Schindler's List | J99: [{"id": 1382, "name": "factory"}, {"id": 1631, "name": "concentration camp"}, {"id": 1701, "name": "hero"}, {"id": 1739, "name": "holocaust"}, {"id": 1956, "name": "world war ii"}, {"id": 2652, "name": "nazis"}, {"id": 3599, "name": "defense industry"}, {"id": 5565, "name": "biography"}, {"id": 194409, "name": "the holocaust"}] | K99: en | L99: The true story of how businessman Oskar Schindler saved over a thousand Jewish lives from the Nazis while they worked as slaves in his factory during World War II. | M99: 104469351 | N99: [{"name": "Universal Pictures", "id": 33}, {"name": "Amblin Entertainment", "id": 56}] | O99: Universal Pictures | P99: [{"iso_3166_1": "US", "name": "United States of America"}] | Q99: 34302 | R99: 1993 | S99: 321365567 | T99: 195 | U99: [{"iso_639_1": "de", "name": "Deutsch"}, {"iso_639_1": "pl", "name": "Polski"}, {"iso_639_1": "he", "name": "\u05e2\u05b4\u05d1\u05b0\u05e8\u05b4\u05d9\u05ea"}, {"iso_639_1": "en", "name": "English"}] | V99: Released | W99: Whoever saves one life, saves the world entire. | X99: 8.3 | Y99: 4329 | Z99: 299365567
A100: 150000000 | B100: [{ 14, name: Fantasy}, { 18, name: Drama}, { 53, name: Thriller}, { 9648, name: Mystery}, { 10749, name: Romance}] | C100: Fantasy | D100: Drama | E100: Thriller | F100: Mystery | G100: http://www.benjaminbutton.com/ | H100: 4922 | I100: The Curious Case of Benjamin Button | J100: [{"id": 2913, "name": "diary"}, {"id": 3588, "name": "navy"}, {"id": 3739, "name": "funeral"}, {"id": 4262, "name": "tea"}, {"id": 9935, "name": "travel"}, {"id": 11612, "name": "hospital"}] | K100: en | L100: Tells the story of Benjamin Button, a man who starts aging backwards with bizarre consequences. | M100: 60269279 | N100: [{"name": "Paramount Pictures", "id": 4}, {"name": "Warner Bros.", "id": 6194}, {"name": "Kennedy/Marshall Company, The", "id": 7383}] | O100: Paramount Pictures | P100: [{"iso_3166_1": "US", "name": "United States of America"}] | Q100: 39776 | R100: 2008 | S100: 333932083 | T100: 166 | U100: [{"iso_639_1": "en", "name": "English"}] | V100: Released | W100: Life isn't measured in minutes, but in moments. | X100: 7.3 | Y100: 3292 | Z100: 183932083
...

Sheet Dashboard
A27: Berdasarkan total profit, paramount pictures menduduki posisi pertama yang diikuti oleh universal pictures dengan selisih pendapatan profit sebesar $ 452.121.987 namun
A28: universal pictures menggunakan budget yang lebih sedikit dibandingkan paramount pictures yaitu selisih $ 1.866.434.296. Dari sini universal pictures mendapatkan
A29: keuntungan sebesar 24% dibandingkan dengan paramount pictures meskipun berada diurutan kedua berdasarkan profit yang diperoleh
A59: Berdasarkan analisis sebelumnya kami melanjutkan untuk mencari tahu apakah terdapat hubungan dengan popularitas yang diperoleh suatu company. Berdasarkan gambar diatas
A60: dapat dilihat bahwa universal pictures memiliki popularity 13.176.408 lebih banyak dari paramount pictures, hal ini berarti urutan total popularitas yang diperoleh film suatu company tidak
A61: bergantung dengan total profit yang diperoleh
A90: Popularitas film tertinggi yang diproduksi oleh universal pictures adala "Minions" meskipun profit yang diperolah lebih besar "Furious 7". Film "Minions" menyumbang
A91: sebesar 12,32% dari seluruh total popularitas yang diperoleh universal pictures. Sedangkan untuk urutan top 10, "Minions" memberikan kontribusi sebesar 48,52%, hal ini menunjukkan
A92: bahwa "Minions" memberikan kontribusi yang sangat besar terhadap popularitas yang diperoleh universal pictures

Sheet Final Dashboard
B22: Berdasarkan total profit, Paramount Pictures menduduki posisi pertama yang diikuti oleh Universal Pictures dengan selisih pendapatan profit sebesar $ 452.121.987 namun
B23: Universal Pictures menggunakan budget yang lebih sedikit dibandingkan Paramount Pictures yaitu selisih $ 1.866.434.296.
B44: Berdasarkan analisa sebelumnya kami melanjutkan untuk mencari tahu perbandingan popularitas 2 perusahaan tertinggi berdasarkan profit. Berdasarkan gambar diatas
B45: dapat dilihat bahwa Universal Pictures memiliki popularity 13.176.408 lebih banyak dari paramount pictures, hal ini berarti total profit suatu perusahaan belum tentu menjamin tinggi atau rendahnya total popularitas
B72: Popularitas film tertinggi yang diproduksi oleh Universal Pictures adala "Minions" meskipun profit yang diperolah lebih besar "Furious 7". Film "Minions" menyumbang
B73: sebesar 12,32% dari seluruh total popularitas yang diperoleh Universal Pictures. Sedangkan untuk urutan top 10, "Minions" memberikan kontribusi sebesar 48,52%, hal ini menunjukkan
B74: bahwa "Minions" memberikan kontribusi yang sangat besar terhadap popularitas yang diperoleh Universal Pictures

Sheet Raw
A1: top 10 movies by profit n budget
A3: company | B3: Total Profit | C3: Total Budget
A4: Paramount Pictures | B4: =SUMIF(Movie[Companies],Raw!A4,Movie[Profit]) -> 25082067469 | C4: =SUMIF(Movie[Companies],Raw!A4,Movie[budget]) -> 11989862948
A5: Universal Pictures | B5: =SUMIF(Movie[Companies],Raw!A5,Movie[Profit]) -> 24629945482 | C5: =SUMIF(Movie[Companies],Raw!A5,Movie[budget]) -> 10123428652
A6: Walt Disney Pictures | B6: =SUMIF(Movie[Companies],Raw!A6,Movie[Profit]) -> 19204470467 | C6: =SUMIF(Movie[Companies],Raw!A6,Movie[budget]) -> 9201780000
A7: Columbia Pictures | B7: =SUMIF(Movie[Companies],Raw!A7,Movie[Profit]) -> 17670376626 | C7: =SUMIF(Movie[Companies],Raw!A7,Movie[budget]) -> 10192774736
A8: Twentieth Century Fox Film Corporation | B8: =SUMIF(Movie[Companies],Raw!A8,Movie[Profit]) -> 16242464696 | C8: =SUMIF(Movie[Companies],Raw!A8,Movie[budget]) -> 6876440000
A9: New Line Cinema | B9: =SUMIF(Movie[Companies],Raw!A9,Movie[Profit]) -> 8552172273 | C9: =SUMIF(Movie[Companies],Raw!A9,Movie[budget]) -> 4641485000
A10: Village Roadshow Pictures | B10: =SUMIF(Movie[Companies],Raw!A10,Movie[Profit]) -> 6951254238 | C10: =SUMIF(Movie[Companies],Raw!A10,Movie[budget]) -> 4867800003
A11: DreamWorks SKG | B11: =SUMIF(Movie[Companies],Raw!A11,Movie[Profit]) -> 6298102144 | C11: =SUMIF(Movie[Companies],Raw!A11,Movie[budget]) -> 3081500000
A12: Lucasfilm | B12: =SUMIF(Movie[Companies],Raw!A12,Movie[Profit]) -> 5810309700 | C12: =SUMIF(Movie[Companies],Raw!A12,Movie[budget]) -> 796427000
A13: Marvel Studios | B13: =SUMIF(Movie[Companies],Raw!A13,Movie[Profit]) -> 5551826201 | C13: =SUMIF(Movie[Companies],Raw!A13,Movie[budget]) -> 1750000000
A16: company | B16: Total Popularity | C16: Total Profit
A17: Paramount Pictures | B17: =SUMIF(Movie[Companies],Raw!A17,Movie[popularity]) -> 7091461706 | C17: 25082067469
A18: Universal Pictures | B18: =SUMIF(Movie[Companies],Raw!A18,Movie[popularity]) -> 7.1046381e+09 | C18: 24629945482
A19: Walt Disney Pictures | B19: =SUMIF(Movie[Companies],Raw!A19,Movie[popularity]) -> 4167392867 | C19: 19204470467
A20: Columbia Pictures | B20: =SUMIF(Movie[Companies],Raw!A20,Movie[popularity]) -> 5414298750 | C20: 17670376626
A21: Twentieth Century Fox Film Corporation | B21: =SUMIF(Movie[Companies],Raw!A21,Movie[popularity]) -> 4780385911 | C21: 16242464696
A22: New Line Cinema | B22: =SUMIF(Movie[Companies],Raw!A22,Movie[popularity]) -> 3226314325 | C22: 8552172273
A23: Village Roadshow Pictures | B23: =SUMIF(Movie[Companies],Raw!A23,Movie[popularity]) -> 2257235739 | C23: 6951254238
A24: DreamWorks SKG | B24: =SUMIF(Movie[Companies],Raw!A24,Movie[popularity]) -> 1427649268 | C24: 6298102144
A25: Lucasfilm | B25: =SUMIF(Movie[Companies],Raw!A25,Movie[popularity]) -> 675268824 | C25: 5810309700
A26: Marvel Studios | B26: =SUMIF(Movie[Companies],Raw!A26,Movie[popularity]) -> 1165905199 | C26: 5551826201
A28: movie | B28: Popularity | C28: Total Profit
A29: Minions | B29: 0.48517361 | C29: =SUMIF(Movie[Title],Raw!A29,Movie[Profit]) -> 1082730962
A30: Despicable Me 2 | B30: 0.075851113 | C30: =SUMIF(Movie[Title],Raw!A30,Movie[Profit]) -> 894761885
A31: Lucy | B31: 0.063857435 | C31: =SUMIF(Movie[Title],Raw!A31,Movie[Profit]) -> 86546825
A32: Despicable Me | B32: 0.063090691 | C32: =SUMIF(Movie[Title],Raw!A32,Movie[Profit]) -> 474513985
A33: Bruce Almighty | B33: 0.060778096 | C33: =SUMIF(Movie[Title],Raw!A33,Movie[Profit]) -> 404572835
A34: Schindler's List | B34: 0.057888139 | C34: =SUMIF(Movie[Title],Raw!A34,Movie[Profit]) -> 299365567
A35: Furious 7 | B35: 0.056698378 | C35: =SUMIF(Movie[Title],Raw!A35,Movie[Profit]) -> 1316249360
A36: The Bourne Identity | B36: 0.047918188 | C36: =SUMIF(Movie[Title],Raw!A36,Movie[Profit]) -> 154034224
A37: The Purge: Anarchy | B37: 0.045978241 | C37: =SUMIF(Movie[Title],Raw!A37,Movie[Profit]) -> 99782847
A38: Snow White and the Huntsman | B38: 0.042766104 | C38: =SUMIF(Movie[Title],Raw!A38,Movie[Profit]) -> 226600000
B39: 1804676267
A42: persentase "Minion" terhadap keseluruhan | B42: 0.1232408 | C42: =SUMIF(Movie[Title];Raw!A29;Movie[popularity])/Raw!B18
A43: popularitas Universal Pictures
W48: p

Sheet Sheet1
A1: budget | B1: genres | C1: genre_1 | D1: genre_2 | E1: genre_3 | F1: genre_4 | G1: homepage | H1: id | I1: Title | J1: keywords | K1: original_language | L1: overview | M1: popularity | N1: production_companies | O1: Company 1 | P1: Company 2 | Q1: Company 3 | R1: Company 4 | S1: Company 5 | T1: Company 6 | U1: Company 7 | V1: Company 8 | W1: Company 9 | X1: Company 10 | Y1: Company 11 | Z1: production_countries | AA1: release_date | AB1: year | AC1: revenue | AD1: runtime | AE1: spoken languages | AF1: status | AG1: tagline | AH1: vote_average | AI1: vote_count | AJ1: Profit
A2: 237000000 | B2: [{ 28, name: Action}, { 12, name: Adventure}, { 14, name: Fantasy}, { 878, name: Science Fiction}] | C2: Action | D2: Adventure | E2: Fantasy | F2: Science Fiction | G2: http://www.avatarmovie.com/ | H2: 19995 | I2: Avatar | J2: [{"id": 1463, "name": "culture clash"}, {"id": 2964, "name": "future"}, {"id": 3386, "name": "space war"}, {"id": 3388, "name": "space colony"}, {"id": 3679, "name": "society"}, {"id": 3801, "name": "space travel"}, {"id": 9685, "name": "futuristic"}, {"id": 9840, "name": "romance"}, {"id": 9882, "name": "space"}, {"id": 9951, "name": "alien"}, {"id": 10148, "name": "tribe"}, {"id": 10158, "name": "alien planet"}, {"id": 10987, "name": "cgi"}, {"id": 11399, "name": "marine"}, {"id": 13065, "name": "soldier"}, {"id": 14643, "name": "battle"}, {"id": 14720, "name": "love affair"}, {"id": 165431, "name": "anti war"}, {"id": 193554, "name": "power relations"}, {"id": 206690, "name": "mind and soul"}, {"id": 209714, "name": "3d"}] | K2: en | L2: In the 22nd century, a paraplegic Marine is dispatched to the moon Pandora on a unique mission, but becomes torn between following orders and protecting an alien civilization. | M2: 150437577 | N2: [{"name": "Ingenious Film Partners", "id": 289}, {"name": "Twentieth Century Fox Film Corporation", "id": 306}, {"name": "Dune Entertainment", "id": 444}, {"name": "Lightstorm Entertainment", "id": 574}] | O2: Ingenious Film Partners | P2: Twentieth Century Fox Film Corporation | Q2: Dune Entertainment | R2: Lightstorm Entertainment | S2: - | T2: - | U2: - | V2: - | W2: - | X2: - | Y2: - | Z2: [{"iso_3166_1": "US", "name": "United States of America"}, {"iso_3166_1": "GB", "name": "United Kingdom"}] | AA2: 40157 | AB2: 2009 | AC2: 2787965087 | AD2: 162 | AE2: [{"iso_639_1": "en", "name": "English"}, {"iso_639_1": "es", "name": "Espa\u00f1ol"}] | AF2: Released | AG2: Enter the World of Pandora. | AH2: 7.2 | AI2: 11800 | AJ2: 2550965087
A3: 300000000 | B3: [{ 12, name: Adventure}, { 14, name: Fantasy}, { 28, name: Action}] | C3: Adventure | D3: Fantasy | E3: Action | F3: - | G3: http://disney.go.com/disneypictures/pirates/ | H3: 285 | I3: Pirates of the Caribbean: At World's End | J3: [{"id": 270, "name": "ocean"}, {"id": 726, "name": "drug abuse"}, {"id": 911, "name": "exotic island"}, {"id": 1319, "name": "east india trading company"}, {"id": 2038, "name": "love of one's life"}, {"id": 2052, "name": "traitor"}, {"id": 2580, "name": "shipwreck"}, {"id": 2660, "name": "strong woman"}, {"id": 3799, "name": "ship"}, {"id": 5740, "name": "alliance"}, {"id": 5941, "name": "calypso"}, {"id": 6155, "name": "afterlife"}, {"id": 6211, "name": "fighter"}, {"id": 12988, "name": "pirate"}, {"id": 157186, "name": "swashbuckler"}, {"id": 179430, "name": "aftercreditsstinger"}] | K3: en | L3: Captain Barbossa, long believed to be dead, has come back to life and is headed to the edge of the Earth with Will Turner and Elizabeth Swann. But nothing is quite as it seems. | M3: 139082615 | N3: [{"name": "Walt Disney Pictures", "id": 2}, {"name": "Jerry Bruckheimer Films", "id": 130}, {"name": "Second Mate Productions", "id": 19936}] | O3: Walt Disney Pictures | P3: Jerry Bruckheimer Films | Q3: Second Mate Productions | R3: - | S3: - | T3: - | U3: - | V3: - | W3: - | X3: - | Y3: - | Z3: [{"iso_3166_1": "US", "name": "United States of America"}] | AA3: 39221 | AB3: 2007 | AC3: 961000000 | AD3: 169 | AE3: [{"iso_639_1": "en", "name": "English"}] | AF3: Released | AG3: At the end of the world, the adventure begins. | AH3: 6.9 | AI3: 4500 | AJ3: 661000000
A4: 245000000 | B4: [{ 28, name: Action}, { 12, name: Adventure}, { 80, name: Crime}] | C4: Action | D4: Adventure | E4: Crime | F4: - | G4: http://www.sonypictures.com/movies/spectre/ | H4: 206647 | I4: Spectre | J4: [{"id": 470, "name": "spy"}, {"id": 818, "name": "based on novel"}, {"id": 4289, "name": "secret agent"}, {"id": 9663, "name": "sequel"}, {"id": 14555, "name": "mi6"}, {"id": 156095, "name": "british secret service"}, {"id": 158431, "name": "united kingdom"}] | K4: en | L4: A cryptic message from Bondâ€™s past sends him on a trail to uncover a sinister organization. While M battles political forces to keep the secret service alive, Bond peels back the layers of deceit to reveal the terrible truth behind SPECTRE. | M4: 107376788 | N4: [{"name": "Columbia Pictures", "id": 5}, {"name": "Danjaq", "id": 10761}, {"name": "B24", "id": 69434}] | O4: Columbia Pictures | P4: Danjaq | Q4: B24 | R4: - | S4: - | T4: - | U4: - | V4: - | W4: - | X4: - | Y4: - | Z4: [{"iso_3166_1": "GB", "name": "United Kingdom"}, {"iso_3166_1": "US", "name": "United States of America"}] | AA4: 42303 | AB4: 2015 | AC4: 880674609 | AD4: 148 | AE4: [{"iso_639_1": "fr", "name": "Fran\u00e7ais"}, {"iso_639_1": "en", "name": "English"}, {"iso_639_1": "es", "name": "Espa\u00f1ol"}, {"iso_639_1": "it", "name": "Italiano"}, {"iso_639_1": "de", "name": "Deutsch"}] | AF4: Released | AG4: A Plan No One Escapes | AH4: 6.3 | AI4: 4466 | AJ4: 635674609
A5: 250000000 | B5: [{ 28, name: Action}, { 80, name: Crime}, { 18, name: Drama}, { 53, name: Thriller}] | C5: Action | D5: Crime | E5: Drama | F5: Thriller | G5: http://www.thedarkknightrises.com/ | H5: 49026 | I5: The Dark Knight Rises | J5: [{"id": 849, "name": "dc comics"}, {"id": 853, "name": "crime fighter"}, {"id": 949, "name": "terrorist"}, {"id": 1308, "name": "secret identity"}, {"id": 1437, "name": "burglar"}, {"id": 3051, "name": "hostage drama"}, {"id": 3562, "name": "time bomb"}, {"id": 6969, "name": "gotham city"}, {"id": 7002, "name": "vigilante"}, {"id": 9665, "name": "cover-up"}, {"id": 9715, "name": "superhero"}, {"id": 9990, "name": "villainess"}, {"id": 10044, "name": "tragic hero"}, {"id": 13015, "name": "terrorism"}, {"id": 14796, "name": "destruction"}, {"id": 18933, "name": "catwoman"}, {"id": 156082, "name": "cat burglar"}, {"id": 156395, "name": "imax"}, {"id": 173272, "name": "flood"}, {"id": 179093, "name": "criminal underworld"}, {"id": 230775, "name": "batman"}] | K5: en | L5: Following the death of District Attorney Harvey Dent, Batman assumes responsibility for Dent's crimes to protect the late attorney's reputation and is subsequently hunted by the Gotham City Police Department. Eight years later, Batman encounters the mysterious Selina Kyle and the villainous Bane, a new terrorist leader who overwhelms Gotham's finest. The Dark Knight resurfaces to protect a city that has branded him an enemy. | M5: 11231295 | N5: [{"name": "Legendary Pictures", "id": 923}, {"name": "Warner Bros.", "id": 6194}, {"name": "DC Entertainment", "id": 9993}, {"name": "Syncopy", "id": 9996}] | O5: Legendary Pictures | P5: Warner Bros. | Q5: DC Entertainment | R5: Syncopy | S5: - | T5: - | U5: - | V5: - | W5: - | X5: - | Y5: - | Z5: [{"iso_3166_1": "US", "name": "United States of America"}] | AA5: 41106 | AB5: 2012 | AC5: 1084939099 | AD5: 165 | AE5: [{"iso_639_1": "en", "name": "English"}] | AF5: Released | AG5: The Legend Ends | AH5: 7.6 | AI5: 9106 | AJ5: 834939099
A6: 260000000 | B6: [{ 28, name: Action}, { 12, name: Adventure}, { 878, name: Science Fiction}] | C6: Action | D6: Adventure | E6: Science Fiction | F6: - | G6: http://movies.disney.com/john-carter | H6: 49529 | I6: John Carter | J6: [{"id": 818, "name": "based on novel"}, {"id": 839, "name": "mars"}, {"id": 1456, "name": "medallion"}, {"id": 3801, "name": "space travel"}, {"id": 7376, "name": "princess"}, {"id": 9951, "name": "alien"}, {"id": 10028, "name": "steampunk"}, {"id": 10539, "name": "martian"}, {"id": 10685, "name": "escape"}, {"id": 161511, "name": "edgar rice burroughs"}, {"id": 163252, "name": "alien race"}, {"id": 179102, "name": "superhuman strength"}, {"id": 190320, "name": "mars civilization"}, {"id": 195446, "name": "sword and planet"}, {"id": 207928, "name": "19th century"}, {"id": 209714, "name": "3d"}] | K6: en | L6: John Carter is a war-weary, former military captain who's inexplicably transported to the mysterious and exotic planet of Barsoom (Mars) and reluctantly becomes embroiled in an epic conflict. It's a world on the brink of collapse, and Carter rediscovers his humanity when he realizes the survival of Barsoom and its people rests in his hands. | M6: 43926995 | N6: [{"name": "Walt Disney Pictures", "id": 2}] | O6: Walt Disney Pictures | P6: - | Q6: - | R6: - | S6: - | T6: - | U6: - | V6: - | W6: - | X6: - | Y6: - | Z6: [{"iso_3166_1": "US", "name": "United States of America"}] | AA6: 40975 | AB6: 2012 | AC6: 284139100 | AD6: 132 | AE6: [{"iso_639_1": "en", "name": "English"}] | AF6: Released | AG6: Lost in our world, found in another. | AH6: 6.1 | AI6: 2124 | AJ6: 24139100
A7: 258000000 | B7: [{ 14, name: Fantasy}, { 28, name: Action}, { 12, name: Adventure}] | C7: Fantasy | D7: Action | E7: Adventure | F7: - | G7: http://www.sonypictures.com/movies/spider-man3/ | H7: 559 | I7: Spider-Man 3 | J7: [{"id": 851, "name": "dual identity"}, {"id": 1453, "name": "amnesia"}, {"id": 1965, "name": "sandstorm"}, {"id": 2038, "name": "love of one's life"}, {"id": 3446, "name": "forgiveness"}, {"id": 3986, "name": "spider"}, {"id": 4391, "name": "wretch"}, {"id": 4959, "name": "death of a friend"}, {"id": 5776, "name": "egomania"}, {"id": 5789, "name": "sand"}, {"id": 5857, "name": "narcism"}, {"id": 6062, "name": "hostility"}, {"id": 8828, "name": "marvel comic"}, {"id": 9663, "name": "sequel"}, {"id": 9715, "name": "superhero"}, {"id": 9748, "name": "revenge"}] | K7: en | L7: The seemingly invincible Spider-Man goes up against an all-new crop of villain â€“ including the shape-shifting Sandman. While Spider-Manâ€™s superpowers are altered by an alien organism, his alter ego, Peter Parker, deals with nemesis Eddie Brock and also gets caught up in a love triangle. | M7: 115699814 | N7: [{"name": "Columbia Pictures", "id": 5}, {"name": "Laura Ziskin Productions", "id": 326}, {"name": "Marvel Enterprises", "id": 19551}] | O7: Columbia Pictures | P7: Laura Ziskin Productions | Q7: Marvel Enterprises | R7: - | S7: - | T7: - | U7: - | V7: - | W7: - | X7: - | Y7: - | Z7: [{"iso_3166_1": "US", "name": "United States of America"}] | AA7: 39203 | AB7: 2007 | AC7: 890871626 | AD7: 139 | AE7: [{"iso_639_1": "en", "name": "English"}, {"iso_639_1": "fr", "name": "Fran\u00e7ais"}] | AF7: Released | AG7: The battle within. | AH7: 5.9 | AI7: 3576 | AJ7: 632871626 | AO7: budget
A8: 260000000 | B8: [{ 16, name: Animation}, { 10751, name: Family}] | C8: Animation | D8: Family | E8: - | F8: - | G8: http://disney.go.com/disneypictures/tangled/ | H8: 38757 | I8: Tangled | J8: [{"id": 1562, "name": "hostage"}, {"id": 2343, "name": "magic"}, {"id": 2673, "name": "horse"}, {"id": 3205, "name": "fairy tale"}, {"id": 4344, "name": "musical"}, {"id": 7376, "name": "princess"}, {"id": 10336, "name": "animation"}, {"id": 33787, "name": "tower"}, {"id": 155658, "name": "blonde woman"}, {"id": 162219, "name": "selfishness"}, {"id": 163545, "name": "healing power"}, {"id": 179411, "name": "based on fairy tale"}, {"id": 179431, "name": "duringcreditsstinger"}, {"id": 215258, "name": "healing gift"}, {"id": 234183, "name": "animal sidekick"}] | K8: en | L8: When the kingdom's most wanted-and most charming-bandit Flynn Rider hides out in a mysterious tower, he's taken hostage by Rapunzel, a beautiful and feisty tower-bound teen with 70 feet of magical, golden hair. Flynn's curious captor, who's looking for her ticket out of the tower where she's been locked away for years, strikes a deal with the handsome thief and the unlikely duo sets off on an action-packed escapade, complete with a super-cop horse, an over-protective chameleon and a gruff gang of pub thugs. | M8: 48681969 | N8: [{"name": "Walt Disney Pictures", "id": 2}, {"name": "Walt Disney Animation Studios", "id": 6125}] | O8: Walt Disney Pictures | P8: Walt Disney Animation Studios | Q8: - | R8: - | S8: - | T8: - | U8: - | V8: - | W8: - | X8: - | Y8: - | Z8: [{"iso_3166_1": "US", "name": "United States of America"}] | AA8: 40506 | AB8: 2010 | AC8: 591794936 | AD8: 100 | AE8: [{"iso_639_1": "en", "name": "English"}] | AF8: Released | AG8: They're taking adventure to new lengths. | AH8: 7.4 | AI8: 3330 | AJ8: 331794936 | AO8: genres
A9: 280000000 | B9: [{ 28, name: Action}, { 12, name: Adventure}, { 878, name: Science Fiction}] | C9: Action | D9: Adventure | E9: Science Fiction | F9: - | G9: http://marvel.com/movies/movie/193/avengers_age_of_ultron | H9: 99861 | I9: Avengers: Age of Ultron | J9: [{"id": 8828, "name": "marvel comic"}, {"id": 9663, "name": "sequel"}, {"id": 9715, "name": "superhero"}, {"id": 9717, "name": "based on comic book"}, {"id": 10629, "name": "vision"}, {"id": 155030, "name": "superhero team"}, {"id": 179431, "name": "duringcreditsstinger"}, {"id": 180547, "name": "marvel cinematic universe"}, {"id": 209714, "name": "3d"}] | K9: en | L9: When Tony Stark tries to jumpstart a dormant peacekeeping program, things go awry and Earthâ€™s Mightiest Heroes are put to the ultimate test as the fate of the planet hangs in the balance. As the villainous Ultron emerges, it is up to The Avengers to stop him from enacting his terrible plans, and soon uneasy alliances and unexpected action pave the way for an epic and unique global adventure. | M9: 134279229 | N9: [{"name": "Marvel Studios", "id": 420}, {"name": "Prime Focus", "id": 15357}, {"name": "Revolution Sun Studios", "id": 76043}] | O9: Marvel Studios | P9: Prime Focus | Q9: Revolution Sun Studios | R9: - | S9: - | T9: - | U9: - | V9: - | W9: - | X9: - | Y9: - | Z9: [{"iso_3166_1": "US", "name": "United States of America"}] | AA9: 42116 | AB9: 2015 | AC9: 1405403694 | AD9: 141 | AE9: [{"iso_639_1": "en", "name": "English"}] | AF9: Released | AG9: A New Age Has Come. | AH9: 7.3 | AI9: 6767 | AJ9: 1125403694 | AO9: genre_1
A10: 250000000 | B10: [{ 12, name: Adventure}, { 14, name: Fantasy}, { 10751, name: Family}] | C10: Adventure | D10: Fantasy | E10: Family | F10: - | G10: http://harrypotter.warnerbros.com/harrypotterandthehalf-bloodprince/dvd/index.html | H10: 767 | I10: Harry Potter and the Half-Blood Prince | J10: [{"id": 616, "name": "witch"}, {"id": 2343, "name": "magic"}, {"id": 3872, "name": "broom"}, {"id": 3884, "name": "school of witchcraft"}, {"id": 6333, "name": "wizardry"}, {"id": 10164, "name": "apparition"}, {"id": 10791, "name": "teenage crush"}, {"id": 12564, "name": "werewolf"}] | K10: en | L10: As Harry begins his sixth year at Hogwarts, he discovers an old book marked as 'Property of the Half-Blood Prince', and begins to learn more about Lord Voldemort's dark past. | M10: 98885637 | N10: [{"name": "Warner Bros.", "id": 6194}, {"name": "Heyday Films", "id": 7364}] | O10: Warner Bros. | P10: Heyday Films | Q10: - | R10: - | S10: - | T10: - | U10: - | V10: - | W10: - | X10: - | Y10: - | Z10: [{"iso_3166_1": "GB", "name": "United Kingdom"}, {"iso_3166_1": "US", "name": "United States of America"}] | AA10: 40001 | AB10: 2009 | AC10: 933959197 | AD10: 153 | AE10: [{"iso_639_1": "en", "name": "English"}] | AF10: Released | AG10: Dark Secrets Revealed | AH10: 7.4 | AI10: 5293 | AJ10: 683959197 | AO10: genre_2
A11: 250000000 | B11: [{ 28, name: Action}, { 12, name: Adventure}, { 14, name: Fantasy}] | C11: Action | D11: Adventure | E11: Fantasy | F11: - | G11: http://www.batmanvsupermandawnofjustice.com/ | H11: 209112 | I11: Batman v Superman: Dawn of Justice | J11: [{"id": 849, "name": "dc comics"}, {"id": 7002, "name": "vigilante"}, {"id": 9715, "name": "superhero"}, {"id": 9717, "name": "based on comic book"}, {"id": 9748, "name": "revenge"}, {"id": 163455, "name": "super powers"}, {"id": 195242, "name": "clark kent"}, {"id": 195243, "name": "bruce wayne"}, {"id": 229266, "name": "dc extended universe"}] | K11: en | L11: Fearing the actions of a god-like Super Hero left unchecked, Gotham Cityâ€™s own formidable, forceful vigilante takes on Metropolisâ€™s most revered, modern-day savior, while the world wrestles with what sort of hero it really needs. And with Batman and Superman at war with one another, a new threat quickly arises, putting mankind in greater danger than itâ€™s ever known before. | M11: 155790452 | N11: [{"name": "DC Comics", "id": 429}, {"name": "Atlas Entertainment", "id": 507}, {"name": "Warner Bros.", "id": 6194}, {"name": "DC Entertainment", "id": 9993}, {"name": "Cruel & Unusual Films", "id": 9995}, {"name": "RatPac-Dune Entertainment", "id": 41624}] | O11: DC Comics | P11: Atlas Entertainment | Q11: Warner Bros. | R11: DC Entertainment | S11: Cruel & Unusual Films | T11: RatPac-Dune Entertainment | U11: - | V11: - | W11: - | X11: - | Y11: - | Z11: [{"iso_3166_1": "US", "name": "United States of America"}] | AA11: 42452 | AB11: 2016 | AC11: 873260194 | AD11: 151 | AE11: [{"iso_639_1": "en", "name": "English"}] | AF11: Released | AG11: Justice or revenge | AH11: 5.7 | AI11: 7004 | AJ11: 623260194 | AO11: genre_3
A12: 270000000 | B12: [{ 12, name: Adventure}, { 14, name: Fantasy}, { 28, name: Action}, { 878, name: Science Fiction}] | C12: Adventure | D12: Fantasy | E12: Action | F12: Science Fiction | G12: http://www.superman.com | H12: 1452 | I12: Superman Returns | J12: [{"id": 83, "name": "saving the world"}, {"id": 849, "name": "dc comics"}, {"id": 8872, "name": "invulnerability"}, {"id": 9663, "name": "sequel"}, {"id": 9715, "name": "superhero"}, {"id": 9717, "name": "based on comic book"}, {"id": 163420, "name": "kryptonite"}, {"id": 163455, "name": "super powers"}, {"id": 179102, "name": "superhuman strength"}, {"id": 202526, "name": "lex luthor"}] | K12: en | L12: Superman returns to discover his 5-year absence has allowed Lex Luthor to walk free, and that those he was closest too felt abandoned and have moved on. Luthor plots his ultimate revenge that could see millions killed and change the face of the planet forever, as well as ridding himself of the Man of Steel. | M12: 57925623 | N12: [{"name": "DC Comics", "id": 429}, {"name": "Legendary Pictures", "id": 923}, {"name": "Warner Bros.", "id": 6194}, {"name": "Bad Hat Harry Productions", "id": 9168}] | O12: DC Comics | P12: Legendary Pictures | Q12: Warner Bros. | R12: Bad Hat Harry Productions | S12: - | T12: - | U12: - | V12: - | W12: - | X12: - | Y12: - | Z12: [{"iso_3166_1": "US", "name": "United States of America"}] | AA12: 38896 | AB12: 2006 | AC12: 391081192 | AD12: 154 | AE12: [{"iso_639_1": "en", "name": "English"}, {"iso_639_1": "fr", "name": "Fran\u00e7ais"}, {"iso_639_1": "de", "name": "Deutsch"}] | AF12: Released | AH12: 5.4 | AI12: 1400 | AJ12: 121081192 | AO12: genre_4
A13: 200000000 | B13: [{ 12, name: Adventure}, { 28, name: Action}, { 53, name: Thriller}, { 80, name: Crime}] | C13: Adventure | D13: Action | E13: Thriller | F13: Crime | G13: http://www.mgm.com/view/movie/234/Quantum-of-Solace/ | H13: 10764 | I13: Quantum of Solace | J13: [{"id": 627, "name": "killing"}, {"id": 1568, "name": "undercover"}, {"id": 4289, "name": "secret agent"}, {"id": 156095, "name": "british secret service"}] | K13: en | L13: Quantum of Solace continues the adventures of James Bond after Casino Royale. Betrayed by Vesper, the woman he loved, 007 fights the urge to make his latest mission personal. Pursuing his determination to uncover the truth, Bond and M interrogate Mr. White, who reveals that the organization that blackmailed Vesper is far more complex and dangerous than anyone had imagined. | M13: 107928811 | N13: [{"name": "Eon Productions", "id": 7576}] | O13: Eon Productions | P13: - | Q13: - | R13: - | S13: - | T13: - | U13: - | V13: - | W13: - | X13: - | Y13: - | Z13: [{"iso_3166_1": "GB", "name": "United Kingdom"}, {"iso_3166_1": "US", "name": "United States of America"}] | AA13: 39751 | AB13: 2008 | AC13: 586090727 | AD13: 106 | AE13: [{"iso_639_1": "en", "name": "English"}, {"iso_639_1": "es", "name": "Espa\u00f1ol"}, {"iso_639_1": "it", "name": "Italiano"}, {"iso_639_1": "fr", "name": "Fran\u00e7ais"}, {"iso_639_1": "de", "name": "Deutsch"}] | AF13: Released | AG13: For love, for hate, for justice, for revenge. | AH13: 6.1 | AI13: 2965 | AJ13: 386090727 | AO13: homepage
A14: 200000000 | B14: [{ 12, name: Adventure}, { 14, name: Fantasy}, { 28, name: Action}] | C14: Adventure | D14: Fantasy | E14: Action | F14: - | G14: http://disney.go.com/disneypictures/pirates/ | H14: 58 | I14: Pirates of the Caribbean: Dead Man's Chest | J14: [{"id": 616, "name": "witch"}, {"id": 663, "name": "fortune teller"}, {"id": 910, "name": "bondage"}, {"id": 911, "name": "exotic island"}, {"id": 1299, "name": "monster"}, {"id": 1316, "name": "captain"}, {"id": 1317, "name": "card game"}, {"id": 1319, "name": "east india trading company"}, {"id": 1461, "name": "compass"}, {"id": 3799, "name": "ship"}, {"id": 5600, "name": "daughter"}, {"id": 12988, "name": "pirate"}, {"id": 157186, "name": "swashbuckler"}, {"id": 179430, "name": "aftercreditsstinger"}] | K14: en | L14: Captain Jack Sparrow works his way out of a blood debt with the ghostly Davey Jones, he also attempts to avoid eternal damnation. | M14: 145847379 | N14: [{"name": "Walt Disney Pictures", "id": 2}, {"name": "Jerry Bruckheimer Films", "id": 130}, {"name": "Second Mate Productions", "id": 19936}] | O14: Walt Disney Pictures | P14: Jerry Bruckheimer Films | Q14: Second Mate Productions | R14: - | S14: - | T14: - | U14: - | V14: - | W14: - | X14: - | Y14: - | Z14: [{"iso_3166_1": "JM", "name": "Jamaica"}, {"iso_3166_1": "US", "name": "United States of America"}, {"iso_3166_1": "BS", "name": "Bahamas"}, {"iso_3166_1": "DM", "name": "Dominica"}] | AA14: 38888 | AB14: 2006 | AC14: 1065659812 | AD14: 151 | AE14: [{"iso_639_1": "en", "name": "English"}, {"iso_639_1": "tr", "name": "T\u00fcrk\u00e7e"}, {"iso_639_1": "el", "name": "\u03b5\u03bb\u03bb\u03b7\u03bd\u03b9\u03ba\u03ac"}, {"iso_639_1": "zh", "name": "\u666e\u901a\u8bdd"}] | AF14: Released | AG14: Jack is back! | AH14: 7.0 | AI14: 5246 | AJ14: 865659812 | AO14: id
A15: 255000000 | B15: [{ 28, name: Action}, { 12, name: Adventure}, { 37, name: Western}] | C15: Action | D15: Adventure | E15: Western | F15: - | G15: http://disney.go.com/the-lone-ranger/ | H15: 57201 | I15: The Lone Ranger | J15: [{"id": 1556, "name": "texas"}, {"id": 2673, "name": "horse"}, {"id": 5385, "name": "survivor"}, {"id": 5901, "name": "texas ranger"}, {"id": 9104, "name": "partner"}, {"id": 9503, "name": "outlaw"}, {"id": 10685, "name": "escape"}, {"id": 10909, "name": "lawyer"}, {"id": 13008, "name": "train"}, {"id": 178867, "name": "lone ranger"}, {"id": 179419, "name": "comanche"}, {"id": 222787, "name": "the lone ranger"}, {"id": 228232, "name": "tonto"}] | K15: en | L15: The Texas Rangers chase down a gang of outlaws led by Butch Cavendish, but the gang ambushes the Rangers, seemingly killing them all. One survivor is found, however, by an American Indian named Tonto, who nurses him back to health. The Ranger, donning a mask and riding a white stallion named Silver, teams up with Tonto to bring the unscrupulous gang and others of that ilk to justice. | M15: 49046956 | N15: [{"name": "Walt Disney Pictures", "id": 2}, {"name": "Jerry Bruckheimer Films", "id": 130}, {"name": "Infinitum Nihil", "id": 2691}, {"name": "Silver Bullet Productions (II)", "id": 37380}, {"name": "Blind Wink Productions", "id": 37381}, {"name": "Classic Media", "id": 37382}] | O15: Walt Disney Pictures | P15: Jerry Bruckheimer Films | Q15: Infinitum Nihil | R15: Silver Bullet Productions (II) | S15: Blind Wink Productions | T15: Classic Media | U15: - | V15: - | W15: - | X15: - | Y15: - | Z15: [{"iso_3166_1": "US", "name": "United States of America"}] | AA15: 41458 | AB15: 2013 | AC15: 89289910 | AD15: 149 | AE15: [{"iso_639_1": "en", "name": "English"}] | AF15: Released | AG15: Never Take Off the Mask | AH15: 5.9 | AI15: 2311 | AJ15: -165710090 | AO15: Title
A16: 225000000 | B16: [{ 28, name: Action}, { 12, name: Adventure}, { 14, name: Fantasy}, { 878, name: Science Fiction}] | C16: Action | D16: Adventure | E16: Fantasy | F16: Science Fiction | G16: http://www.manofsteel.com/ | H16: 49521 | I16: Man of Steel | J16: [{"id": 83, "name": "saving the world"}, {"id": 849, "name": "dc comics"}, {"id": 9715, "name": "superhero"}, {"id": 9717, "name": "based on comic book"}, {"id": 10761, "name": "superhuman"}, {"id": 14909, "name": "alien invasion"}, {"id": 161184, "name": "reboot"}, {"id": 163455, "name": "super powers"}, {"id": 229266, "name": "dc extended universe"}] | K16: en | L16: A young boy learns that he has extraordinary powers and is not of this earth. As a young man, he journeys to discover where he came from and what he was sent here to do. But the hero in him must emerge if he is to save the world from annihilation and become the symbol of hope for all mankind. | M16: 99398009 | N16: [{"name": "Legendary Pictures", "id": 923}, {"name": "Warner Bros.", "id": 6194}, {"name": "DC Entertainment", "id": 9993}, {"name": "Syncopy", "id": 9996}, {"name": "Cruel and Unusual Films", "id": 78685}] | O16: Legendary Pictures | P16: Warner Bros. | Q16: DC Entertainment | R16: Syncopy | S16: Cruel and Unusual Films | T16: - | U16: - | V16: - | W16: - | X16: - | Y16: - | Z16: [{"iso_3166_1": "GB", "name": "United Kingdom"}, {"iso_3166_1": "US", "name": "United States of America"}] | AA16: 41437 | AB16: 2013 | AC16: 662845518 | AD16: 143 | AE16: [{"iso_639_1": "en", "name": "English"}] | AF16: Released | AG16: You will believe that a man can fly. | AH16: 6.5 | AI16: 6359 | AJ16: 437845518 | AO16: keywords
A17: 225000000 | B17: [{ 12, name: Adventure}, { 10751, name: Family}, { 14, name: Fantasy}] | C17: Adventure | D17: Family | E17: Fantasy | F17: - | H17: 2454 | I17: The Chronicles of Narnia: Prince Caspian | J17: [{"id": 818, "name": "based on novel"}, {"id": 855, "name": "fictional place"}, {"id": 1155, "name": "brother sister relationship"}, {"id": 2043, "name": "lion"}, {"id": 3714, "name": "human being"}, {"id": 4391, "name": "wretch"}, {"id": 4820, "name": "leap in time"}, {"id": 5144, "name": "matter of life and death"}, {"id": 6150, "name": "faith"}, {"id": 6464, "name": "uncle"}, {"id": 166930, "name": "narnia"}, {"id": 170362, "name": "fantasy world"}] | K17: en | L17: One year after their incredible adventures in the Lion, the Witch and the Wardrobe, Peter, Edmund, Lucy and Susan Pevensie return to Narnia to aid a young prince whose life has been threatened by the evil King Miraz. Now, with the help of a colorful cast of new characters, including Trufflehunter the badger and Nikabrik the dwarf, the Pevensie clan embarks on an incredible quest to ensure that Narnia is returned to its rightful heir. | M17: 53978602 | N17: [{"name": "Walt Disney", "id": 5888}, {"name": "Walden Media", "id": 10221}, {"name": "Stillking Films", "id": 11345}, {"name": "Ozumi Films", "id": 11440}, {"name": "Propeler", "id": 11441}, {"name": "Silverbell Films", "id": 11442}, {"name": "Revolution Sun Studios", "id": 76043}] | O17: Walt Disney | P17: Walden Media | Q17: Stillking Films | R17: Ozumi Films | S17: Propeler | T17: Silverbell Films | U17: Revolution Sun Studios | V17: - | W17: - | X17: - | Y17: - | Z17: [{"iso_3166_1": "CZ", "name": "Czech Republic"}, {"iso_3166_1": "PL", "name": "Poland"}, {"iso_3166_1": "SI", "name": "Slovenia"}, {"iso_3166_1": "US", "name": "United States of America"}] | AA17: 39583 | AB17: 2008 | AC17: 419651413 | AD17: 150 | AE17: [{"iso_639_1": "en", "name": "English"}] | AF17: Released | AG17: Hope has a new face. | AH17: 6.3 | AI17: 1630 | AJ17: 194651413 | AO17: original_language
A18: 220000000 | B18: [{ 878, name: Science Fiction}, { 28, name: Action}, { 12, name: Adventure}] | C18: Science Fiction | D18: Action | E18: Adventure | F18: - | G18: http://marvel.com/avengers_movie/ | H18: 24428 | I18: The Avengers | J18: [{"id": 242, "name": "new york"}, {"id": 5539, "name": "shield"}, {"id": 8828, "name": "marvel comic"}, {"id": 9715, "name": "superhero"}, {"id": 9717, "name": "based on comic book"}, {"id": 14909, "name": "alien invasion"}, {"id": 155030, "name": "superhero team"}, {"id": 179430, "name": "aftercreditsstinger"}, {"id": 179431, "name": "duringcreditsstinger"}, {"id": 180547, "name": "marvel cinematic universe"}] | K18: en | L18: When an unexpected enemy emerges and threatens global safety and security, Nick Fury, director of the international peacekeeping agency known as S.H.I.E.L.D., finds himself in need of a team to pull the world back from the brink of disaster. Spanning the globe, a daring recruitment effort begins! | M18: 144448633 | N18: [{"name": "Paramount Pictures", "id": 4}, {"name": "Marvel Studios", "id": 420}] | O18: Paramount Pictures | P18: Marvel Studios | Q18: - | R18: - | S18: - | T18: - | U18: - | V18: - | W18: - | X18: - | Y18: - | Z18: [{"iso_3166_1": "US", "name": "United States of America"}] | AA18: 41024 | AB18: 2012 | AC18: 1519557910 | AD18: 143 | AE18: [{"iso_639_1": "en", "name": "English"}] | AF18: Released | AG18: Some assembly required. | AH18: 7.4 | AI18: 11776 | AJ18: 1299557910 | AO18: overview
A19: 380000000 | B19: [{ 12, name: Adventure}, { 28, name: Action}, { 14, name: Fantasy}] | C19: Adventure | D19: Action | E19: Fantasy | F19: - | G19: http://disney.go.com/pirates/index-on-stranger-tides.html#/video/ | H19: 1865 | I19: Pirates of the Caribbean: On Stranger Tides | J19: [{"id": 658, "name": "sea"}, {"id": 1316, "name": "captain"}, {"id": 1860, "name": "mutiny"}, {"id": 1938, "name": "sword"}, {"id": 2569, "name": "prime minister"}, {"id": 3180, "name": "sailing"}, {"id": 3625, "name": "silver"}, {"id": 3799, "name": "ship"}, {"id": 4235, "name": "duke"}, {"id": 5938, "name": "mermaid"}, {"id": 12988, "name": "pirate"}, {"id": 13065, "name": "soldier"}, {"id": 14643, "name": "battle"}, {"id": 157186, "name": "swashbuckler"}, {"id": 179430, "name": "aftercreditsstinger"}, {"id": 209714, "name": "3d"}] | K19: en | L19: Captain Jack Sparrow crosses paths with a woman from his past, and he's not sure if it's love -- or if she's a ruthless con artist who's using him to find the fabled Fountain of Youth. When she forces him aboard the Queen Anne's Revenge, the ship of the formidable pirate Blackbeard, Jack finds himself on an unexpected adventure in which he doesn't know who to fear more: Blackbeard or the woman from his past. | M19: 135413856 | N19: [{"name": "Walt Disney Pictures", "id": 2}, {"name": "Jerry Bruckheimer Films", "id": 130}, {"name": "Moving Picture Company (MPC)", "id": 20478}] | O19: Walt Disney Pictures | P19: Jerry Bruckheimer Films | Q19: Moving Picture Company (MPC) | R19: - | S19: - | T19: - | U19: - | V19: - | W19: - | X19: - | Y19: - | Z19: [{"iso_3166_1": "US", "name": "United States of America"}] | AA19: 40677 | AB19: 2011 | AC19: 1045713802 | AD19: 136 | AE19: [{"iso_639_1": "en", "name": "English"}, {"iso_639_1": "es", "name": "Espa\u00f1ol"}] | AF19: Released | AG19: Live Forever Or Die Trying. | AH19: 6.4 | AI19: 4948 | AJ19: 665713802 | AO19: popularity
A20: 225000000 | B20: [{ 28, name: Action}, { 35, name: Comedy}, { 878, name: Science Fiction}] | C20: Action | D20: Comedy | E20: Science Fiction | F20: - | G20: http://www.sonypictures.com/movies/meninblack3/ | H20: 41154 | I20: Men in Black 3 | J20: [{"id": 4379, "name": "time travel"}, {"id": 5455, "name": "time machine"}, {"id": 9951, "name": "alien"}, {"id": 174915, "name": "fictional government agency"}, {"id": 185668, "name": "seeing the future"}, {"id": 208756, "name": "changing history"}] | K20: en | L20: Agents J (Will Smith) and K (Tommy Lee Jones) are back...in time. J has seen some inexplicable things in his 15 years with the Men in Black, but nothing, not even aliens, perplexes him as much as his wry, reticent partner. But when K's life and the fate of the planet are put at stake, Agent J will have to travel back in time to put things right. J discovers that there are secrets to the universe that K never told him - secrets that will reveal themselves as he teams up with the young Agent K (Josh Brolin) to save his partner, the agency, and the future of humankind. | M20: 52035179 | N20: [{"name": "Amblin Entertainment", "id": 56}, {"name": "Media Magik Entertainment", "id": 5627}, {"name": "Imagenation Abu Dhabi FZ", "id": 6736}, {"name": "Hemisphere Media Capital", "id": 9169}, {"name": "Parkes/MacDonald Productions", "id": 11084}] | O20: Amblin Entertainment | P20: Media Magik Entertainment | Q20: Imagenation Abu Dhabi FZ | R20: Hemisphere Media Capital | S20: Parkes/MacDonald Productions | T20: - | U20: - | V20: - | W20: - | X20: - | Y20: - | Z20: [{"iso_3166_1": "US", "name": "United States of America"}] | AA20: 41052 | AB20: 2012 | AC20: 624026776 | AD20: 106 | AE20: [{"iso_639_1": "en", "name": "English"}] | AF20: Released | AG20: They are back... in time. | AH20: 6.2 | AI20: 4160 | AJ20: 399026776 | AO20: production_companies
A21: 250000000 | B21: [{ 28, name: Action}, { 12, name: Adventure}, { 14, name: Fantasy}] | C21: Action | D21: Adventure | E21: Fantasy | F21: - | G21: http://www.thehobbit.com/ | H21: 122917 | I21: The Hobbit: The Battle of the Five Armies | J21: [{"id": 417, "name": "corruption"}, {"id": 603, "name": "elves"}, {"id": 604, "name": "dwarves"}, {"id": 606, "name": "orcs"}, {"id": 609, "name": "middle-earth (tolkien)"}, {"id": 611, "name": "hobbit"}, {"id": 12554, "name": "dragon"}, {"id": 14643, "name": "battle"}, {"id": 167982, "name": "unlikely friendship"}, {"id": 188270, "name": "epic battle"}, {"id": 234213, "name": "sword and sorcery"}] | K21: en | L21: Immediately after the events of The Desolation of Smaug, Bilbo and the dwarves try to defend Erebor's mountain of treasure from others who claim it: the men of the ruined Laketown and the elves of Mirkwood. Meanwhile an army of Orcs led by Azog the Defiler is marching on Erebor, fueled by the rise of the dark lord Sauron. Dwarves, elves and men must unite, and the hope for Middle-Earth falls into Bilbo's hands. | M21: 120965743 | N21: [{"name": "WingNut Films", "id": 11}, {"name": "New Line Cinema", "id": 12}, {"name": "Warner Bros. Pictures", "id": 174}, {"name": "3Foot7", "id": 7413}, {"name": "Metro-Goldwyn-Mayer (MGM)", "id": 8411}] | O21: WingNut Films | P21: New Line Cinema | Q21: Warner Bros. Pictures | R21: 3Foot7 | S21: Metro-Goldwyn-Mayer (MGM) | T21: - | U21: - | V21: - | W21: - | X21: - | Y21: - | Z21: [{"iso_3166_1": "NZ", "name": "New Zealand"}, {"iso_3166_1": "US", "name": "United States of America"}] | AA21: 41983 | AB21: 2014 | AC21: 956019788 | AD21: 144 | AE21: [{"iso_639_1": "en", "name": "English"}] | AF21: Released | AG21: Witness the defining chapter of the Middle-Earth saga | AH21: 7.1 | AI21: 4760 | AJ21: 706019788 | AO21: Companies
